{
  "Info": [
    {
      "IsSuccess": "True",
      "InAddress": "基隆市暖暖區八南里八堵路１８５巷７５、７７號",
      "InSRS": "EPSG:4326",
      "InFuzzyType": "[單雙號機制]+[最近門牌號機制]",
      "InFuzzyBuffer": "0",
      "InIsOnlyFullMatch": "False",
      "InIsLockCounty": "True",
      "InIsLockTown": "False",
      "InIsLockVillage": "False",
      "InIsLockRoadSection": "False",
      "InIsLockLane": "False",
      "InIsLockAlley": "False",
      "InIsLockArea": "False",
      "InIsSameNumber_SubNumber": "True",
      "InCanIgnoreVillage": "True",
      "InCanIgnoreNeighborhood": "True",
      "InReturnMaxCount": "0",
      "OutTotal": "3",
      "OutMatchType": "模糊比對",
      "OutMatchCode": "[基隆市]\tT:1,V:1,R:1,S:-1,L:1,A:-1,SA:-1,T:-1,AR:-1,NO:0(-7482),E:-1,N:-1",
      "OutTraceInfo": "[基隆市]\t { 模糊比對 } (暖暖區)\t找到符合的[鄉鎮市區]，(八南里)\t找到符合的[村里]，(八堵路)\t找到符合的[路街名]，(185巷)\t找到符合的[巷]，(7577號)\t找不到符合的[門牌號碼]，進行轉換搜尋[巷視為號]，進行[單號過濾]，進行[找小於且最接近的門牌號碼]，找到小於輸入的門牌號碼 -7482 號，進行[找最小門牌的號之、之號]，模糊比對找到 3 筆符合的門牌地址。"
    }
  ],
  "AddressList": [
    {
      "FULL_ADDR": "基隆市暖暖區八南里1鄰八堵路185巷95之1號",
      "COUNTY": "基隆市",
      "TOWN": "暖暖區",
      "VILLAGE": "八南里",
      "NEIGHBORHOOD": "1鄰",
      "ROAD": "八堵路",
      "SECTION": "",
      "LANE": "185巷",
      "ALLEY": "",
      "SUB_ALLEY": "",
      "TONG": "",
      "AREA": "",
      "NUMBER": "95之1號",
      "X": 121.725153,
      "Y": 25.100600
    },
    {
      "FULL_ADDR": "基隆市暖暖區八南里1鄰八堵路185巷95之2號",
      "COUNTY": "基隆市",
      "TOWN": "暖暖區",
      "VILLAGE": "八南里",
      "NEIGHBORHOOD": "1鄰",
      "ROAD": "八堵路",
      "SECTION": "",
      "LANE": "185巷",
      "ALLEY": "",
      "SUB_ALLEY": "",
      "TONG": "",
      "AREA": "",
      "NUMBER": "95之2號",
      "X": 121.725211,
      "Y": 25.100560
    },
    {
      "FULL_ADDR": "基隆市暖暖區八南里1鄰八堵路185巷95之3號",
      "COUNTY": "基隆市",
      "TOWN": "暖暖區",
      "VILLAGE": "八南里",
      "NEIGHBORHOOD": "1鄰",
      "ROAD": "八堵路",
      "SECTION": "",
      "LANE": "185巷",
      "ALLEY": "",
      "SUB_ALLEY": "",
      "TONG": "",
      "AREA": "",
      "NUMBER": "95之3號",
      "X": 121.725260,
      "Y": 25.100528
    }
  ]
}