{
  "Info": [
    {
      "IsSuccess": "True",
      "InAddress": "臺中市北屯區民政里北坑巷２１―８號",
      "InSRS": "EPSG:4326",
      "InFuzzyType": "[單雙號機制]+[最近門牌號機制]",
      "InFuzzyBuffer": "0",
      "InIsOnlyFullMatch": "False",
      "InIsLockCounty": "True",
      "InIsLockTown": "False",
      "InIsLockVillage": "False",
      "InIsLockRoadSection": "False",
      "InIsLockLane": "False",
      "InIsLockAlley": "False",
      "InIsLockArea": "False",
      "InIsSameNumber_SubNumber": "True",
      "InCanIgnoreVillage": "True",
      "InCanIgnoreNeighborhood": "True",
      "InReturnMaxCount": "0",
      "OutTotal": "21",
      "OutMatchType": "模糊比對",
      "OutMatchCode": "[臺中市]\tT:1,V:1,R:-1,S:-1,L:0,A:-1,SA:-1,T:-1,AR:0,NO:0(+4),E:-1,N:-1",
      "OutTraceInfo": "[臺中市]\t { 模糊比對 } (北屯區)\t找到符合的[鄉鎮市區]，(民政里)\t找到符合的[村里]，(北坑巷)\t找不到符合的[巷]，(二一―)\t找不到符合的[地區]，轉換搜尋找不到符合的[地區]，(8號)\t進行[雙號過濾]，進行[找大於且最接近的門牌號碼]，找到大於輸入的門牌號碼 +4 號，進行[找最小門牌的號之、之號]，模糊比對找到 21 筆符合的門牌地址。( 限制回傳 10 筆門牌地址 )"
    }
  ],
  "AddressList": [
    {
      "FULL_ADDR": "臺中市北屯區民政里1鄰北坑巷12之10號",
      "COUNTY": "臺中市",
      "TOWN": "北屯區",
      "VILLAGE": "民政里",
      "NEIGHBORHOOD": "1鄰",
      "ROAD": "",
      "SECTION": "",
      "LANE": "",
      "ALLEY": "",
      "SUB_ALLEY": "",
      "TONG": "",
      "AREA": "北坑巷",
      "NUMBER": "12之10號",
      "X": 120.742583,
      "Y": 24.166331
    },
    {
      "FULL_ADDR": "臺中市北屯區民政里1鄰北坑巷12之11號",
      "COUNTY": "臺中市",
      "TOWN": "北屯區",
      "VILLAGE": "民政里",
      "NEIGHBORHOOD": "1鄰",
      "ROAD": "",
      "SECTION": "",
      "LANE": "",
      "ALLEY": "",
      "SUB_ALLEY": "",
      "TONG": "",
      "AREA": "北坑巷",
      "NUMBER": "12之11號",
      "X": 120.742751,
      "Y": 24.165503
    },
    {
      "FULL_ADDR": "臺中市北屯區民政里1鄰北坑巷12之12號",
      "COUNTY": "臺中市",
      "TOWN": "北屯區",
      "VILLAGE": "民政里",
      "NEIGHBORHOOD": "1鄰",
      "ROAD": "",
      "SECTION": "",
      "LANE": "",
      "ALLEY": "",
      "SUB_ALLEY": "",
      "TONG": "",
      "AREA": "北坑巷",
      "NUMBER": "12之12號",
      "X": 120.742613,
      "Y": 24.165455
    },
    {
      "FULL_ADDR": "臺中市北屯區民政里1鄰北坑巷12之15號",
      "COUNTY": "臺中市",
      "TOWN": "北屯區",
      "VILLAGE": "民政里",
      "NEIGHBORHOOD": "1鄰",
      "ROAD": "",
      "SECTION": "",
      "LANE": "",
      "ALLEY": "",
      "SUB_ALLEY": "",
      "TONG": "",
      "AREA": "北坑巷",
      "NUMBER": "12之15號",
      "X": 120.742752,
      "Y": 24.165116
    },
    {
      "FULL_ADDR": "臺中市北屯區民政里1鄰北坑巷12之16號",
      "COUNTY": "臺中市",
      "TOWN": "北屯區",
      "VILLAGE": "民政里",
      "NEIGHBORHOOD": "1鄰",
      "ROAD": "",
      "SECTION": "",
      "LANE": "",
      "ALLEY": "",
      "SUB_ALLEY": "",
      "TONG": "",
      "AREA": "北坑巷",
      "NUMBER": "12之16號",
      "X": 120.742848,
      "Y": 24.165085
    },
    {
      "FULL_ADDR": "臺中市北屯區民政里1鄰北坑巷12之18號",
      "COUNTY": "臺中市",
      "TOWN": "北屯區",
      "VILLAGE": "民政里",
      "NEIGHBORHOOD": "1鄰",
      "ROAD": "",
      "SECTION": "",
      "LANE": "",
      "ALLEY": "",
      "SUB_ALLEY": "",
      "TONG": "",
      "AREA": "北坑巷",
      "NUMBER": "12之18號",
      "X": 120.743153,
      "Y": 24.164566
    },
    {
      "FULL_ADDR": "臺中市北屯區民政里1鄰北坑巷12之20號",
      "COUNTY": "臺中市",
      "TOWN": "北屯區",
      "VILLAGE": "民政里",
      "NEIGHBORHOOD": "1鄰",
      "ROAD": "",
      "SECTION": "",
      "LANE": "",
      "ALLEY": "",
      "SUB_ALLEY": "",
      "TONG": "",
      "AREA": "北坑巷",
      "NUMBER": "12之20號",
      "X": 120.740835,
      "Y": 24.165647
    },
    {
      "FULL_ADDR": "臺中市北屯區民政里1鄰北坑巷12之21號",
      "COUNTY": "臺中市",
      "TOWN": "北屯區",
      "VILLAGE": "民政里",
      "NEIGHBORHOOD": "1鄰",
      "ROAD": "",
      "SECTION": "",
      "LANE": "",
      "ALLEY": "",
      "SUB_ALLEY": "",
      "TONG": "",
      "AREA": "北坑巷",
      "NUMBER": "12之21號",
      "X": 120.741043,
      "Y": 24.165932
    },
    {
      "FULL_ADDR": "臺中市北屯區民政里1鄰北坑巷12之22號",
      "COUNTY": "臺中市",
      "TOWN": "北屯區",
      "VILLAGE": "民政里",
      "NEIGHBORHOOD": "1鄰",
      "ROAD": "",
      "SECTION": "",
      "LANE": "",
      "ALLEY": "",
      "SUB_ALLEY": "",
      "TONG": "",
      "AREA": "北坑巷",
      "NUMBER": "12之22號",
      "X": 120.741142,
      "Y": 24.166219
    },
    {
      "FULL_ADDR": "臺中市北屯區民政里1鄰北坑巷12之26號",
      "COUNTY": "臺中市",
      "TOWN": "北屯區",
      "VILLAGE": "民政里",
      "NEIGHBORHOOD": "1鄰",
      "ROAD": "",
      "SECTION": "",
      "LANE": "",
      "ALLEY": "",
      "SUB_ALLEY": "",
      "TONG": "",
      "AREA": "北坑巷",
      "NUMBER": "12之26號",
      "X": 120.741345,
      "Y": 24.165472
    }
  ]
}