{
    "name": "第一公有零售市場",
    "address": "嘉義縣竹崎鄉中山路109號",
    "x": 120.550765,
    "y": 23.521609,
    "shops": [
        {
            "shop": "第一公有零售市場-糧食",
            "pay_list": ""
        },
        {
            "shop": "第一公有零售市場-花卉",
            "pay_list": ""
        },
        {
            "shop": "第一公有零售市場-蔬果",
            "pay_list": ""
        },
        {
            "shop": "第一公有零售市場-雜貨",
            "pay_list": ""
        },
        {
            "shop": "第一公有零售市場-雜貨",
            "pay_list": ""
        },
        {
            "shop": "第一公有零售市場-禽肉",
            "pay_list": ""
        }
    ],
    "pay_list": ""
}