[{"index":1,"id":10000002,"category":"夜市小吃/市場","city":"桃園市","area":"八德區","market_name":"興仁花園夜市","market_address":"桃園市八德區長興路46號","shop":"興仁花園夜市 B8-LS美飾館","pay_list":["LINE Pay Money"],"zone":"桃竹苗","user":"李云婷","pay_tool":["行動支付"]},{"index":2,"id":10000100,"category":"夜市小吃/市場","city":"桃園市","area":"八德區","market_name":"興仁花園夜市","market_address":"桃園市八德區長興路46號","shop":"興仁花園夜市 F9.10 烤畫","pay_list":["LINE Pay Money"],"zone":"桃竹苗","user":"程圓融","pay_tool":["行動支付"]},{"index":3,"id":10000104,"category":"夜市小吃/市場","city":"桃園市","area":"八德區","market_name":"興仁花園夜市","market_address":"桃園市八德區長興路46號","shop":"興仁花園夜市 G13.14 神槍手遊戲機","pay_list":["LINE Pay Money"],"zone":"桃竹苗","user":"劉綵甄","pay_tool":["行動支付"]},{"index":4,"id":10000124,"category":"夜市小吃/市場","city":"桃園市","area":"八德區","market_name":"興仁花園夜市","market_address":"桃園市八德區長興路46號","shop":"興仁花園夜市 N5.6撈魚釣蝦","pay_list":["LINE Pay Money"],"zone":"桃竹苗","user":"徐宏智","pay_tool":["行動支付"]},{"index":5,"id":10044591,"category":"夜市小吃/市場","city":"桃園市","area":"八德區","market_name":"八德公有零售市場","market_address":"桃園市八德區建國路45號","shop":"八德公有零售市場 甲1 (相印時尚)","pay_list":["LINE Pay Money"],"zone":"桃竹苗","user":"顏佑珊","pay_tool":["行動支付"]},{"index":6,"id":10044636,"category":"夜市小吃/市場","city":"桃園市","area":"八德區","market_name":"八德公有零售市場","market_address":"桃園市八德區建國路45號","shop":"八德公有零售市場 乙05","pay_list":["LINE Pay Money"],"zone":"桃竹苗","user":"黃馨嬅","pay_tool":["行動支付"]},{"index":7,"id":10044669,"category":"夜市小吃/市場","city":"桃園市","area":"八德區","market_name":"八德公有零售市場","market_address":"桃園市八德區建國路45號","shop":"八德公有零售市場 乙08","pay_list":["LINE Pay Money"],"zone":"桃竹苗","user":"顏秀芬","pay_tool":["行動支付"]},{"index":8,"id":10044780,"category":"夜市小吃/市場","city":"桃園市","area":"八德區","market_name":"八德公有零售市場","market_address":"桃園市八德區建國路45號","shop":"八德公有零售市場 乙18 (雞世家)","pay_list":["LINE Pay Money"],"zone":"桃竹苗","user":"陳照美","pay_tool":["行動支付"]},{"index":9,"id":10044802,"category":"夜市小吃/市場","city":"桃園市","area":"八德區","market_name":"八德公有零售市場","market_address":"桃園市八德區建國路45號","shop":"八德公有零售市場 乙20 (福來禽肉店)","pay_list":["LINE Pay Money"],"zone":"桃竹苗","user":"邱月琴","pay_tool":["行動支付"]},{"index":10,"id":10044847,"category":"夜市小吃/市場","city":"桃園市","area":"八德區","market_name":"八德公有零售市場","market_address":"桃園市八德區建國路45號","shop":"八德公有零售市場 甲24 (百美商行)","pay_list":["LINE Pay Money"],"zone":"桃竹苗","user":"邱茂貴","pay_tool":["行動支付"]},{"index":11,"id":10045146,"category":"夜市小吃/市場","city":"桃園市","area":"八德區","market_name":"八德公有零售市場","market_address":"桃園市八德區建國路45號","shop":"八德公有零售市場 乙51","pay_list":["LINE Pay Money"],"zone":"桃竹苗","user":"邱元禾","pay_tool":["行動支付"]},{"index":12,"id":10046810,"category":"夜市小吃/市場","city":"桃園市","area":"八德區","market_name":"興仁花園夜市","market_address":"桃園市八德區長興路46號","shop":"興仁花園夜市 A5.6-油飯瓜仔肉飯綜合丸湯甜不辣","pay_list":["LINE Pay Money"],"zone":"桃竹苗","user":"陳正雄","pay_tool":["行動支付"]},{"index":13,"id":10046956,"category":"夜市小吃/市場","city":"桃園市","area":"八德區","market_name":"興仁花園夜市","market_address":"桃園市八德區長興路46號","shop":"興仁花園夜市 A22-豪記御鮮G","pay_list":["LINE Pay Money"],"zone":"桃竹苗","user":"邱昭童","pay_tool":["行動支付"]},{"index":14,"id":10046967,"category":"夜市小吃/市場","city":"桃園市","area":"八德區","market_name":"興仁花園夜市","market_address":"桃園市八德區長興路46號","shop":"興仁花園夜市 A23-金G母G蛋仔","pay_list":["LINE Pay Money"],"zone":"桃竹苗","user":"曾婉婷","pay_tool":["行動支付"]},{"index":15,"id":10047011,"category":"夜市小吃/市場","city":"桃園市","area":"八德區","market_name":"興仁花園夜市","market_address":"桃園市八德區長興路46號","shop":"興仁花園夜市 A27-黃金雞腿捲","pay_list":["LINE Pay Money"],"zone":"桃竹苗","user":"黃馨儀","pay_tool":["行動支付"]},{"index":16,"id":10047022,"category":"夜市小吃/市場","city":"桃園市","area":"八德區","market_name":"興仁花園夜市","market_address":"桃園市八德區長興路46號","shop":"興仁花園夜市 A28-雞BOSS?水雞","pay_list":["LINE Pay Money"],"zone":"桃竹苗","user":"黃馨儀","pay_tool":["行動支付"]},{"index":17,"id":10047033,"category":"夜市小吃/市場","city":"桃園市","area":"八德區","market_name":"興仁花園夜市","market_address":"桃園市八德區長興路46號","shop":"興仁花園夜市 A29-開心果樂園現切水果果汁果凍","pay_list":["LINE Pay Money"],"zone":"桃竹苗","user":"曾珮珊","pay_tool":["行動支付"]},{"index":18,"id":10047111,"category":"夜市小吃/市場","city":"桃園市","area":"八德區","market_name":"興仁花園夜市","market_address":"桃園市八德區長興路46號","shop":"興仁花園夜市 A37.38-柚子奶奶力屋食堂炒泡麵","pay_list":["LINE Pay Money"],"zone":"桃竹苗","user":"呂鎮宏","pay_tool":["行動支付"]},{"index":19,"id":10047133,"category":"夜市小吃/市場","city":"桃園市","area":"八德區","market_name":"興仁花園夜市","market_address":"桃園市八德區長興路46號","shop":"興仁花園夜市 B1-小丑烤馬鈴薯","pay_list":["LINE Pay Money"],"zone":"桃竹苗","user":"陳泓熹","pay_tool":["行動支付"]},{"index":20,"id":10047233,"category":"夜市小吃/市場","city":"桃園市","area":"八德區","market_name":"興仁花園夜市","market_address":"桃園市八德區長興路46號","shop":"興仁花園夜市 B13.14-何滿妹黑糖珍珠鮮奶","pay_list":["LINE Pay Money"],"zone":"桃竹苗","user":"林文正","pay_tool":["行動支付"]},{"index":21,"id":10047244,"category":"夜市小吃/市場","city":"桃園市","area":"八德區","market_name":"興仁花園夜市","market_address":"桃園市八德區長興路46號","shop":"興仁花園夜市 B15-豬桑豬血糕","pay_list":["LINE Pay Money"],"zone":"桃竹苗","user":"莊名皓","pay_tool":["行動支付"]},{"index":22,"id":10047455,"category":"夜市小吃/市場","city":"桃園市","area":"八德區","market_name":"興仁花園夜市","market_address":"桃園市八德區長興路46號","shop":"興仁花園夜市 B37.38-腸腸久久","pay_list":["LINE Pay Money"],"zone":"桃竹苗","user":"蔡祥榮","pay_tool":["行動支付"]},{"index":23,"id":10047466,"category":"夜市小吃/市場","city":"桃園市","area":"八德區","market_name":"興仁花園夜市","market_address":"桃園市八德區長興路46號","shop":"興仁花園夜市 C1-糖葫蘆西瓜汁棉花糖","pay_list":["LINE Pay Money"],"zone":"桃竹苗","user":"黃建榮","pay_tool":["行動支付"]},{"index":24,"id":10047477,"category":"夜市小吃/市場","city":"桃園市","area":"八德區","market_name":"興仁花園夜市","market_address":"桃園市八德區長興路46號","shop":"興仁花園夜市 C2-福氣狠贊芋泥球","pay_list":["LINE Pay Money"],"zone":"桃竹苗","user":"邱國權","pay_tool":["行動支付"]},{"index":25,"id":10047488,"category":"夜市小吃/市場","city":"桃園市","area":"八德區","market_name":"興仁花園夜市","market_address":"桃園市八德區長興路46號","shop":"興仁花園夜市 C5-曾師父新疆羊肉串","pay_list":["LINE Pay Money"],"zone":"桃竹苗","user":"梁瓊文","pay_tool":["行動支付"]},{"index":26,"id":10047511,"category":"夜市小吃/市場","city":"桃園市","area":"八德區","market_name":"興仁花園夜市","market_address":"桃園市八德區長興路46號","shop":"興仁花園夜市 C7-比利時鬆餅","pay_list":["LINE Pay Money"],"zone":"桃竹苗","user":"?秀琴","pay_tool":["行動支付"]},{"index":27,"id":10047611,"category":"夜市小吃/市場","city":"桃園市","area":"八德區","market_name":"興仁花園夜市","market_address":"桃園市八德區長興路46號","shop":"興仁花園夜市 C18-冰角公主茶飲","pay_list":["LINE Pay Money"],"zone":"桃竹苗","user":"吳博武","pay_tool":["行動支付"]},{"index":28,"id":10047644,"category":"夜市小吃/市場","city":"桃園市","area":"八德區","market_name":"興仁花園夜市","market_address":"桃園市八德區長興路46號","shop":"興仁花園夜市 C25-木瓜牛奶果汁","pay_list":["LINE Pay Money"],"zone":"桃竹苗","user":"游偉利","pay_tool":["行動支付"]},{"index":29,"id":10047710,"category":"夜市小吃/市場","city":"桃園市","area":"八德區","market_name":"興仁花園夜市","market_address":"桃園市八德區長興路46號","shop":"興仁花園夜市 C33-炒炒肉","pay_list":["LINE Pay Money"],"zone":"桃竹苗","user":"邱莉娟","pay_tool":["行動支付"]},{"index":30,"id":10047766,"category":"夜市小吃/市場","city":"桃園市","area":"八德區","market_name":"興仁花園夜市","market_address":"桃園市八德區長興路46號","shop":"興仁花園夜市 D1.2-芙琳卡","pay_list":["LINE Pay Money"],"zone":"桃竹苗","user":"張自伶","pay_tool":["行動支付"]},{"index":31,"id":10047777,"category":"夜市小吃/市場","city":"桃園市","area":"八德區","market_name":"興仁花園夜市","market_address":"桃園市八德區長興路46號","shop":"興仁花園夜市 DE3-7-文化牛排","pay_list":["LINE Pay Money"],"zone":"桃竹苗","user":"林莉莉","pay_tool":["行動支付"]},{"index":32,"id":10047788,"category":"夜市小吃/市場","city":"桃園市","area":"八德區","market_name":"興仁花園夜市","market_address":"桃園市八德區長興路46號","shop":"興仁花園夜市 D8菱角酥","pay_list":["LINE Pay Money"],"zone":"桃竹苗","user":"劉珊妮","pay_tool":["行動支付"]},{"index":33,"id":10047866,"category":"夜市小吃/市場","city":"桃園市","area":"八德區","market_name":"興仁花園夜市","market_address":"桃園市八德區長興路46號","shop":"興仁花園夜市 D21-24-日式涼麵，魷魚拉麵饅頭","pay_list":["LINE Pay Money"],"zone":"桃竹苗","user":"吳明聰","pay_tool":["行動支付"]},{"index":34,"id":10047877,"category":"夜市小吃/市場","city":"桃園市","area":"八德區","market_name":"興仁花園夜市","market_address":"桃園市八德區長興路46號","shop":"興仁花園夜市 D25-大上海生煎包","pay_list":["LINE Pay Money"],"zone":"桃竹苗","user":"吳順楓","pay_tool":["行動支付"]},{"index":35,"id":10047921,"category":"夜市小吃/市場","city":"桃園市","area":"八德區","market_name":"興仁花園夜市","market_address":"桃園市八德區長興路46號","shop":"興仁花園夜市 DE33-36-御品香麻辣鍋","pay_list":["LINE Pay Money"],"zone":"桃竹苗","user":"黃淑媛","pay_tool":["行動支付"]},{"index":36,"id":30000708,"category":"夜市小吃/市場","city":"桃園市","area":"八德區","market_name":"八德公有零售市場","market_address":"桃園市八德區建國路45號","shop":"八德公有零售市場 甲24 (百美商行)","pay_list":["LINE Pay Money"],"zone":"桃竹苗","user":"邱茂貴","pay_tool":["行動支付"]},{"index":37,"id":30000711,"category":"夜市小吃/市場","city":"桃園市","area":"八德區","market_name":"八德公有零售市場","market_address":"桃園市八德區建國路45號","shop":"八德公有零售市場 乙20 (福來禽肉店)","pay_list":["LINE Pay Money"],"zone":"桃竹苗","user":"邱月琴","pay_tool":["行動支付"]},{"index":38,"id":30000714,"category":"夜市小吃/市場","city":"桃園市","area":"八德區","market_name":"八德公有零售市場","market_address":"桃園市八德區建國路45號","shop":"八德公有零售市場 乙18 (雞世家)","pay_list":["LINE Pay Money"],"zone":"桃竹苗","user":"陳照美","pay_tool":["行動支付"]},{"index":39,"id":30002055,"category":"夜市小吃/市場","city":"桃園市","area":"八德區","market_name":"八德公有零售市場","market_address":"桃園市八德區建國路45號","shop":"八德公有零售市場 甲1 (相印時尚)","pay_list":["LINE Pay Money"],"zone":"桃竹苗","user":"顏佑珊","pay_tool":["行動支付"]},{"index":40,"id":30065976,"category":"夜市小吃/市場","city":"桃園市","area":"八德區","market_name":"八德公有零售市場","market_address":"桃園市八德區建國路45號","shop":"八德公有零售市場 乙05","pay_list":["LINE Pay Money"],"zone":"桃竹苗","user":"黃馨嬅","pay_tool":["行動支付"]},{"index":41,"id":30066009,"category":"夜市小吃/市場","city":"桃園市","area":"八德區","market_name":"八德公有零售市場","market_address":"桃園市八德區建國路45號","shop":"八德公有零售市場 乙08","pay_list":["LINE Pay Money"],"zone":"桃竹苗","user":"顏秀芬","pay_tool":["行動支付"]},{"index":42,"id":30066472,"category":"夜市小吃/市場","city":"桃園市","area":"八德區","market_name":"八德公有零售市場","market_address":"桃園市八德區建國路45號","shop":"八德公有零售市場 乙51","pay_list":["LINE Pay Money"],"zone":"桃竹苗","user":"邱元禾","pay_tool":["行動支付"]},{"index":43,"id":30067348,"category":"夜市小吃/市場","city":"桃園市","area":"八德區","market_name":"大湳公有零售市場","market_address":"桃園市八德區四維路.信義街","shop":"大湳公有零售市場 甲6","pay_list":["LINE Pay Money"],"zone":"桃竹苗","user":"蕭李月霞","pay_tool":["行動支付"]},{"index":44,"id":30068290,"category":"夜市小吃/市場","city":"桃園市","area":"八德區","market_name":"大湳公有零售市場","market_address":"桃園市八德區四維路.信義街","shop":"大湳公有零售市場 乙148","pay_list":["LINE Pay Money"],"zone":"桃竹苗","user":"邱垂梁","pay_tool":["行動支付"]},{"index":45,"id":30068654,"category":"夜市小吃/市場","city":"桃園市","area":"八德區","market_name":"興仁花園夜市","market_address":"桃園市八德區長興路46號","shop":"興仁花園夜市 A5.6-油飯瓜仔肉飯綜合丸湯甜不辣","pay_list":["LINE Pay Money"],"zone":"桃竹苗","user":"陳正雄","pay_tool":["行動支付"]},{"index":46,"id":30068765,"category":"夜市小吃/市場","city":"桃園市","area":"八德區","market_name":"興仁花園夜市","market_address":"桃園市八德區長興路46號","shop":"興仁花園夜市 A19-激脆王子麵起司餅起司棒起司派","pay_list":["台灣 PAY"],"zone":"桃竹苗","user":"蕭旭秀","pay_tool":["行動支付"]},{"index":47,"id":30068798,"category":"夜市小吃/市場","city":"桃園市","area":"八德區","market_name":"興仁花園夜市","market_address":"桃園市八德區長興路46號","shop":"興仁花園夜市 A22-豪記御鮮G","pay_list":["LINE Pay Money"],"zone":"桃竹苗","user":"邱昭童","pay_tool":["行動支付"]},{"index":48,"id":30068809,"category":"夜市小吃/市場","city":"桃園市","area":"八德區","market_name":"興仁花園夜市","market_address":"桃園市八德區長興路46號","shop":"興仁花園夜市 A23-金G母G蛋仔","pay_list":["LINE Pay Money"],"zone":"桃竹苗","user":"曾婉婷","pay_tool":["行動支付"]},{"index":49,"id":30068854,"category":"夜市小吃/市場","city":"桃園市","area":"八德區","market_name":"興仁花園夜市","market_address":"桃園市八德區長興路46號","shop":"興仁花園夜市 A27-黃金雞腿捲","pay_list":["LINE Pay Money"],"zone":"桃竹苗","user":"黃馨儀","pay_tool":["行動支付"]},{"index":50,"id":30068865,"category":"夜市小吃/市場","city":"桃園市","area":"八德區","market_name":"興仁花園夜市","market_address":"桃園市八德區長興路46號","shop":"興仁花園夜市 A28-雞BOSS?水雞","pay_list":["LINE Pay Money"],"zone":"桃竹苗","user":"黃馨儀","pay_tool":["行動支付"]},{"index":51,"id":30068876,"category":"夜市小吃/市場","city":"桃園市","area":"八德區","market_name":"興仁花園夜市","market_address":"桃園市八德區長興路46號","shop":"興仁花園夜市 A29-開心果樂園現切水果果汁果凍","pay_list":["LINE Pay Money"],"zone":"桃竹苗","user":"曾珮珊","pay_tool":["行動支付"]},{"index":52,"id":30068954,"category":"夜市小吃/市場","city":"桃園市","area":"八德區","market_name":"興仁花園夜市","market_address":"桃園市八德區長興路46號","shop":"興仁花園夜市 A37.38-柚子奶奶力屋食堂炒泡麵","pay_list":["LINE Pay Money"],"zone":"桃竹苗","user":"呂鎮宏","pay_tool":["行動支付"]},{"index":53,"id":30068976,"category":"夜市小吃/市場","city":"桃園市","area":"八德區","market_name":"興仁花園夜市","market_address":"桃園市八德區長興路46號","shop":"興仁花園夜市 B1-小丑烤馬鈴薯","pay_list":["LINE Pay Money"],"zone":"桃竹苗","user":"陳泓熹","pay_tool":["行動支付"]},{"index":54,"id":30069076,"category":"夜市小吃/市場","city":"桃園市","area":"八德區","market_name":"興仁花園夜市","market_address":"桃園市八德區長興路46號","shop":"興仁花園夜市 B13.14-何滿妹黑糖珍珠鮮奶","pay_list":["LINE Pay Money"],"zone":"桃竹苗","user":"林文正","pay_tool":["行動支付"]},{"index":55,"id":30069087,"category":"夜市小吃/市場","city":"桃園市","area":"八德區","market_name":"興仁花園夜市","market_address":"桃園市八德區長興路46號","shop":"興仁花園夜市 B15-豬桑豬血糕","pay_list":["LINE Pay Money"],"zone":"桃竹苗","user":"莊名皓","pay_tool":["行動支付"]},{"index":56,"id":30069253,"category":"夜市小吃/市場","city":"桃園市","area":"八德區","market_name":"興仁花園夜市","market_address":"桃園市八德區長興路46號","shop":"興仁花園夜市 B31-棉花糖彩虹冰冰淇淋雞蛋仔爆米花","pay_list":["台灣 PAY"],"zone":"桃竹苗","user":"黃涵筠","pay_tool":["行動支付"]},{"index":57,"id":30069298,"category":"夜市小吃/市場","city":"桃園市","area":"八德區","market_name":"興仁花園夜市","market_address":"桃園市八德區長興路46號","shop":"興仁花園夜市 B37.38-腸腸久久","pay_list":["LINE Pay Money"],"zone":"桃竹苗","user":"蔡祥榮","pay_tool":["行動支付"]},{"index":58,"id":30069309,"category":"夜市小吃/市場","city":"桃園市","area":"八德區","market_name":"興仁花園夜市","market_address":"桃園市八德區長興路46號","shop":"興仁花園夜市 C1-糖葫蘆西瓜汁棉花糖","pay_list":["LINE Pay Money"],"zone":"桃竹苗","user":"黃建榮","pay_tool":["行動支付"]},{"index":59,"id":30069319,"category":"夜市小吃/市場","city":"桃園市","area":"八德區","market_name":"興仁花園夜市","market_address":"桃園市八德區長興路46號","shop":"興仁花園夜市 C2-福氣狠贊芋泥球","pay_list":["LINE Pay Money"],"zone":"桃竹苗","user":"邱國權","pay_tool":["行動支付"]},{"index":60,"id":30069330,"category":"夜市小吃/市場","city":"桃園市","area":"八德區","market_name":"興仁花園夜市","market_address":"桃園市八德區長興路46號","shop":"興仁花園夜市 C5-曾師父新疆羊肉串","pay_list":["LINE Pay Money"],"zone":"桃竹苗","user":"梁瓊文","pay_tool":["行動支付"]},{"index":61,"id":30069352,"category":"夜市小吃/市場","city":"桃園市","area":"八德區","market_name":"興仁花園夜市","market_address":"桃園市八德區長興路46號","shop":"興仁花園夜市 C7-比利時鬆餅","pay_list":["LINE Pay Money"],"zone":"桃竹苗","user":"?秀琴","pay_tool":["行動支付"]},{"index":62,"id":30069416,"category":"夜市小吃/市場","city":"桃園市","area":"八德區","market_name":"興仁花園夜市","market_address":"桃園市八德區長興路46號","shop":"興仁花園夜市 C16-拉絲起司熱狗特濃起司薯條、年糕、酥炸杏鮑菇","pay_list":["台灣 PAY"],"zone":"桃竹苗","user":"馬楓婷","pay_tool":["行動支付"]},{"index":63,"id":30069433,"category":"夜市小吃/市場","city":"桃園市","area":"八德區","market_name":"興仁花園夜市","market_address":"桃園市八德區長興路46號","shop":"興仁花園夜市 C18-冰角公主茶飲","pay_list":["LINE Pay Money"],"zone":"桃竹苗","user":"吳博武","pay_tool":["行動支付"]},{"index":64,"id":30069465,"category":"夜市小吃/市場","city":"桃園市","area":"八德區","market_name":"興仁花園夜市","market_address":"桃園市八德區長興路46號","shop":"興仁花園夜市 C25-木瓜牛奶果汁","pay_list":["LINE Pay Money"],"zone":"桃竹苗","user":"游偉利","pay_tool":["行動支付"]},{"index":65,"id":30069531,"category":"夜市小吃/市場","city":"桃園市","area":"八德區","market_name":"興仁花園夜市","market_address":"桃園市八德區長興路46號","shop":"興仁花園夜市 C33-炒炒肉","pay_list":["LINE Pay Money"],"zone":"桃竹苗","user":"邱莉娟","pay_tool":["行動支付"]},{"index":66,"id":30069587,"category":"夜市小吃/市場","city":"桃園市","area":"八德區","market_name":"興仁花園夜市","market_address":"桃園市八德區長興路46號","shop":"興仁花園夜市 D1.2-芙琳卡","pay_list":["LINE Pay Money"],"zone":"桃竹苗","user":"張自伶","pay_tool":["行動支付"]},{"index":67,"id":30069598,"category":"夜市小吃/市場","city":"桃園市","area":"八德區","market_name":"興仁花園夜市","market_address":"桃園市八德區長興路46號","shop":"興仁花園夜市 DE3-7-文化牛排","pay_list":["LINE Pay Money"],"zone":"桃竹苗","user":"林莉莉","pay_tool":["行動支付"]},{"index":68,"id":30069609,"category":"夜市小吃/市場","city":"桃園市","area":"八德區","market_name":"興仁花園夜市","market_address":"桃園市八德區長興路46號","shop":"興仁花園夜市 D8菱角酥","pay_list":["LINE Pay Money"],"zone":"桃竹苗","user":"劉珊妮","pay_tool":["行動支付"]},{"index":69,"id":30069684,"category":"夜市小吃/市場","city":"桃園市","area":"八德區","market_name":"興仁花園夜市","market_address":"桃園市八德區長興路46號","shop":"興仁花園夜市 D21-24-日式涼麵/魷魚拉麵饅頭","pay_list":["LINE Pay Money"],"zone":"桃竹苗","user":"吳明聰","pay_tool":["行動支付"]},{"index":70,"id":30069695,"category":"夜市小吃/市場","city":"桃園市","area":"八德區","market_name":"興仁花園夜市","market_address":"桃園市八德區長興路46號","shop":"興仁花園夜市 D25-大上海生煎包","pay_list":["LINE Pay Money"],"zone":"桃竹苗","user":"吳順楓","pay_tool":["行動支付"]},{"index":71,"id":30069739,"category":"夜市小吃/市場","city":"桃園市","area":"八德區","market_name":"興仁花園夜市","market_address":"桃園市八德區長興路46號","shop":"興仁花園夜市 DE33-36-御品香麻辣鍋","pay_list":["LINE Pay Money"],"zone":"桃竹苗","user":"黃淑媛","pay_tool":["行動支付"]},{"index":72,"id":30069806,"category":"夜市小吃/市場","city":"桃園市","area":"八德區","market_name":"興仁花園夜市","market_address":"桃園市八德區長興路46號","shop":"興仁花園夜市 E10-脆皮甜甜圈","pay_list":["LINE Pay Money"],"zone":"桃竹苗","user":"林敏琪","pay_tool":["行動支付"]},{"index":73,"id":30069817,"category":"夜市小吃/市場","city":"桃園市","area":"八德區","market_name":"興仁花園夜市","market_address":"桃園市八德區長興路46號","shop":"興仁花園夜市 E11.12-老牛豆花嫩仙草曉諭的店","pay_list":["LINE Pay Money"],"zone":"桃竹苗","user":"陳曉諭","pay_tool":["行動支付"]},{"index":74,"id":30069872,"category":"夜市小吃/市場","city":"桃園市","area":"八德區","market_name":"興仁花園夜市","market_address":"桃園市八德區長興路46號","shop":"興仁花園夜市 E24魷魚船","pay_list":["LINE Pay Money"],"zone":"桃竹苗","user":"黃季淳","pay_tool":["行動支付"]},{"index":75,"id":30070028,"category":"夜市小吃/市場","city":"桃園市","area":"八德區","market_name":"興仁花園夜市","market_address":"桃園市八德區長興路46號","shop":"興仁花園夜市 F17泰式料理飯類、青木瓜絲","pay_list":["LINE Pay Money"],"zone":"桃竹苗","user":"張葶楀","pay_tool":["行動支付"]},{"index":76,"id":30070061,"category":"夜市小吃/市場","city":"桃園市","area":"八德區","market_name":"興仁花園夜市","market_address":"桃園市八德區長興路46號","shop":"興仁花園夜市 FG29-34牛肉湯","pay_list":["LINE Pay Money"],"zone":"桃竹苗","user":"郭柏毅","pay_tool":["行動支付"]},{"index":77,"id":30070185,"category":"夜市小吃/市場","city":"桃園市","area":"八德區","market_name":"興仁花園夜市","market_address":"桃園市八德區長興路46號","shop":"興仁花園夜市 H19.20-西瓜汁、現打果汁","pay_list":["LINE Pay Money"],"zone":"桃竹苗","user":"陳米雲","pay_tool":["行動支付"]},{"index":78,"id":30070196,"category":"夜市小吃/市場","city":"桃園市","area":"八德區","market_name":"興仁花園夜市","market_address":"桃園市八德區長興路46號","shop":"興仁花園夜市 H21-26-藥燉排骨、蚵仔煎土虱、青草茶","pay_list":["LINE Pay Money"],"zone":"桃竹苗","user":"陳米雲","pay_tool":["行動支付"]},{"index":79,"id":30070274,"category":"夜市小吃/市場","city":"桃園市","area":"八德區","market_name":"興仁花園夜市","market_address":"桃園市八德區長興路46號","shop":"興仁花園夜市 H39-微笑?子G蛋糕","pay_list":["LINE Pay Money"],"zone":"桃竹苗","user":"黃志豪","pay_tool":["行動支付"]},{"index":80,"id":30070296,"category":"夜市小吃/市場","city":"桃園市","area":"八德區","market_name":"興仁花園夜市","market_address":"桃園市八德區長興路46號","shop":"興仁花園夜市 IJ-有GO讚牛排","pay_list":["LINE Pay Money"],"zone":"桃竹苗","user":"李明政","pay_tool":["行動支付"]},{"index":81,"id":30070496,"category":"夜市小吃/市場","city":"桃園市","area":"八德區","market_name":"興仁花園夜市","market_address":"桃園市八德區長興路46號","shop":"興仁花園夜市 B8-LS美飾館","pay_list":["LINE Pay Money"],"zone":"桃竹苗","user":"李云婷","pay_tool":["行動支付"]},{"index":82,"id":30070884,"category":"夜市小吃/市場","city":"桃園市","area":"八德區","market_name":"興仁花園夜市","market_address":"桃園市八德區長興路46號","shop":"興仁花園夜市 F9.10 烤畫","pay_list":["LINE Pay Money"],"zone":"桃竹苗","user":"程圓融","pay_tool":["行動支付"]},{"index":83,"id":30070929,"category":"夜市小吃/市場","city":"桃園市","area":"八德區","market_name":"興仁花園夜市","market_address":"桃園市八德區長興路46號","shop":"興仁花園夜市 G13.14 神槍手遊戲機","pay_list":["LINE Pay Money"],"zone":"桃竹苗","user":"劉綵甄","pay_tool":["行動支付"]},{"index":84,"id":30071152,"category":"夜市小吃/市場","city":"桃園市","area":"八德區","market_name":"興仁花園夜市","market_address":"桃園市八德區長興路46號","shop":"興仁花園夜市 N5.6撈魚釣蝦","pay_list":["LINE Pay Money"],"zone":"桃竹苗","user":"徐宏智","pay_tool":["行動支付"]}]