[{"index":1,"id":10053862,"user":"龔伯賢","shop":"中興里夜市-香酥排骨","category":"夜市/市場攤販","zone":"雲嘉南","city":"臺南市","area":"永康區","market_name":"中興里夜市","market_address":"中華二路","pay_list":"","pay_tool":"","行業代號":null,"行業代號1":null,"名稱1":null,"行業代號2":null,"名稱2":null,"行業代號3":null,"名稱3":null},{"index":2,"id":10053863,"user":"侯文嘉","shop":"中興里夜市-鴨肉羹","category":"夜市/市場攤販","zone":"雲嘉南","city":"臺南市","area":"永康區","market_name":"中興里夜市","market_address":"中華二路","pay_list":"","pay_tool":"","行業代號":null,"行業代號1":null,"名稱1":null,"行業代號2":null,"名稱2":null,"行業代號3":null,"名稱3":null},{"index":3,"id":10053864,"user":"蔡清奇","shop":"中興里夜市-豆滷雞翅","category":"夜市/市場攤販","zone":"雲嘉南","city":"臺南市","area":"永康區","market_name":"中興里夜市","market_address":"中華二路","pay_list":"","pay_tool":"","行業代號":null,"行業代號1":null,"名稱1":null,"行業代號2":null,"名稱2":null,"行業代號3":null,"名稱3":null},{"index":4,"id":10053865,"user":"曾向民","shop":"中興里夜市-蜜餞糖果","category":"夜市/市場攤販","zone":"雲嘉南","city":"臺南市","area":"永康區","market_name":"中興里夜市","market_address":"中華二路","pay_list":"","pay_tool":"","行業代號":null,"行業代號1":null,"名稱1":null,"行業代號2":null,"名稱2":null,"行業代號3":null,"名稱3":null},{"index":5,"id":10053866,"user":"陳明盛","shop":"中興里夜市-地瓜球","category":"夜市/市場攤販","zone":"雲嘉南","city":"臺南市","area":"永康區","market_name":"中興里夜市","market_address":"中華二路","pay_list":"","pay_tool":"","行業代號":null,"行業代號1":null,"名稱1":null,"行業代號2":null,"名稱2":null,"行業代號3":null,"名稱3":null},{"index":6,"id":10053867,"user":"邱長守","shop":"中興里夜市-滷味","category":"夜市/市場攤販","zone":"雲嘉南","city":"臺南市","area":"永康區","market_name":"中興里夜市","market_address":"中華二路","pay_list":"","pay_tool":"","行業代號":null,"行業代號1":null,"名稱1":null,"行業代號2":null,"名稱2":null,"行業代號3":null,"名稱3":null},{"index":7,"id":10053869,"user":"陳保全","shop":"中興里夜市-肉丸","category":"夜市/市場攤販","zone":"雲嘉南","city":"臺南市","area":"永康區","market_name":"中興里夜市","market_address":"中華二路","pay_list":"","pay_tool":"","行業代號":null,"行業代號1":null,"名稱1":null,"行業代號2":null,"名稱2":null,"行業代號3":null,"名稱3":null},{"index":8,"id":10053870,"user":"曾金河","shop":"中興里夜市-豆腐雞","category":"夜市/市場攤販","zone":"雲嘉南","city":"臺南市","area":"永康區","market_name":"中興里夜市","market_address":"中華二路","pay_list":"","pay_tool":"","行業代號":null,"行業代號1":null,"名稱1":null,"行業代號2":null,"名稱2":null,"行業代號3":null,"名稱3":null},{"index":9,"id":10053871,"user":"潘建志","shop":"中興里夜市-雄記麻辣","category":"夜市/市場攤販","zone":"雲嘉南","city":"臺南市","area":"永康區","market_name":"中興里夜市","market_address":"中華二路","pay_list":"","pay_tool":"","行業代號":null,"行業代號1":null,"名稱1":null,"行業代號2":null,"名稱2":null,"行業代號3":null,"名稱3":null},{"index":10,"id":10053872,"user":"溫勝凱","shop":"中興里夜市-豆花","category":"夜市/市場攤販","zone":"雲嘉南","city":"臺南市","area":"永康區","market_name":"中興里夜市","market_address":"中華二路","pay_list":"","pay_tool":"","行業代號":null,"行業代號1":null,"名稱1":null,"行業代號2":null,"名稱2":null,"行業代號3":null,"名稱3":null},{"index":11,"id":10053873,"user":"喬繼華","shop":"中興里夜市-安得盧麵包","category":"夜市/市場攤販","zone":"雲嘉南","city":"臺南市","area":"永康區","market_name":"中興里夜市","market_address":"中華二路","pay_list":"","pay_tool":"","行業代號":null,"行業代號1":null,"名稱1":null,"行業代號2":null,"名稱2":null,"行業代號3":null,"名稱3":null},{"index":12,"id":10053874,"user":"劉春富","shop":"中興里夜市-雞蛋冰 杏仁茶","category":"夜市/市場攤販","zone":"雲嘉南","city":"臺南市","area":"永康區","market_name":"中興里夜市","market_address":"中華二路","pay_list":"","pay_tool":"","行業代號":null,"行業代號1":null,"名稱1":null,"行業代號2":null,"名稱2":null,"行業代號3":null,"名稱3":null},{"index":13,"id":10053875,"user":"李東龍","shop":"中興里夜市-手工蛋糕","category":"夜市/市場攤販","zone":"雲嘉南","city":"臺南市","area":"永康區","market_name":"中興里夜市","market_address":"中華二路","pay_list":"","pay_tool":"","行業代號":null,"行業代號1":null,"名稱1":null,"行業代號2":null,"名稱2":null,"行業代號3":null,"名稱3":null},{"index":14,"id":10053876,"user":"翁文興","shop":"中興里夜市-錄音帶","category":"夜市/市場攤販","zone":"雲嘉南","city":"臺南市","area":"永康區","market_name":"中興里夜市","market_address":"中華二路","pay_list":"","pay_tool":"","行業代號":null,"行業代號1":null,"名稱1":null,"行業代號2":null,"名稱2":null,"行業代號3":null,"名稱3":null},{"index":15,"id":10053877,"user":"陳福明","shop":"中興里夜市-白糖粿","category":"夜市/市場攤販","zone":"雲嘉南","city":"臺南市","area":"永康區","market_name":"中興里夜市","market_address":"中華二路","pay_list":"","pay_tool":"","行業代號":null,"行業代號1":null,"名稱1":null,"行業代號2":null,"名稱2":null,"行業代號3":null,"名稱3":null},{"index":16,"id":10053878,"user":"陳懋林","shop":"中興里夜市-桶仔冰 燒仙草","category":"夜市/市場攤販","zone":"雲嘉南","city":"臺南市","area":"永康區","market_name":"中興里夜市","market_address":"中華二路","pay_list":"","pay_tool":"","行業代號":null,"行業代號1":null,"名稱1":null,"行業代號2":null,"名稱2":null,"行業代號3":null,"名稱3":null},{"index":17,"id":10053881,"user":"錢存富","shop":"中興里夜市-新疆炭烤","category":"夜市/市場攤販","zone":"雲嘉南","city":"臺南市","area":"永康區","market_name":"中興里夜市","market_address":"中華二路","pay_list":"","pay_tool":"","行業代號":null,"行業代號1":null,"名稱1":null,"行業代號2":null,"名稱2":null,"行業代號3":null,"名稱3":null},{"index":18,"id":10053882,"user":"林碧照","shop":"中興里夜市-水果","category":"夜市/市場攤販","zone":"雲嘉南","city":"臺南市","area":"永康區","market_name":"中興里夜市","market_address":"中華二路","pay_list":"","pay_tool":"","行業代號":null,"行業代號1":null,"名稱1":null,"行業代號2":null,"名稱2":null,"行業代號3":null,"名稱3":null},{"index":19,"id":10053883,"user":"曾志星","shop":"中興里夜市-邱記炭烤","category":"夜市/市場攤販","zone":"雲嘉南","city":"臺南市","area":"永康區","market_name":"中興里夜市","market_address":"中華二路","pay_list":"","pay_tool":"","行業代號":null,"行業代號1":null,"名稱1":null,"行業代號2":null,"名稱2":null,"行業代號3":null,"名稱3":null},{"index":20,"id":10053884,"user":"陳其龍","shop":"中興里夜市-可莉餅","category":"夜市/市場攤販","zone":"雲嘉南","city":"臺南市","area":"永康區","market_name":"中興里夜市","market_address":"中華二路","pay_list":"","pay_tool":"","行業代號":null,"行業代號1":null,"名稱1":null,"行業代號2":null,"名稱2":null,"行業代號3":null,"名稱3":null},{"index":21,"id":10053885,"user":"陳美華","shop":"中興里夜市-煎鳥蛋","category":"夜市/市場攤販","zone":"雲嘉南","city":"臺南市","area":"永康區","market_name":"中興里夜市","market_address":"中華二路","pay_list":"","pay_tool":"","行業代號":null,"行業代號1":null,"名稱1":null,"行業代號2":null,"名稱2":null,"行業代號3":null,"名稱3":null},{"index":22,"id":10053886,"user":"李育財","shop":"中興里夜市-東山鴨頭","category":"夜市/市場攤販","zone":"雲嘉南","city":"臺南市","area":"永康區","market_name":"中興里夜市","market_address":"中華二路","pay_list":"","pay_tool":"","行業代號":null,"行業代號1":null,"名稱1":null,"行業代號2":null,"名稱2":null,"行業代號3":null,"名稱3":null},{"index":23,"id":10053887,"user":"邱萬福","shop":"中興里夜市-地瓜球","category":"夜市/市場攤販","zone":"雲嘉南","city":"臺南市","area":"永康區","market_name":"中興里夜市","market_address":"中華二路","pay_list":"","pay_tool":"","行業代號":null,"行業代號1":null,"名稱1":null,"行業代號2":null,"名稱2":null,"行業代號3":null,"名稱3":null},{"index":24,"id":10053888,"user":"黃南陞","shop":"中興里夜市-壽司","category":"夜市/市場攤販","zone":"雲嘉南","city":"臺南市","area":"永康區","market_name":"中興里夜市","market_address":"中華二路","pay_list":"","pay_tool":"","行業代號":null,"行業代號1":null,"名稱1":null,"行業代號2":null,"名稱2":null,"行業代號3":null,"名稱3":null},{"index":25,"id":10053889,"user":"范泳嫻","shop":"中興里夜市-木瓜牛奶","category":"夜市/市場攤販","zone":"雲嘉南","city":"臺南市","area":"永康區","market_name":"中興里夜市","market_address":"中華二路","pay_list":"","pay_tool":"","行業代號":null,"行業代號1":null,"名稱1":null,"行業代號2":null,"名稱2":null,"行業代號3":null,"名稱3":null},{"index":26,"id":10053890,"user":"張名路","shop":"中興里夜市-米糕","category":"夜市/市場攤販","zone":"雲嘉南","city":"臺南市","area":"永康區","market_name":"中興里夜市","market_address":"中華二路","pay_list":"","pay_tool":"","行業代號":null,"行業代號1":null,"名稱1":null,"行業代號2":null,"名稱2":null,"行業代號3":null,"名稱3":null},{"index":27,"id":10053892,"user":"汪秀娟","shop":"中興里夜市-蔥油餅","category":"夜市/市場攤販","zone":"雲嘉南","city":"臺南市","area":"永康區","market_name":"中興里夜市","market_address":"中華二路","pay_list":"","pay_tool":"","行業代號":null,"行業代號1":null,"名稱1":null,"行業代號2":null,"名稱2":null,"行業代號3":null,"名稱3":null},{"index":28,"id":10053893,"user":"郭淑芬","shop":"中興里夜市-玉米","category":"夜市/市場攤販","zone":"雲嘉南","city":"臺南市","area":"永康區","market_name":"中興里夜市","market_address":"中華二路","pay_list":"","pay_tool":"","行業代號":null,"行業代號1":null,"名稱1":null,"行業代號2":null,"名稱2":null,"行業代號3":null,"名稱3":null},{"index":29,"id":10053894,"user":"劉晉宏","shop":"中興里夜市-豆花","category":"夜市/市場攤販","zone":"雲嘉南","city":"臺南市","area":"永康區","market_name":"中興里夜市","market_address":"中華二路","pay_list":"","pay_tool":"","行業代號":null,"行業代號1":null,"名稱1":null,"行業代號2":null,"名稱2":null,"行業代號3":null,"名稱3":null},{"index":30,"id":10053895,"user":"朱春錦","shop":"中興里夜市-朱家豆乳雞","category":"夜市/市場攤販","zone":"雲嘉南","city":"臺南市","area":"永康區","market_name":"中興里夜市","market_address":"中華二路","pay_list":"","pay_tool":"","行業代號":null,"行業代號1":null,"名稱1":null,"行業代號2":null,"名稱2":null,"行業代號3":null,"名稱3":null},{"index":31,"id":10053896,"user":"吳建璋","shop":"中興里夜市-海產粥","category":"夜市/市場攤販","zone":"雲嘉南","city":"臺南市","area":"永康區","market_name":"中興里夜市","market_address":"中華二路","pay_list":"","pay_tool":"","行業代號":null,"行業代號1":null,"名稱1":null,"行業代號2":null,"名稱2":null,"行業代號3":null,"名稱3":null},{"index":32,"id":10053897,"user":"林明元","shop":"中興里夜市-小上海香酥雞","category":"夜市/市場攤販","zone":"雲嘉南","city":"臺南市","area":"永康區","market_name":"中興里夜市","market_address":"中華二路","pay_list":"","pay_tool":"","行業代號":null,"行業代號1":null,"名稱1":null,"行業代號2":null,"名稱2":null,"行業代號3":null,"名稱3":null},{"index":33,"id":10053898,"user":"呂秀琴","shop":"中興里夜市-轟炸魷魚","category":"夜市/市場攤販","zone":"雲嘉南","city":"臺南市","area":"永康區","market_name":"中興里夜市","market_address":"中華二路","pay_list":"","pay_tool":"","行業代號":null,"行業代號1":null,"名稱1":null,"行業代號2":null,"名稱2":null,"行業代號3":null,"名稱3":null},{"index":34,"id":10053899,"user":"王泉富","shop":"中興里夜市-章魚燒","category":"夜市/市場攤販","zone":"雲嘉南","city":"臺南市","area":"永康區","market_name":"中興里夜市","market_address":"中華二路","pay_list":"","pay_tool":"","行業代號":null,"行業代號1":null,"名稱1":null,"行業代號2":null,"名稱2":null,"行業代號3":null,"名稱3":null},{"index":35,"id":10053900,"user":"洪耿堂","shop":"中興里夜市-蚵仔煎","category":"夜市/市場攤販","zone":"雲嘉南","city":"臺南市","area":"永康區","market_name":"中興里夜市","market_address":"中華二路","pay_list":"","pay_tool":"","行業代號":null,"行業代號1":null,"名稱1":null,"行業代號2":null,"名稱2":null,"行業代號3":null,"名稱3":null},{"index":36,"id":10053901,"user":"陳水來","shop":"中興里夜市-紐西蘭牛排","category":"夜市/市場攤販","zone":"雲嘉南","city":"臺南市","area":"永康區","market_name":"中興里夜市","market_address":"中華二路","pay_list":"","pay_tool":"","行業代號":null,"行業代號1":null,"名稱1":null,"行業代號2":null,"名稱2":null,"行業代號3":null,"名稱3":null},{"index":37,"id":10053903,"user":"鄭水榮","shop":"中興里夜市-沙威瑪","category":"夜市/市場攤販","zone":"雲嘉南","city":"臺南市","area":"永康區","market_name":"中興里夜市","market_address":"中華二路","pay_list":"","pay_tool":"","行業代號":null,"行業代號1":null,"名稱1":null,"行業代號2":null,"名稱2":null,"行業代號3":null,"名稱3":null},{"index":38,"id":10053904,"user":"蔡淑芬","shop":"中興里夜市-牛排","category":"夜市/市場攤販","zone":"雲嘉南","city":"臺南市","area":"永康區","market_name":"中興里夜市","market_address":"中華二路","pay_list":"","pay_tool":"","行業代號":null,"行業代號1":null,"名稱1":null,"行業代號2":null,"名稱2":null,"行業代號3":null,"名稱3":null},{"index":39,"id":10053905,"user":"施金男","shop":"中興里夜市-煎餃","category":"夜市/市場攤販","zone":"雲嘉南","city":"臺南市","area":"永康區","market_name":"中興里夜市","market_address":"中華二路","pay_list":"","pay_tool":"","行業代號":null,"行業代號1":null,"名稱1":null,"行業代號2":null,"名稱2":null,"行業代號3":null,"名稱3":null},{"index":40,"id":10053906,"user":"李東龍","shop":"中興里夜市-手工燒賣","category":"夜市/市場攤販","zone":"雲嘉南","city":"臺南市","area":"永康區","market_name":"中興里夜市","market_address":"中華二路","pay_list":"","pay_tool":"","行業代號":null,"行業代號1":null,"名稱1":null,"行業代號2":null,"名稱2":null,"行業代號3":null,"名稱3":null},{"index":41,"id":10053907,"user":"方靜怡","shop":"中興里夜市-鹽水雞","category":"夜市/市場攤販","zone":"雲嘉南","city":"臺南市","area":"永康區","market_name":"中興里夜市","market_address":"中華二路","pay_list":"","pay_tool":"","行業代號":null,"行業代號1":null,"名稱1":null,"行業代號2":null,"名稱2":null,"行業代號3":null,"名稱3":null},{"index":42,"id":10053908,"user":"黃仙助","shop":"中興里夜市-無骨鳳爪","category":"夜市/市場攤販","zone":"雲嘉南","city":"臺南市","area":"永康區","market_name":"中興里夜市","market_address":"中華二路","pay_list":"","pay_tool":"","行業代號":null,"行業代號1":null,"名稱1":null,"行業代號2":null,"名稱2":null,"行業代號3":null,"名稱3":null},{"index":43,"id":10053909,"user":"王啟源","shop":"中興里夜市-湯包","category":"夜市/市場攤販","zone":"雲嘉南","city":"臺南市","area":"永康區","market_name":"中興里夜市","market_address":"中華二路","pay_list":"","pay_tool":"","行業代號":null,"行業代號1":null,"名稱1":null,"行業代號2":null,"名稱2":null,"行業代號3":null,"名稱3":null},{"index":44,"id":10053910,"user":"呂樹林","shop":"中興里夜市-海產粥","category":"夜市/市場攤販","zone":"雲嘉南","city":"臺南市","area":"永康區","market_name":"中興里夜市","market_address":"中華二路","pay_list":"","pay_tool":"","行業代號":null,"行業代號1":null,"名稱1":null,"行業代號2":null,"名稱2":null,"行業代號3":null,"名稱3":null},{"index":45,"id":10053911,"user":"李國廷","shop":"中興里夜市-芭樂","category":"夜市/市場攤販","zone":"雲嘉南","city":"臺南市","area":"永康區","market_name":"中興里夜市","market_address":"中華二路","pay_list":"","pay_tool":"","行業代號":null,"行業代號1":null,"名稱1":null,"行業代號2":null,"名稱2":null,"行業代號3":null,"名稱3":null},{"index":46,"id":10053912,"user":"陳鴻基","shop":"中興里夜市-雞腿捲","category":"夜市/市場攤販","zone":"雲嘉南","city":"臺南市","area":"永康區","market_name":"中興里夜市","market_address":"中華二路","pay_list":"","pay_tool":"","行業代號":null,"行業代號1":null,"名稱1":null,"行業代號2":null,"名稱2":null,"行業代號3":null,"名稱3":null},{"index":47,"id":10053914,"user":"蔡長叡","shop":"中興里夜市-雪淇冰","category":"夜市/市場攤販","zone":"雲嘉南","city":"臺南市","area":"永康區","market_name":"中興里夜市","market_address":"中華二路","pay_list":"","pay_tool":"","行業代號":null,"行業代號1":null,"名稱1":null,"行業代號2":null,"名稱2":null,"行業代號3":null,"名稱3":null},{"index":48,"id":10053915,"user":"郭建志","shop":"中興里夜市-廣林炭烤","category":"夜市/市場攤販","zone":"雲嘉南","city":"臺南市","area":"永康區","market_name":"中興里夜市","market_address":"中華二路","pay_list":"","pay_tool":"","行業代號":null,"行業代號1":null,"名稱1":null,"行業代號2":null,"名稱2":null,"行業代號3":null,"名稱3":null},{"index":49,"id":10053916,"user":"胡麗娟","shop":"中興里夜市-炸魷魚","category":"夜市/市場攤販","zone":"雲嘉南","city":"臺南市","area":"永康區","market_name":"中興里夜市","market_address":"中華二路","pay_list":"","pay_tool":"","行業代號":null,"行業代號1":null,"名稱1":null,"行業代號2":null,"名稱2":null,"行業代號3":null,"名稱3":null},{"index":50,"id":10053917,"user":"王致遠","shop":"中興里夜市-大腸麵線","category":"夜市/市場攤販","zone":"雲嘉南","city":"臺南市","area":"永康區","market_name":"中興里夜市","market_address":"中華二路","pay_list":"","pay_tool":"","行業代號":null,"行業代號1":null,"名稱1":null,"行業代號2":null,"名稱2":null,"行業代號3":null,"名稱3":null},{"index":51,"id":10053918,"user":"王亞倫","shop":"中興里夜市-炸魷魚","category":"夜市/市場攤販","zone":"雲嘉南","city":"臺南市","area":"永康區","market_name":"中興里夜市","market_address":"中華二路","pay_list":"","pay_tool":"","行業代號":null,"行業代號1":null,"名稱1":null,"行業代號2":null,"名稱2":null,"行業代號3":null,"名稱3":null},{"index":52,"id":10053919,"user":"呂坤皇","shop":"中興里夜市-章魚燒","category":"夜市/市場攤販","zone":"雲嘉南","city":"臺南市","area":"永康區","market_name":"中興里夜市","market_address":"中華二路","pay_list":"","pay_tool":"","行業代號":null,"行業代號1":null,"名稱1":null,"行業代號2":null,"名稱2":null,"行業代號3":null,"名稱3":null},{"index":53,"id":10053920,"user":"楊育涵","shop":"中興里夜市-雪淇冰","category":"夜市/市場攤販","zone":"雲嘉南","city":"臺南市","area":"永康區","market_name":"中興里夜市","market_address":"中華二路","pay_list":"","pay_tool":"","行業代號":null,"行業代號1":null,"名稱1":null,"行業代號2":null,"名稱2":null,"行業代號3":null,"名稱3":null},{"index":54,"id":10053921,"user":"陳佳億","shop":"中興里夜市-果汁","category":"夜市/市場攤販","zone":"雲嘉南","city":"臺南市","area":"永康區","market_name":"中興里夜市","market_address":"中華二路","pay_list":"","pay_tool":"","行業代號":null,"行業代號1":null,"名稱1":null,"行業代號2":null,"名稱2":null,"行業代號3":null,"名稱3":null},{"index":55,"id":10053922,"user":"侯錫琳","shop":"中興里夜市-內衣毛巾","category":"夜市/市場攤販","zone":"雲嘉南","city":"臺南市","area":"永康區","market_name":"中興里夜市","market_address":"中華二路","pay_list":"","pay_tool":"","行業代號":null,"行業代號1":null,"名稱1":null,"行業代號2":null,"名稱2":null,"行業代號3":null,"名稱3":null},{"index":56,"id":10053923,"user":"洪慶和","shop":"中興里夜市-蚵仔煎","category":"夜市/市場攤販","zone":"雲嘉南","city":"臺南市","area":"永康區","market_name":"中興里夜市","market_address":"中華二路","pay_list":"","pay_tool":"","行業代號":null,"行業代號1":null,"名稱1":null,"行業代號2":null,"名稱2":null,"行業代號3":null,"名稱3":null},{"index":57,"id":10053925,"user":"傅明林","shop":"中興里夜市-香腸","category":"夜市/市場攤販","zone":"雲嘉南","city":"臺南市","area":"永康區","market_name":"中興里夜市","market_address":"中華二路","pay_list":"","pay_tool":"","行業代號":null,"行業代號1":null,"名稱1":null,"行業代號2":null,"名稱2":null,"行業代號3":null,"名稱3":null},{"index":58,"id":10053926,"user":"江文泉","shop":"五王市場-江文泉","category":"夜市/市場攤販","zone":"雲嘉南","city":"臺南市","area":"永康區","market_name":"五王市場","market_address":"臺南市永康區中華二路206巷68弄25號","pay_list":"","pay_tool":"","行業代號":null,"行業代號1":null,"名稱1":null,"行業代號2":null,"名稱2":null,"行業代號3":null,"名稱3":null},{"index":59,"id":10053927,"user":"李鳳珠","shop":"五王市場-李鳳珠","category":"夜市/市場攤販","zone":"雲嘉南","city":"臺南市","area":"永康區","market_name":"五王市場","market_address":"臺南市永康區中華二路206巷68弄25號","pay_list":"","pay_tool":"","行業代號":null,"行業代號1":null,"名稱1":null,"行業代號2":null,"名稱2":null,"行業代號3":null,"名稱3":null},{"index":60,"id":10053928,"user":"洪桂華","shop":"五王市場-洪桂華","category":"夜市/市場攤販","zone":"雲嘉南","city":"臺南市","area":"永康區","market_name":"五王市場","market_address":"臺南市永康區中華二路206巷68弄25號","pay_list":"","pay_tool":"","行業代號":null,"行業代號1":null,"名稱1":null,"行業代號2":null,"名稱2":null,"行業代號3":null,"名稱3":null},{"index":61,"id":10053929,"user":"朱明賢","shop":"五王市場-朱明賢","category":"夜市/市場攤販","zone":"雲嘉南","city":"臺南市","area":"永康區","market_name":"五王市場","market_address":"臺南市永康區中華二路206巷68弄25號","pay_list":"","pay_tool":"","行業代號":null,"行業代號1":null,"名稱1":null,"行業代號2":null,"名稱2":null,"行業代號3":null,"名稱3":null},{"index":62,"id":10053930,"user":"魏振宇","shop":"永康公有零售市場-畜肉","category":"夜市/市場攤販","zone":"雲嘉南","city":"臺南市","area":"永康區","market_name":"永康公有零售市場","market_address":"台南市永康區中山南路1116巷2號","pay_list":"","pay_tool":"","行業代號":null,"行業代號1":null,"名稱1":null,"行業代號2":null,"名稱2":null,"行業代號3":null,"名稱3":null},{"index":63,"id":10053931,"user":"黃李玉梅","shop":"永康公有零售市場-青果","category":"夜市/市場攤販","zone":"雲嘉南","city":"臺南市","area":"永康區","market_name":"永康公有零售市場","market_address":"台南市永康區中山南路1116巷2號","pay_list":"","pay_tool":"","行業代號":null,"行業代號1":null,"名稱1":null,"行業代號2":null,"名稱2":null,"行業代號3":null,"名稱3":null},{"index":64,"id":10053932,"user":"李沅臻","shop":"永康公有零售市場-飲食","category":"夜市/市場攤販","zone":"雲嘉南","city":"臺南市","area":"永康區","market_name":"永康公有零售市場","market_address":"台南市永康區中山南路1116巷2號","pay_list":"","pay_tool":"","行業代號":null,"行業代號1":null,"名稱1":null,"行業代號2":null,"名稱2":null,"行業代號3":null,"名稱3":null},{"index":65,"id":10053933,"user":"吳瑞星","shop":"永康公有零售市場-飲食","category":"夜市/市場攤販","zone":"雲嘉南","city":"臺南市","area":"永康區","market_name":"永康公有零售市場","market_address":"台南市永康區中山南路1116巷2號","pay_list":"","pay_tool":"","行業代號":null,"行業代號1":null,"名稱1":null,"行業代號2":null,"名稱2":null,"行業代號3":null,"名稱3":null},{"index":66,"id":10053934,"user":"馮陳錦春","shop":"永康公有零售市場-水產","category":"夜市/市場攤販","zone":"雲嘉南","city":"臺南市","area":"永康區","market_name":"永康公有零售市場","market_address":"台南市永康區中山南路1116巷2號","pay_list":"","pay_tool":"","行業代號":null,"行業代號1":null,"名稱1":null,"行業代號2":null,"名稱2":null,"行業代號3":null,"名稱3":null},{"index":67,"id":10053936,"user":"陳宥瑾","shop":"永康公有零售市場-水產","category":"夜市/市場攤販","zone":"雲嘉南","city":"臺南市","area":"永康區","market_name":"永康公有零售市場","market_address":"台南市永康區中山南路1116巷2號","pay_list":"","pay_tool":"","行業代號":null,"行業代號1":null,"名稱1":null,"行業代號2":null,"名稱2":null,"行業代號3":null,"名稱3":null},{"index":68,"id":10053937,"user":"甘金專","shop":"永康公有零售市場-畜肉","category":"夜市/市場攤販","zone":"雲嘉南","city":"臺南市","area":"永康區","market_name":"永康公有零售市場","market_address":"台南市永康區中山南路1116巷2號","pay_list":"","pay_tool":"","行業代號":null,"行業代號1":null,"名稱1":null,"行業代號2":null,"名稱2":null,"行業代號3":null,"名稱3":null},{"index":69,"id":10053938,"user":"林金月","shop":"永康公有零售市場-畜肉","category":"夜市/市場攤販","zone":"雲嘉南","city":"臺南市","area":"永康區","market_name":"永康公有零售市場","market_address":"台南市永康區中山南路1116巷2號","pay_list":"","pay_tool":"","行業代號":null,"行業代號1":null,"名稱1":null,"行業代號2":null,"名稱2":null,"行業代號3":null,"名稱3":null},{"index":70,"id":10053939,"user":"王麗花","shop":"永康公有零售市場-水產","category":"夜市/市場攤販","zone":"雲嘉南","city":"臺南市","area":"永康區","market_name":"永康公有零售市場","market_address":"台南市永康區中山南路1116巷2號","pay_list":"","pay_tool":"","行業代號":null,"行業代號1":null,"名稱1":null,"行業代號2":null,"名稱2":null,"行業代號3":null,"名稱3":null},{"index":71,"id":10053940,"user":"黃錫川","shop":"永康公有零售市場-青果","category":"夜市/市場攤販","zone":"雲嘉南","city":"臺南市","area":"永康區","market_name":"永康公有零售市場","market_address":"台南市永康區中山南路1116巷2號","pay_list":"","pay_tool":"","行業代號":null,"行業代號1":null,"名稱1":null,"行業代號2":null,"名稱2":null,"行業代號3":null,"名稱3":null},{"index":72,"id":10053941,"user":"甘淽萓","shop":"永康公有零售市場-畜肉","category":"夜市/市場攤販","zone":"雲嘉南","city":"臺南市","area":"永康區","market_name":"永康公有零售市場","market_address":"台南市永康區中山南路1116巷2號","pay_list":"","pay_tool":"","行業代號":null,"行業代號1":null,"名稱1":null,"行業代號2":null,"名稱2":null,"行業代號3":null,"名稱3":null},{"index":73,"id":10053942,"user":"楊勝龍","shop":"永康公有零售市場-花卉","category":"夜市/市場攤販","zone":"雲嘉南","city":"臺南市","area":"永康區","market_name":"永康公有零售市場","market_address":"台南市永康區中山南路1116巷2號","pay_list":"","pay_tool":"","行業代號":null,"行業代號1":null,"名稱1":null,"行業代號2":null,"名稱2":null,"行業代號3":null,"名稱3":null},{"index":74,"id":10053943,"user":"陳永泉","shop":"永康公有零售市場-食品","category":"夜市/市場攤販","zone":"雲嘉南","city":"臺南市","area":"永康區","market_name":"永康公有零售市場","market_address":"台南市永康區中山南路1116巷2號","pay_list":"","pay_tool":"","行業代號":null,"行業代號1":null,"名稱1":null,"行業代號2":null,"名稱2":null,"行業代號3":null,"名稱3":null},{"index":75,"id":10053944,"user":"郭翰霖","shop":"永康公有零售市場-飲食","category":"夜市/市場攤販","zone":"雲嘉南","city":"臺南市","area":"永康區","market_name":"永康公有零售市場","market_address":"台南市永康區中山南路1116巷2號","pay_list":"","pay_tool":"","行業代號":null,"行業代號1":null,"名稱1":null,"行業代號2":null,"名稱2":null,"行業代號3":null,"名稱3":null},{"index":76,"id":10053945,"user":"李瑞芬","shop":"永康公有零售市場-飲食","category":"夜市/市場攤販","zone":"雲嘉南","city":"臺南市","area":"永康區","market_name":"永康公有零售市場","market_address":"台南市永康區中山南路1116巷2號","pay_list":"","pay_tool":"","行業代號":null,"行業代號1":null,"名稱1":null,"行業代號2":null,"名稱2":null,"行業代號3":null,"名稱3":null},{"index":77,"id":10053947,"user":"王俊雄","shop":"永康公有零售市場-百貨","category":"夜市/市場攤販","zone":"雲嘉南","city":"臺南市","area":"永康區","market_name":"永康公有零售市場","market_address":"台南市永康區中山南路1116巷2號","pay_list":"","pay_tool":"","行業代號":null,"行業代號1":null,"名稱1":null,"行業代號2":null,"名稱2":null,"行業代號3":null,"名稱3":null},{"index":78,"id":10053948,"user":"洪顏好","shop":"永康公有零售市場-百貨","category":"夜市/市場攤販","zone":"雲嘉南","city":"臺南市","area":"永康區","market_name":"永康公有零售市場","market_address":"台南市永康區中山南路1116巷2號","pay_list":"","pay_tool":"","行業代號":null,"行業代號1":null,"名稱1":null,"行業代號2":null,"名稱2":null,"行業代號3":null,"名稱3":null},{"index":79,"id":10053949,"user":"陳雅枝","shop":"永康公有零售市場-食品","category":"夜市/市場攤販","zone":"雲嘉南","city":"臺南市","area":"永康區","market_name":"永康公有零售市場","market_address":"台南市永康區中山南路1116巷2號","pay_list":"","pay_tool":"","行業代號":null,"行業代號1":null,"名稱1":null,"行業代號2":null,"名稱2":null,"行業代號3":null,"名稱3":null},{"index":80,"id":10053950,"user":"陳明輝","shop":"永康公有零售市場-食品","category":"夜市/市場攤販","zone":"雲嘉南","city":"臺南市","area":"永康區","market_name":"永康公有零售市場","market_address":"台南市永康區中山南路1116巷2號","pay_list":"","pay_tool":"","行業代號":null,"行業代號1":null,"名稱1":null,"行業代號2":null,"名稱2":null,"行業代號3":null,"名稱3":null},{"index":81,"id":10053951,"user":"陳玉蘭","shop":"永康公有零售市場-食品","category":"夜市/市場攤販","zone":"雲嘉南","city":"臺南市","area":"永康區","market_name":"永康公有零售市場","market_address":"台南市永康區中山南路1116巷2號","pay_list":"","pay_tool":"","行業代號":null,"行業代號1":null,"名稱1":null,"行業代號2":null,"名稱2":null,"行業代號3":null,"名稱3":null},{"index":82,"id":10053952,"user":"郭宗儒","shop":"永康公有零售市場-百貨","category":"夜市/市場攤販","zone":"雲嘉南","city":"臺南市","area":"永康區","market_name":"永康公有零售市場","market_address":"台南市永康區中山南路1116巷2號","pay_list":"","pay_tool":"","行業代號":null,"行業代號1":null,"名稱1":null,"行業代號2":null,"名稱2":null,"行業代號3":null,"名稱3":null},{"index":83,"id":10053953,"user":"張月美","shop":"永康公有零售市場-水產","category":"夜市/市場攤販","zone":"雲嘉南","city":"臺南市","area":"永康區","market_name":"永康公有零售市場","market_address":"台南市永康區中山南路1116巷2號","pay_list":"","pay_tool":"","行業代號":null,"行業代號1":null,"名稱1":null,"行業代號2":null,"名稱2":null,"行業代號3":null,"名稱3":null},{"index":84,"id":10053954,"user":"陳雅雲","shop":"永康公有零售市場-百貨","category":"夜市/市場攤販","zone":"雲嘉南","city":"臺南市","area":"永康區","market_name":"永康公有零售市場","market_address":"台南市永康區中山南路1116巷2號","pay_list":"","pay_tool":"","行業代號":null,"行業代號1":null,"名稱1":null,"行業代號2":null,"名稱2":null,"行業代號3":null,"名稱3":null},{"index":85,"id":10053955,"user":"王秀?","shop":"永康公有零售市場-水產","category":"夜市/市場攤販","zone":"雲嘉南","city":"臺南市","area":"永康區","market_name":"永康公有零售市場","market_address":"台南市永康區中山南路1116巷2號","pay_list":"","pay_tool":"","行業代號":null,"行業代號1":null,"名稱1":null,"行業代號2":null,"名稱2":null,"行業代號3":null,"名稱3":null},{"index":86,"id":10053956,"user":"張?恩","shop":"永康公有零售市場-畜肉","category":"夜市/市場攤販","zone":"雲嘉南","city":"臺南市","area":"永康區","market_name":"永康公有零售市場","market_address":"台南市永康區中山南路1116巷2號","pay_list":"","pay_tool":"","行業代號":null,"行業代號1":null,"名稱1":null,"行業代號2":null,"名稱2":null,"行業代號3":null,"名稱3":null},{"index":87,"id":10053958,"user":"林富山","shop":"永康公有零售市場-禽肉","category":"夜市/市場攤販","zone":"雲嘉南","city":"臺南市","area":"永康區","market_name":"永康公有零售市場","market_address":"台南市永康區中山南路1116巷2號","pay_list":"","pay_tool":"","行業代號":null,"行業代號1":null,"名稱1":null,"行業代號2":null,"名稱2":null,"行業代號3":null,"名稱3":null},{"index":88,"id":10053959,"user":"陳文彬","shop":"永康公有零售市場-食品","category":"夜市/市場攤販","zone":"雲嘉南","city":"臺南市","area":"永康區","market_name":"永康公有零售市場","market_address":"台南市永康區中山南路1116巷2號","pay_list":"","pay_tool":"","行業代號":null,"行業代號1":null,"名稱1":null,"行業代號2":null,"名稱2":null,"行業代號3":null,"名稱3":null},{"index":89,"id":10053960,"user":"王秀英","shop":"永康公有零售市場-百貨","category":"夜市/市場攤販","zone":"雲嘉南","city":"臺南市","area":"永康區","market_name":"永康公有零售市場","market_address":"台南市永康區中山南路1116巷2號","pay_list":"","pay_tool":"","行業代號":null,"行業代號1":null,"名稱1":null,"行業代號2":null,"名稱2":null,"行業代號3":null,"名稱3":null},{"index":90,"id":10053961,"user":"丁美雲","shop":"永康公有零售市場-水產","category":"夜市/市場攤販","zone":"雲嘉南","city":"臺南市","area":"永康區","market_name":"永康公有零售市場","market_address":"台南市永康區中山南路1116巷2號","pay_list":"","pay_tool":"","行業代號":null,"行業代號1":null,"名稱1":null,"行業代號2":null,"名稱2":null,"行業代號3":null,"名稱3":null},{"index":91,"id":10053962,"user":"蔡秀琴","shop":"永康公有零售市場-食品","category":"夜市/市場攤販","zone":"雲嘉南","city":"臺南市","area":"永康區","market_name":"永康公有零售市場","market_address":"台南市永康區中山南路1116巷2號","pay_list":"","pay_tool":"","行業代號":null,"行業代號1":null,"名稱1":null,"行業代號2":null,"名稱2":null,"行業代號3":null,"名稱3":null},{"index":92,"id":10053963,"user":"李連春","shop":"永康公有零售市場-食品","category":"夜市/市場攤販","zone":"雲嘉南","city":"臺南市","area":"永康區","market_name":"永康公有零售市場","market_address":"台南市永康區中山南路1116巷2號","pay_list":"","pay_tool":"","行業代號":null,"行業代號1":null,"名稱1":null,"行業代號2":null,"名稱2":null,"行業代號3":null,"名稱3":null},{"index":93,"id":10053964,"user":"吳錳鋒","shop":"永康公有零售市場-食品","category":"夜市/市場攤販","zone":"雲嘉南","city":"臺南市","area":"永康區","market_name":"永康公有零售市場","market_address":"台南市永康區中山南路1116巷2號","pay_list":"","pay_tool":"","行業代號":null,"行業代號1":null,"名稱1":null,"行業代號2":null,"名稱2":null,"行業代號3":null,"名稱3":null},{"index":94,"id":10053965,"user":"吳陳麗華","shop":"永康公有零售市場-食品","category":"夜市/市場攤販","zone":"雲嘉南","city":"臺南市","area":"永康區","market_name":"永康公有零售市場","market_address":"台南市永康區中山南路1116巷2號","pay_list":"","pay_tool":"","行業代號":null,"行業代號1":null,"名稱1":null,"行業代號2":null,"名稱2":null,"行業代號3":null,"名稱3":null},{"index":95,"id":10053966,"user":"魏眾丞","shop":"永康公有零售市場-飲食","category":"夜市/市場攤販","zone":"雲嘉南","city":"臺南市","area":"永康區","market_name":"永康公有零售市場","market_address":"台南市永康區中山南路1116巷2號","pay_list":"","pay_tool":"","行業代號":null,"行業代號1":null,"名稱1":null,"行業代號2":null,"名稱2":null,"行業代號3":null,"名稱3":null},{"index":96,"id":10053967,"user":"蔡進旺","shop":"永康公有零售市場-食品","category":"夜市/市場攤販","zone":"雲嘉南","city":"臺南市","area":"永康區","market_name":"永康公有零售市場","market_address":"台南市永康區中山南路1116巷2號","pay_list":"","pay_tool":"","行業代號":null,"行業代號1":null,"名稱1":null,"行業代號2":null,"名稱2":null,"行業代號3":null,"名稱3":null},{"index":97,"id":10053969,"user":"黃美蓁","shop":"永康公有零售市場-食品","category":"夜市/市場攤販","zone":"雲嘉南","city":"臺南市","area":"永康區","market_name":"永康公有零售市場","market_address":"台南市永康區中山南路1116巷2號","pay_list":"","pay_tool":"","行業代號":null,"行業代號1":null,"名稱1":null,"行業代號2":null,"名稱2":null,"行業代號3":null,"名稱3":null},{"index":98,"id":10053970,"user":"史素鈴","shop":"永康公有零售市場-蔬菜","category":"夜市/市場攤販","zone":"雲嘉南","city":"臺南市","area":"永康區","market_name":"永康公有零售市場","market_address":"台南市永康區中山南路1116巷2號","pay_list":"","pay_tool":"","行業代號":null,"行業代號1":null,"名稱1":null,"行業代號2":null,"名稱2":null,"行業代號3":null,"名稱3":null},{"index":99,"id":10053971,"user":"林敬堯","shop":"永康公有零售市場-蔬菜","category":"夜市/市場攤販","zone":"雲嘉南","city":"臺南市","area":"永康區","market_name":"永康公有零售市場","market_address":"台南市永康區中山南路1116巷2號","pay_list":"","pay_tool":"","行業代號":null,"行業代號1":null,"名稱1":null,"行業代號2":null,"名稱2":null,"行業代號3":null,"名稱3":null},{"index":100,"id":10053972,"user":"程正雄","shop":"永康公有零售市場-食品","category":"夜市/市場攤販","zone":"雲嘉南","city":"臺南市","area":"永康區","market_name":"永康公有零售市場","market_address":"台南市永康區中山南路1116巷2號","pay_list":"","pay_tool":"","行業代號":null,"行業代號1":null,"名稱1":null,"行業代號2":null,"名稱2":null,"行業代號3":null,"名稱3":null},{"index":101,"id":10053973,"user":"顏金月","shop":"永康公有零售市場-蔬菜","category":"夜市/市場攤販","zone":"雲嘉南","city":"臺南市","area":"永康區","market_name":"永康公有零售市場","market_address":"台南市永康區中山南路1116巷2號","pay_list":"","pay_tool":"","行業代號":null,"行業代號1":null,"名稱1":null,"行業代號2":null,"名稱2":null,"行業代號3":null,"名稱3":null},{"index":102,"id":10053974,"user":"林美玉","shop":"永康公有零售市場-蔬菜","category":"夜市/市場攤販","zone":"雲嘉南","city":"臺南市","area":"永康區","market_name":"永康公有零售市場","market_address":"台南市永康區中山南路1116巷2號","pay_list":"","pay_tool":"","行業代號":null,"行業代號1":null,"名稱1":null,"行業代號2":null,"名稱2":null,"行業代號3":null,"名稱3":null},{"index":103,"id":10053975,"user":"林政法","shop":"永康公有零售市場-畜肉","category":"夜市/市場攤販","zone":"雲嘉南","city":"臺南市","area":"永康區","market_name":"永康公有零售市場","market_address":"台南市永康區中山南路1116巷2號","pay_list":"","pay_tool":"","行業代號":null,"行業代號1":null,"名稱1":null,"行業代號2":null,"名稱2":null,"行業代號3":null,"名稱3":null},{"index":104,"id":10053976,"user":"陳林春鳳","shop":"永康公有零售市場-食品","category":"夜市/市場攤販","zone":"雲嘉南","city":"臺南市","area":"永康區","market_name":"永康公有零售市場","market_address":"台南市永康區中山南路1116巷2號","pay_list":"","pay_tool":"","行業代號":null,"行業代號1":null,"名稱1":null,"行業代號2":null,"名稱2":null,"行業代號3":null,"名稱3":null},{"index":105,"id":10053977,"user":"楊福仁","shop":"永康公有零售市場-水產","category":"夜市/市場攤販","zone":"雲嘉南","city":"臺南市","area":"永康區","market_name":"永康公有零售市場","market_address":"台南市永康區中山南路1116巷2號","pay_list":"","pay_tool":"","行業代號":null,"行業代號1":null,"名稱1":null,"行業代號2":null,"名稱2":null,"行業代號3":null,"名稱3":null},{"index":106,"id":10053978,"user":"董滿花","shop":"永康公有零售市場-百貨","category":"夜市/市場攤販","zone":"雲嘉南","city":"臺南市","area":"永康區","market_name":"永康公有零售市場","market_address":"台南市永康區中山南路1116巷2號","pay_list":"","pay_tool":"","行業代號":null,"行業代號1":null,"名稱1":null,"行業代號2":null,"名稱2":null,"行業代號3":null,"名稱3":null},{"index":107,"id":10053980,"user":"吳謝秀琴","shop":"永康公有零售市場-百貨","category":"夜市/市場攤販","zone":"雲嘉南","city":"臺南市","area":"永康區","market_name":"永康公有零售市場","market_address":"台南市永康區中山南路1116巷2號","pay_list":"","pay_tool":"","行業代號":null,"行業代號1":null,"名稱1":null,"行業代號2":null,"名稱2":null,"行業代號3":null,"名稱3":null},{"index":108,"id":10053981,"user":"楊敬修","shop":"永康公有零售市場-食品","category":"夜市/市場攤販","zone":"雲嘉南","city":"臺南市","area":"永康區","market_name":"永康公有零售市場","market_address":"台南市永康區中山南路1116巷2號","pay_list":"","pay_tool":"","行業代號":null,"行業代號1":null,"名稱1":null,"行業代號2":null,"名稱2":null,"行業代號3":null,"名稱3":null},{"index":109,"id":10053982,"user":"鄭勝發","shop":"永康公有零售市場-食品","category":"夜市/市場攤販","zone":"雲嘉南","city":"臺南市","area":"永康區","market_name":"永康公有零售市場","market_address":"台南市永康區中山南路1116巷2號","pay_list":"","pay_tool":"","行業代號":null,"行業代號1":null,"名稱1":null,"行業代號2":null,"名稱2":null,"行業代號3":null,"名稱3":null},{"index":110,"id":10053983,"user":"蔡林春月","shop":"永康公有零售市場-食品","category":"夜市/市場攤販","zone":"雲嘉南","city":"臺南市","area":"永康區","market_name":"永康公有零售市場","market_address":"台南市永康區中山南路1116巷2號","pay_list":"","pay_tool":"","行業代號":null,"行業代號1":null,"名稱1":null,"行業代號2":null,"名稱2":null,"行業代號3":null,"名稱3":null},{"index":111,"id":10053984,"user":"王秉宏","shop":"永康公有零售市場-魚蝦","category":"夜市/市場攤販","zone":"雲嘉南","city":"臺南市","area":"永康區","market_name":"永康公有零售市場","market_address":"台南市永康區中山南路1116巷2號","pay_list":"","pay_tool":"","行業代號":null,"行業代號1":null,"名稱1":null,"行業代號2":null,"名稱2":null,"行業代號3":null,"名稱3":null},{"index":112,"id":10053985,"user":"陳順利","shop":"永康公有零售市場-食品","category":"夜市/市場攤販","zone":"雲嘉南","city":"臺南市","area":"永康區","market_name":"永康公有零售市場","market_address":"台南市永康區中山南路1116巷2號","pay_list":"","pay_tool":"","行業代號":null,"行業代號1":null,"名稱1":null,"行業代號2":null,"名稱2":null,"行業代號3":null,"名稱3":null},{"index":113,"id":10053986,"user":"陳永裕","shop":"永康公有零售市場-禽肉","category":"夜市/市場攤販","zone":"雲嘉南","city":"臺南市","area":"永康區","market_name":"永康公有零售市場","market_address":"台南市永康區中山南路1116巷2號","pay_list":"","pay_tool":"","行業代號":null,"行業代號1":null,"名稱1":null,"行業代號2":null,"名稱2":null,"行業代號3":null,"名稱3":null},{"index":114,"id":10053987,"user":"陳永昌","shop":"永康公有零售市場-農產加工品","category":"夜市/市場攤販","zone":"雲嘉南","city":"臺南市","area":"永康區","market_name":"永康公有零售市場","market_address":"台南市永康區中山南路1116巷2號","pay_list":"","pay_tool":"","行業代號":null,"行業代號1":null,"名稱1":null,"行業代號2":null,"名稱2":null,"行業代號3":null,"名稱3":null},{"index":115,"id":10053988,"user":"李榮發","shop":"永康公有零售市場-畜肉","category":"夜市/市場攤販","zone":"雲嘉南","city":"臺南市","area":"永康區","market_name":"永康公有零售市場","market_address":"台南市永康區中山南路1116巷2號","pay_list":"","pay_tool":"","行業代號":null,"行業代號1":null,"名稱1":null,"行業代號2":null,"名稱2":null,"行業代號3":null,"名稱3":null},{"index":116,"id":10053989,"user":"陳李金針","shop":"永康公有零售市場-農產加工品","category":"夜市/市場攤販","zone":"雲嘉南","city":"臺南市","area":"永康區","market_name":"永康公有零售市場","market_address":"台南市永康區中山南路1116巷2號","pay_list":"","pay_tool":"","行業代號":null,"行業代號1":null,"名稱1":null,"行業代號2":null,"名稱2":null,"行業代號3":null,"名稱3":null},{"index":117,"id":10053992,"user":"陳明發","shop":"永康公有零售市場-百貨","category":"夜市/市場攤販","zone":"雲嘉南","city":"臺南市","area":"永康區","market_name":"永康公有零售市場","market_address":"台南市永康區中山南路1116巷2號","pay_list":"","pay_tool":"","行業代號":null,"行業代號1":null,"名稱1":null,"行業代號2":null,"名稱2":null,"行業代號3":null,"名稱3":null},{"index":118,"id":10053993,"user":"薛志忠","shop":"永康公有零售市場-食品","category":"夜市/市場攤販","zone":"雲嘉南","city":"臺南市","area":"永康區","market_name":"永康公有零售市場","market_address":"台南市永康區中山南路1116巷2號","pay_list":"","pay_tool":"","行業代號":null,"行業代號1":null,"名稱1":null,"行業代號2":null,"名稱2":null,"行業代號3":null,"名稱3":null},{"index":119,"id":10053994,"user":"鄭玉花","shop":"永康公有零售市場-食品","category":"夜市/市場攤販","zone":"雲嘉南","city":"臺南市","area":"永康區","market_name":"永康公有零售市場","market_address":"台南市永康區中山南路1116巷2號","pay_list":"","pay_tool":"","行業代號":null,"行業代號1":null,"名稱1":null,"行業代號2":null,"名稱2":null,"行業代號3":null,"名稱3":null},{"index":120,"id":10053995,"user":"陳春德","shop":"永康公有零售市場-百貨","category":"夜市/市場攤販","zone":"雲嘉南","city":"臺南市","area":"永康區","market_name":"永康公有零售市場","market_address":"台南市永康區中山南路1116巷2號","pay_list":"","pay_tool":"","行業代號":null,"行業代號1":null,"名稱1":null,"行業代號2":null,"名稱2":null,"行業代號3":null,"名稱3":null},{"index":121,"id":10053996,"user":"葉楊雪","shop":"永康公有零售市場-食品","category":"夜市/市場攤販","zone":"雲嘉南","city":"臺南市","area":"永康區","market_name":"永康公有零售市場","market_address":"台南市永康區中山南路1116巷2號","pay_list":"","pay_tool":"","行業代號":null,"行業代號1":null,"名稱1":null,"行業代號2":null,"名稱2":null,"行業代號3":null,"名稱3":null},{"index":122,"id":10053997,"user":"林招岑","shop":"永康公有零售市場-百貨","category":"夜市/市場攤販","zone":"雲嘉南","city":"臺南市","area":"永康區","market_name":"永康公有零售市場","market_address":"台南市永康區中山南路1116巷2號","pay_list":"","pay_tool":"","行業代號":null,"行業代號1":null,"名稱1":null,"行業代號2":null,"名稱2":null,"行業代號3":null,"名稱3":null},{"index":123,"id":10053998,"user":"王裕隆","shop":"永康公有零售市場-百貨","category":"夜市/市場攤販","zone":"雲嘉南","city":"臺南市","area":"永康區","market_name":"永康公有零售市場","market_address":"台南市永康區中山南路1116巷2號","pay_list":"","pay_tool":"","行業代號":null,"行業代號1":null,"名稱1":null,"行業代號2":null,"名稱2":null,"行業代號3":null,"名稱3":null},{"index":124,"id":10053999,"user":"陳政壹","shop":"永康公有零售市場-蔬菜","category":"夜市/市場攤販","zone":"雲嘉南","city":"臺南市","area":"永康區","market_name":"永康公有零售市場","market_address":"台南市永康區中山南路1116巷2號","pay_list":"","pay_tool":"","行業代號":null,"行業代號1":null,"名稱1":null,"行業代號2":null,"名稱2":null,"行業代號3":null,"名稱3":null},{"index":125,"id":10054000,"user":"王月娥","shop":"永康公有零售市場-蔬菜","category":"夜市/市場攤販","zone":"雲嘉南","city":"臺南市","area":"永康區","market_name":"永康公有零售市場","market_address":"台南市永康區中山南路1116巷2號","pay_list":"","pay_tool":"","行業代號":null,"行業代號1":null,"名稱1":null,"行業代號2":null,"名稱2":null,"行業代號3":null,"名稱3":null},{"index":126,"id":10054001,"user":"黃俊士","shop":"永康公有零售市場-食品","category":"夜市/市場攤販","zone":"雲嘉南","city":"臺南市","area":"永康區","market_name":"永康公有零售市場","market_address":"台南市永康區中山南路1116巷2號","pay_list":"","pay_tool":"","行業代號":null,"行業代號1":null,"名稱1":null,"行業代號2":null,"名稱2":null,"行業代號3":null,"名稱3":null},{"index":127,"id":10054003,"user":"丁雅薇","shop":"永康公有零售市場-食品","category":"夜市/市場攤販","zone":"雲嘉南","city":"臺南市","area":"永康區","market_name":"永康公有零售市場","market_address":"台南市永康區中山南路1116巷2號","pay_list":"","pay_tool":"","行業代號":null,"行業代號1":null,"名稱1":null,"行業代號2":null,"名稱2":null,"行業代號3":null,"名稱3":null},{"index":128,"id":10054004,"user":"曾基財","shop":"永康公有零售市場-蔬菜","category":"夜市/市場攤販","zone":"雲嘉南","city":"臺南市","area":"永康區","market_name":"永康公有零售市場","market_address":"台南市永康區中山南路1116巷2號","pay_list":"","pay_tool":"","行業代號":null,"行業代號1":null,"名稱1":null,"行業代號2":null,"名稱2":null,"行業代號3":null,"名稱3":null},{"index":129,"id":10054005,"user":"黃素真","shop":"永康公有零售市場-飲食","category":"夜市/市場攤販","zone":"雲嘉南","city":"臺南市","area":"永康區","market_name":"永康公有零售市場","market_address":"台南市永康區中山南路1116巷2號","pay_list":"","pay_tool":"","行業代號":null,"行業代號1":null,"名稱1":null,"行業代號2":null,"名稱2":null,"行業代號3":null,"名稱3":null},{"index":130,"id":10054006,"user":"李佳雯","shop":"永康公有零售市場-飲食","category":"夜市/市場攤販","zone":"雲嘉南","city":"臺南市","area":"永康區","market_name":"永康公有零售市場","market_address":"台南市永康區中山南路1116巷2號","pay_list":"","pay_tool":"","行業代號":null,"行業代號1":null,"名稱1":null,"行業代號2":null,"名稱2":null,"行業代號3":null,"名稱3":null},{"index":131,"id":10054007,"user":"陳謝月珠","shop":"永康公有零售市場-蔬菜","category":"夜市/市場攤販","zone":"雲嘉南","city":"臺南市","area":"永康區","market_name":"永康公有零售市場","market_address":"台南市永康區中山南路1116巷2號","pay_list":"","pay_tool":"","行業代號":null,"行業代號1":null,"名稱1":null,"行業代號2":null,"名稱2":null,"行業代號3":null,"名稱3":null},{"index":132,"id":10054008,"user":"陳志清","shop":"永康公有零售市場-蔬菜","category":"夜市/市場攤販","zone":"雲嘉南","city":"臺南市","area":"永康區","market_name":"永康公有零售市場","market_address":"台南市永康區中山南路1116巷2號","pay_list":"","pay_tool":"","行業代號":null,"行業代號1":null,"名稱1":null,"行業代號2":null,"名稱2":null,"行業代號3":null,"名稱3":null},{"index":133,"id":10054009,"user":"葉韋廷","shop":"永康公有零售市場-蔬菜","category":"夜市/市場攤販","zone":"雲嘉南","city":"臺南市","area":"永康區","market_name":"永康公有零售市場","market_address":"台南市永康區中山南路1116巷2號","pay_list":"","pay_tool":"","行業代號":null,"行業代號1":null,"名稱1":null,"行業代號2":null,"名稱2":null,"行業代號3":null,"名稱3":null},{"index":134,"id":10054010,"user":"林秀琴","shop":"永康公有零售市場-蔬菜","category":"夜市/市場攤販","zone":"雲嘉南","city":"臺南市","area":"永康區","market_name":"永康公有零售市場","market_address":"台南市永康區中山南路1116巷2號","pay_list":"","pay_tool":"","行業代號":null,"行業代號1":null,"名稱1":null,"行業代號2":null,"名稱2":null,"行業代號3":null,"名稱3":null},{"index":135,"id":10054011,"user":"林碧珠","shop":"永康公有零售市場-蔬菜","category":"夜市/市場攤販","zone":"雲嘉南","city":"臺南市","area":"永康區","market_name":"永康公有零售市場","market_address":"台南市永康區中山南路1116巷2號","pay_list":"","pay_tool":"","行業代號":null,"行業代號1":null,"名稱1":null,"行業代號2":null,"名稱2":null,"行業代號3":null,"名稱3":null},{"index":136,"id":10054012,"user":"郭吳秀子","shop":"永康公有零售市場-禽肉","category":"夜市/市場攤販","zone":"雲嘉南","city":"臺南市","area":"永康區","market_name":"永康公有零售市場","market_address":"台南市永康區中山南路1116巷2號","pay_list":"","pay_tool":"","行業代號":null,"行業代號1":null,"名稱1":null,"行業代號2":null,"名稱2":null,"行業代號3":null,"名稱3":null},{"index":137,"id":10054014,"user":"林秀治","shop":"永康公有零售市場-青果","category":"夜市/市場攤販","zone":"雲嘉南","city":"臺南市","area":"永康區","market_name":"永康公有零售市場","market_address":"台南市永康區中山南路1116巷2號","pay_list":"","pay_tool":"","行業代號":null,"行業代號1":null,"名稱1":null,"行業代號2":null,"名稱2":null,"行業代號3":null,"名稱3":null},{"index":138,"id":10054015,"user":"梁林玉換","shop":"永康公有零售市場-食品","category":"夜市/市場攤販","zone":"雲嘉南","city":"臺南市","area":"永康區","market_name":"永康公有零售市場","market_address":"台南市永康區中山南路1116巷2號","pay_list":"","pay_tool":"","行業代號":null,"行業代號1":null,"名稱1":null,"行業代號2":null,"名稱2":null,"行業代號3":null,"名稱3":null},{"index":139,"id":10054016,"user":"莊清裕","shop":"永康公有零售市場-飲食","category":"夜市/市場攤販","zone":"雲嘉南","city":"臺南市","area":"永康區","market_name":"永康公有零售市場","market_address":"台南市永康區中山南路1116巷2號","pay_list":"","pay_tool":"","行業代號":null,"行業代號1":null,"名稱1":null,"行業代號2":null,"名稱2":null,"行業代號3":null,"名稱3":null},{"index":140,"id":10054017,"user":"郭明山","shop":"永康公有零售市場-飲食","category":"夜市/市場攤販","zone":"雲嘉南","city":"臺南市","area":"永康區","market_name":"永康公有零售市場","market_address":"台南市永康區中山南路1116巷2號","pay_list":"","pay_tool":"","行業代號":null,"行業代號1":null,"名稱1":null,"行業代號2":null,"名稱2":null,"行業代號3":null,"名稱3":null},{"index":141,"id":10054018,"user":"林陳玉秀","shop":"永康公有零售市場-水產","category":"夜市/市場攤販","zone":"雲嘉南","city":"臺南市","area":"永康區","market_name":"永康公有零售市場","market_address":"台南市永康區中山南路1116巷2號","pay_list":"","pay_tool":"","行業代號":null,"行業代號1":null,"名稱1":null,"行業代號2":null,"名稱2":null,"行業代號3":null,"名稱3":null},{"index":142,"id":10054019,"user":"郭美祝","shop":"永康公有零售市場-食品","category":"夜市/市場攤販","zone":"雲嘉南","city":"臺南市","area":"永康區","market_name":"永康公有零售市場","market_address":"台南市永康區中山南路1116巷2號","pay_list":"","pay_tool":"","行業代號":null,"行業代號1":null,"名稱1":null,"行業代號2":null,"名稱2":null,"行業代號3":null,"名稱3":null},{"index":143,"id":10054020,"user":"張水木","shop":"永康公有零售市場-飲食","category":"夜市/市場攤販","zone":"雲嘉南","city":"臺南市","area":"永康區","market_name":"永康公有零售市場","market_address":"台南市永康區中山南路1116巷2號","pay_list":"","pay_tool":"","行業代號":null,"行業代號1":null,"名稱1":null,"行業代號2":null,"名稱2":null,"行業代號3":null,"名稱3":null},{"index":144,"id":10054021,"user":"郭秀梅","shop":"永康公有零售市場-飲食","category":"夜市/市場攤販","zone":"雲嘉南","city":"臺南市","area":"永康區","market_name":"永康公有零售市場","market_address":"台南市永康區中山南路1116巷2號","pay_list":"","pay_tool":"","行業代號":null,"行業代號1":null,"名稱1":null,"行業代號2":null,"名稱2":null,"行業代號3":null,"名稱3":null},{"index":145,"id":10054022,"user":"林邵秀香","shop":"永康公有零售市場-飲食","category":"夜市/市場攤販","zone":"雲嘉南","city":"臺南市","area":"永康區","market_name":"永康公有零售市場","market_address":"台南市永康區中山南路1116巷2號","pay_list":"","pay_tool":"","行業代號":null,"行業代號1":null,"名稱1":null,"行業代號2":null,"名稱2":null,"行業代號3":null,"名稱3":null},{"index":146,"id":10054023,"user":"陳沛妤","shop":"永康公有零售市場-飲食","category":"夜市/市場攤販","zone":"雲嘉南","city":"臺南市","area":"永康區","market_name":"永康公有零售市場","market_address":"台南市永康區中山南路1116巷2號","pay_list":"","pay_tool":"","行業代號":null,"行業代號1":null,"名稱1":null,"行業代號2":null,"名稱2":null,"行業代號3":null,"名稱3":null},{"index":147,"id":10054025,"user":"許智堯","shop":"復華夜市-地瓜球","category":"夜市/市場攤販","zone":"雲嘉南","city":"臺南市","area":"永康區","market_name":"復華夜市","market_address":"復國一路與復華三街交叉口廣場","pay_list":"","pay_tool":"","行業代號":null,"行業代號1":null,"名稱1":null,"行業代號2":null,"名稱2":null,"行業代號3":null,"名稱3":null},{"index":148,"id":10054026,"user":"鄭榮男","shop":"復華夜市-蚵仔煎","category":"夜市/市場攤販","zone":"雲嘉南","city":"臺南市","area":"永康區","market_name":"復華夜市","market_address":"復國一路與復華三街交叉口廣場","pay_list":"","pay_tool":"","行業代號":null,"行業代號1":null,"名稱1":null,"行業代號2":null,"名稱2":null,"行業代號3":null,"名稱3":null},{"index":149,"id":10054027,"user":"黃瑞麟","shop":"復華夜市-棉被","category":"夜市/市場攤販","zone":"雲嘉南","city":"臺南市","area":"永康區","market_name":"復華夜市","market_address":"復國一路與復華三街交叉口廣場","pay_list":"","pay_tool":"","行業代號":null,"行業代號1":null,"名稱1":null,"行業代號2":null,"名稱2":null,"行業代號3":null,"名稱3":null},{"index":150,"id":10054028,"user":"林崑明","shop":"復華夜市-蝦仁肉圓","category":"夜市/市場攤販","zone":"雲嘉南","city":"臺南市","area":"永康區","market_name":"復華夜市","market_address":"復國一路與復華三街交叉口廣場","pay_list":"","pay_tool":"","行業代號":null,"行業代號1":null,"名稱1":null,"行業代號2":null,"名稱2":null,"行業代號3":null,"名稱3":null},{"index":151,"id":10054029,"user":"李育財","shop":"復華夜市-東山饅頭","category":"夜市/市場攤販","zone":"雲嘉南","city":"臺南市","area":"永康區","market_name":"復華夜市","market_address":"復國一路與復華三街交叉口廣場","pay_list":"","pay_tool":"","行業代號":null,"行業代號1":null,"名稱1":null,"行業代號2":null,"名稱2":null,"行業代號3":null,"名稱3":null},{"index":152,"id":10054030,"user":"張雅棠","shop":"復華夜市-飾品","category":"夜市/市場攤販","zone":"雲嘉南","city":"臺南市","area":"永康區","market_name":"復華夜市","market_address":"復國一路與復華三街交叉口廣場","pay_list":"","pay_tool":"","行業代號":null,"行業代號1":null,"名稱1":null,"行業代號2":null,"名稱2":null,"行業代號3":null,"名稱3":null},{"index":153,"id":10054031,"user":"錢海明","shop":"復華夜市-錢記燒烤","category":"夜市/市場攤販","zone":"雲嘉南","city":"臺南市","area":"永康區","market_name":"復華夜市","market_address":"復國一路與復華三街交叉口廣場","pay_list":"","pay_tool":"","行業代號":null,"行業代號1":null,"名稱1":null,"行業代號2":null,"名稱2":null,"行業代號3":null,"名稱3":null},{"index":154,"id":10054032,"user":"詹俊明","shop":"復華夜市-撈魚寵物","category":"夜市/市場攤販","zone":"雲嘉南","city":"臺南市","area":"永康區","market_name":"復華夜市","market_address":"復國一路與復華三街交叉口廣場","pay_list":"","pay_tool":"","行業代號":null,"行業代號1":null,"名稱1":null,"行業代號2":null,"名稱2":null,"行業代號3":null,"名稱3":null},{"index":155,"id":10054033,"user":"龔伯賢","shop":"復華夜市-膳品香酥排骨","category":"夜市/市場攤販","zone":"雲嘉南","city":"臺南市","area":"永康區","market_name":"復華夜市","market_address":"復國一路與復華三街交叉口廣場","pay_list":"","pay_tool":"","行業代號":null,"行業代號1":null,"名稱1":null,"行業代號2":null,"名稱2":null,"行業代號3":null,"名稱3":null},{"index":156,"id":10054034,"user":"葉莉祝","shop":"復華夜市-皮包","category":"夜市/市場攤販","zone":"雲嘉南","city":"臺南市","area":"永康區","market_name":"復華夜市","market_address":"復國一路與復華三街交叉口廣場","pay_list":"","pay_tool":"","行業代號":null,"行業代號1":null,"名稱1":null,"行業代號2":null,"名稱2":null,"行業代號3":null,"名稱3":null},{"index":157,"id":10054036,"user":"陳春良","shop":"復華夜市-運動褲","category":"夜市/市場攤販","zone":"雲嘉南","city":"臺南市","area":"永康區","market_name":"復華夜市","market_address":"復國一路與復華三街交叉口廣場","pay_list":"","pay_tool":"","行業代號":null,"行業代號1":null,"名稱1":null,"行業代號2":null,"名稱2":null,"行業代號3":null,"名稱3":null},{"index":158,"id":10054037,"user":"陳銀樹","shop":"復華夜市-邱記炭烤","category":"夜市/市場攤販","zone":"雲嘉南","city":"臺南市","area":"永康區","market_name":"復華夜市","market_address":"復國一路與復華三街交叉口廣場","pay_list":"","pay_tool":"","行業代號":null,"行業代號1":null,"名稱1":null,"行業代號2":null,"名稱2":null,"行業代號3":null,"名稱3":null},{"index":159,"id":10054038,"user":"蔡曉萍","shop":"復華夜市-炸魷魚","category":"夜市/市場攤販","zone":"雲嘉南","city":"臺南市","area":"永康區","market_name":"復華夜市","market_address":"復國一路與復華三街交叉口廣場","pay_list":"","pay_tool":"","行業代號":null,"行業代號1":null,"名稱1":null,"行業代號2":null,"名稱2":null,"行業代號3":null,"名稱3":null},{"index":160,"id":10054039,"user":"洪獻忠","shop":"復華夜市-麻油雞","category":"夜市/市場攤販","zone":"雲嘉南","city":"臺南市","area":"永康區","market_name":"復華夜市","market_address":"復國一路與復華三街交叉口廣場","pay_list":"","pay_tool":"","行業代號":null,"行業代號1":null,"名稱1":null,"行業代號2":null,"名稱2":null,"行業代號3":null,"名稱3":null},{"index":161,"id":10054040,"user":"王啟明","shop":"復華夜市-神槍手","category":"夜市/市場攤販","zone":"雲嘉南","city":"臺南市","area":"永康區","market_name":"復華夜市","market_address":"復國一路與復華三街交叉口廣場","pay_list":"","pay_tool":"","行業代號":null,"行業代號1":null,"名稱1":null,"行業代號2":null,"名稱2":null,"行業代號3":null,"名稱3":null},{"index":162,"id":10054041,"user":"莊鳳雪","shop":"復華夜市-佛珠","category":"夜市/市場攤販","zone":"雲嘉南","city":"臺南市","area":"永康區","market_name":"復華夜市","market_address":"復國一路與復華三街交叉口廣場","pay_list":"","pay_tool":"","行業代號":null,"行業代號1":null,"名稱1":null,"行業代號2":null,"名稱2":null,"行業代號3":null,"名稱3":null},{"index":163,"id":10054042,"user":"王秀月","shop":"復華夜市-內衣","category":"夜市/市場攤販","zone":"雲嘉南","city":"臺南市","area":"永康區","market_name":"復華夜市","market_address":"復國一路與復華三街交叉口廣場","pay_list":"","pay_tool":"","行業代號":null,"行業代號1":null,"名稱1":null,"行業代號2":null,"名稱2":null,"行業代號3":null,"名稱3":null},{"index":164,"id":10054043,"user":"林素錦","shop":"復華夜市-女裝","category":"夜市/市場攤販","zone":"雲嘉南","city":"臺南市","area":"永康區","market_name":"復華夜市","market_address":"復國一路與復華三街交叉口廣場","pay_list":"","pay_tool":"","行業代號":null,"行業代號1":null,"名稱1":null,"行業代號2":null,"名稱2":null,"行業代號3":null,"名稱3":null},{"index":165,"id":10054044,"user":"徐銘祥","shop":"復華夜市-章魚燒","category":"夜市/市場攤販","zone":"雲嘉南","city":"臺南市","area":"永康區","market_name":"復華夜市","market_address":"復國一路與復華三街交叉口廣場","pay_list":"","pay_tool":"","行業代號":null,"行業代號1":null,"名稱1":null,"行業代號2":null,"名稱2":null,"行業代號3":null,"名稱3":null},{"index":166,"id":10054045,"user":"陳美華","shop":"復華夜市-煎鳥蛋","category":"夜市/市場攤販","zone":"雲嘉南","city":"臺南市","area":"永康區","market_name":"復華夜市","market_address":"復國一路與復華三街交叉口廣場","pay_list":"","pay_tool":"","行業代號":null,"行業代號1":null,"名稱1":null,"行業代號2":null,"名稱2":null,"行業代號3":null,"名稱3":null},{"index":167,"id":10054047,"user":"李興妹","shop":"復華夜市-蚵仔煎","category":"夜市/市場攤販","zone":"雲嘉南","city":"臺南市","area":"永康區","market_name":"復華夜市","market_address":"復國一路與復華三街交叉口廣場","pay_list":"","pay_tool":"","行業代號":null,"行業代號1":null,"名稱1":null,"行業代號2":null,"名稱2":null,"行業代號3":null,"名稱3":null},{"index":168,"id":10054048,"user":"方景漢","shop":"復華夜市-清葉臭豆腐","category":"夜市/市場攤販","zone":"雲嘉南","city":"臺南市","area":"永康區","market_name":"復華夜市","market_address":"復國一路與復華三街交叉口廣場","pay_list":"","pay_tool":"","行業代號":null,"行業代號1":null,"名稱1":null,"行業代號2":null,"名稱2":null,"行業代號3":null,"名稱3":null},{"index":169,"id":10054049,"user":"張明輝","shop":"復華夜市-雪淇冰","category":"夜市/市場攤販","zone":"雲嘉南","city":"臺南市","area":"永康區","market_name":"復華夜市","market_address":"復國一路與復華三街交叉口廣場","pay_list":"","pay_tool":"","行業代號":null,"行業代號1":null,"名稱1":null,"行業代號2":null,"名稱2":null,"行業代號3":null,"名稱3":null},{"index":170,"id":10054050,"user":"陳淑鈴","shop":"復華夜市-KIWI髮飾","category":"夜市/市場攤販","zone":"雲嘉南","city":"臺南市","area":"永康區","market_name":"復華夜市","market_address":"復國一路與復華三街交叉口廣場","pay_list":"","pay_tool":"","行業代號":null,"行業代號1":null,"名稱1":null,"行業代號2":null,"名稱2":null,"行業代號3":null,"名稱3":null},{"index":171,"id":10054051,"user":"郭柏松","shop":"復華夜市-內衣襪","category":"夜市/市場攤販","zone":"雲嘉南","city":"臺南市","area":"永康區","market_name":"復華夜市","market_address":"復國一路與復華三街交叉口廣場","pay_list":"","pay_tool":"","行業代號":null,"行業代號1":null,"名稱1":null,"行業代號2":null,"名稱2":null,"行業代號3":null,"名稱3":null},{"index":172,"id":10054052,"user":"陳煙銘","shop":"復華夜市-果汁","category":"夜市/市場攤販","zone":"雲嘉南","city":"臺南市","area":"永康區","market_name":"復華夜市","market_address":"復國一路與復華三街交叉口廣場","pay_list":"","pay_tool":"","行業代號":null,"行業代號1":null,"名稱1":null,"行業代號2":null,"名稱2":null,"行業代號3":null,"名稱3":null},{"index":173,"id":10054053,"user":"侯順發","shop":"復華夜市-阿發師石板烤肉","category":"夜市/市場攤販","zone":"雲嘉南","city":"臺南市","area":"永康區","market_name":"復華夜市","market_address":"復國一路與復華三街交叉口廣場","pay_list":"","pay_tool":"","行業代號":null,"行業代號1":null,"名稱1":null,"行業代號2":null,"名稱2":null,"行業代號3":null,"名稱3":null},{"index":174,"id":10054054,"user":"潘月秋","shop":"復華夜市-烤小卷","category":"夜市/市場攤販","zone":"雲嘉南","city":"臺南市","area":"永康區","market_name":"復華夜市","market_address":"復國一路與復華三街交叉口廣場","pay_list":"","pay_tool":"","行業代號":null,"行業代號1":null,"名稱1":null,"行業代號2":null,"名稱2":null,"行業代號3":null,"名稱3":null},{"index":175,"id":10054055,"user":"陳其龍","shop":"復華夜市-可麗餅","category":"夜市/市場攤販","zone":"雲嘉南","city":"臺南市","area":"永康區","market_name":"復華夜市","market_address":"復國一路與復華三街交叉口廣場","pay_list":"","pay_tool":"","行業代號":null,"行業代號1":null,"名稱1":null,"行業代號2":null,"名稱2":null,"行業代號3":null,"名稱3":null},{"index":176,"id":10054056,"user":"方文景","shop":"復華夜市-手錶","category":"夜市/市場攤販","zone":"雲嘉南","city":"臺南市","area":"永康區","market_name":"復華夜市","market_address":"復國一路與復華三街交叉口廣場","pay_list":"","pay_tool":"","行業代號":null,"行業代號1":null,"名稱1":null,"行業代號2":null,"名稱2":null,"行業代號3":null,"名稱3":null},{"index":177,"id":10054058,"user":"林淑惠","shop":"復華夜市-小叮噹鐵板燒","category":"夜市/市場攤販","zone":"雲嘉南","city":"臺南市","area":"永康區","market_name":"復華夜市","market_address":"復國一路與復華三街交叉口廣場","pay_list":"","pay_tool":"","行業代號":null,"行業代號1":null,"名稱1":null,"行業代號2":null,"名稱2":null,"行業代號3":null,"名稱3":null},{"index":178,"id":10054059,"user":"溫聖凱","shop":"復華夜市-豆花","category":"夜市/市場攤販","zone":"雲嘉南","city":"臺南市","area":"永康區","market_name":"復華夜市","market_address":"復國一路與復華三街交叉口廣場","pay_list":"","pay_tool":"","行業代號":null,"行業代號1":null,"名稱1":null,"行業代號2":null,"名稱2":null,"行業代號3":null,"名稱3":null},{"index":179,"id":10054060,"user":"顏鈴娟","shop":"復華夜市-關東煮","category":"夜市/市場攤販","zone":"雲嘉南","city":"臺南市","area":"永康區","market_name":"復華夜市","market_address":"復國一路與復華三街交叉口廣場","pay_list":"","pay_tool":"","行業代號":null,"行業代號1":null,"名稱1":null,"行業代號2":null,"名稱2":null,"行業代號3":null,"名稱3":null},{"index":180,"id":10054061,"user":"陳漢欽","shop":"復華夜市-花枝意麵","category":"夜市/市場攤販","zone":"雲嘉南","city":"臺南市","area":"永康區","market_name":"復華夜市","market_address":"復國一路與復華三街交叉口廣場","pay_list":"","pay_tool":"","行業代號":null,"行業代號1":null,"名稱1":null,"行業代號2":null,"名稱2":null,"行業代號3":null,"名稱3":null},{"index":181,"id":10054062,"user":"蘇得超","shop":"復華夜市-皇家牛排","category":"夜市/市場攤販","zone":"雲嘉南","city":"臺南市","area":"永康區","market_name":"復華夜市","market_address":"復國一路與復華三街交叉口廣場","pay_list":"","pay_tool":"","行業代號":null,"行業代號1":null,"名稱1":null,"行業代號2":null,"名稱2":null,"行業代號3":null,"名稱3":null},{"index":182,"id":10054063,"user":"蕭文諒","shop":"復華夜市-蛋糕","category":"夜市/市場攤販","zone":"雲嘉南","city":"臺南市","area":"永康區","market_name":"復華夜市","market_address":"復國一路與復華三街交叉口廣場","pay_list":"","pay_tool":"","行業代號":null,"行業代號1":null,"名稱1":null,"行業代號2":null,"名稱2":null,"行業代號3":null,"名稱3":null},{"index":183,"id":10054064,"user":"錢志堅","shop":"復華夜市-蜜餞","category":"夜市/市場攤販","zone":"雲嘉南","city":"臺南市","area":"永康區","market_name":"復華夜市","market_address":"復國一路與復華三街交叉口廣場","pay_list":"","pay_tool":"","行業代號":null,"行業代號1":null,"名稱1":null,"行業代號2":null,"名稱2":null,"行業代號3":null,"名稱3":null},{"index":184,"id":10054065,"user":"路偉君","shop":"復華夜市-芭樂","category":"夜市/市場攤販","zone":"雲嘉南","city":"臺南市","area":"永康區","market_name":"復華夜市","market_address":"復國一路與復華三街交叉口廣場","pay_list":"","pay_tool":"","行業代號":null,"行業代號1":null,"名稱1":null,"行業代號2":null,"名稱2":null,"行業代號3":null,"名稱3":null},{"index":185,"id":20002454,"user":"胡瑞美","shop":"胡瑞美","category":["夜市/市場攤販"],"zone":"雲嘉南","city":"臺南市","area":"永康區","market_name":["餐食攤販"],"market_address":"臺南市永康區西灣里民族路４０７號","pay_list":"","pay_tool":"","行業代號":null,"行業代號1":null,"名稱1":null,"行業代號2":null,"名稱2":null,"行業代號3":null,"名稱3":null},{"index":186,"id":20002463,"user":"林謝金淑","shop":"林謝金淑","category":["夜市/市場攤販"],"zone":"雲嘉南","city":"臺南市","area":"永康區","market_name":["餐食攤販"],"market_address":"臺南市永康區大灣里民族路１７６－１號","pay_list":"","pay_tool":"","行業代號":null,"行業代號1":null,"名稱1":null,"行業代號2":null,"名稱2":null,"行業代號3":null,"名稱3":null},{"index":187,"id":20002467,"user":"周黃美娟","shop":"周黃美娟","category":["夜市/市場攤販"],"zone":"雲嘉南","city":"臺南市","area":"永康區","market_name":["餐食攤販"],"market_address":"臺南市永康區北興里大安街４８２號","pay_list":"","pay_tool":"","行業代號":null,"行業代號1":null,"名稱1":null,"行業代號2":null,"名稱2":null,"行業代號3":null,"名稱3":null},{"index":188,"id":20002471,"user":"商瓊文","shop":"就是想喝茶飲","category":["夜市/市場攤販"],"zone":"雲嘉南","city":"臺南市","area":"永康區","market_name":["水果零售","調理飲料攤販","蔬菜零售"],"market_address":"臺南市永康區永康里永明街１１０號前","pay_list":"","pay_tool":"","行業代號":null,"行業代號1":null,"名稱1":null,"行業代號2":null,"名稱2":null,"行業代號3":null,"名稱3":null},{"index":189,"id":20002502,"user":"陳李美蘭","shop":"陳李美蘭","category":["夜市/市場攤販"],"zone":"雲嘉南","city":"臺南市","area":"永康區","market_name":["餐食攤販"],"market_address":"臺南市永康區南灣里大灣路５８７號","pay_list":"","pay_tool":"","行業代號":null,"行業代號1":null,"名稱1":null,"行業代號2":null,"名稱2":null,"行業代號3":null,"名稱3":null},{"index":190,"id":20002503,"user":"吳美玲","shop":"茶鄉泡沫飲品","category":["夜市/市場攤販"],"zone":"雲嘉南","city":"臺南市","area":"永康區","market_name":["餐食攤販"],"market_address":"臺南市永康區五王里中山東路１１６號１樓","pay_list":"","pay_tool":"","行業代號":null,"行業代號1":null,"名稱1":null,"行業代號2":null,"名稱2":null,"行業代號3":null,"名稱3":null},{"index":191,"id":20002511,"user":"陳寶祥","shop":"陳寶祥","category":["夜市/市場攤販"],"zone":"雲嘉南","city":"臺南市","area":"永康區","market_name":["餐食攤販"],"market_address":"臺南市永康區埔園里中山路５７號旁","pay_list":"","pay_tool":"","行業代號":null,"行業代號1":null,"名稱1":null,"行業代號2":null,"名稱2":null,"行業代號3":null,"名稱3":null},{"index":192,"id":20002514,"user":"紀阿綢","shop":"紀阿綢","category":["夜市/市場攤販"],"zone":"雲嘉南","city":"臺南市","area":"永康區","market_name":["餐食攤販"],"market_address":"臺南市永康區北灣里大灣路１７５號","pay_list":"","pay_tool":"","行業代號":null,"行業代號1":null,"名稱1":null,"行業代號2":null,"名稱2":null,"行業代號3":null,"名稱3":null},{"index":193,"id":20002520,"user":"邱芳誼","shop":"邱芳誼","category":["夜市/市場攤販"],"zone":"雲嘉南","city":"臺南市","area":"永康區","market_name":["餐食攤販"],"market_address":"臺南市永康區永康里中山路２６號","pay_list":"","pay_tool":"","行業代號":null,"行業代號1":null,"名稱1":null,"行業代號2":null,"名稱2":null,"行業代號3":null,"名稱3":null},{"index":194,"id":20002549,"user":"許淑懿","shop":"許淑懿","category":["夜市/市場攤販"],"zone":"雲嘉南","city":"臺南市","area":"永康區","market_name":["調理飲料攤販"],"market_address":"臺南市永康區正強里中正路１２７巷２６號","pay_list":"","pay_tool":"","行業代號":null,"行業代號1":null,"名稱1":null,"行業代號2":null,"名稱2":null,"行業代號3":null,"名稱3":null},{"index":195,"id":20002570,"user":"陳慧玉","shop":"陳慧玉","category":["夜市/市場攤販"],"zone":"雲嘉南","city":"臺南市","area":"永康區","market_name":["調理飲料攤販"],"market_address":"臺南市永康區正強里中正路２２６號１樓","pay_list":"","pay_tool":"","行業代號":null,"行業代號1":null,"名稱1":null,"行業代號2":null,"名稱2":null,"行業代號3":null,"名稱3":null},{"index":196,"id":20002603,"user":"羅文發","shop":"春成北平烤鴨","category":["夜市/市場攤販"],"zone":"雲嘉南","city":"臺南市","area":"永康區","market_name":["餐食攤販"],"market_address":"臺南市永康區南灣里大灣路５７３號","pay_list":"","pay_tool":"","行業代號":null,"行業代號1":null,"名稱1":null,"行業代號2":null,"名稱2":null,"行業代號3":null,"名稱3":null},{"index":197,"id":20002623,"user":"林月琴","shop":"林月琴","category":["夜市/市場攤販"],"zone":"雲嘉南","city":"臺南市","area":"永康區","market_name":["調理飲料攤販"],"market_address":"臺南市永康區西勢里富強路１段２７９巷７弄２號","pay_list":"","pay_tool":"","行業代號":null,"行業代號1":null,"名稱1":null,"行業代號2":null,"名稱2":null,"行業代號3":null,"名稱3":null},{"index":198,"id":20002657,"user":"洪月珠","shop":"雅客廣東粥","category":["夜市/市場攤販"],"zone":"雲嘉南","city":"臺南市","area":"永康區","market_name":["餐食攤販"],"market_address":"臺南市永康區復國里復國一路２１８號騎樓","pay_list":"","pay_tool":"","行業代號":null,"行業代號1":null,"名稱1":null,"行業代號2":null,"名稱2":null,"行業代號3":null,"名稱3":null},{"index":199,"id":20002675,"user":"陳偉賢","shop":"陳偉賢","category":["夜市/市場攤販"],"zone":"雲嘉南","city":"臺南市","area":"永康區","market_name":["調理飲料攤販"],"market_address":"臺南市永康區三民里中正北路９９３號","pay_list":"","pay_tool":"","行業代號":null,"行業代號1":null,"名稱1":null,"行業代號2":null,"名稱2":null,"行業代號3":null,"名稱3":null},{"index":200,"id":20002734,"user":"陳文隆","shop":"陳文隆","category":["夜市/市場攤販"],"zone":"雲嘉南","city":"臺南市","area":"永康區","market_name":["餐食攤販"],"market_address":"臺南市永康區??行里中正路５５７號騎樓","pay_list":"","pay_tool":"","行業代號":null,"行業代號1":null,"名稱1":null,"行業代號2":null,"名稱2":null,"行業代號3":null,"名稱3":null}]