[{"index":1,"shop":"建來成行","zone":"雲嘉南","city":"雲林縣","area":"北港鎮","market_address":"雲林縣北港鎮東華里中山路１０６號","user":"蔡建成","行業代號":null,"market_name":["冰果店、冷（熱）飲店","麵店、小吃店"],"行業代號1":null,"名稱1":null,"行業代號2":null,"名稱2":null,"行業代號3":null,"名稱3":null,"category":["餐飲"],"id":20001508,"pay_list":"","pay_tool":""},{"index":2,"shop":"老地方火鍋城","zone":"雲嘉南","city":"雲林縣","area":"北港鎮","market_address":"雲林縣北港鎮新街里華勝路２５９號","user":"黃品蒨","行業代號":null,"market_name":["麵店、小吃店"],"行業代號1":null,"名稱1":null,"行業代號2":null,"名稱2":null,"行業代號3":null,"名稱3":null,"category":["餐飲"],"id":20001509,"pay_list":"","pay_tool":""},{"index":3,"shop":"攤販小吃","zone":"雲嘉南","city":"雲林縣","area":"北港鎮","market_address":"雲林縣北港鎮東華里中華路５號","user":"許嘉成","行業代號":null,"market_name":["麵店、小吃店"],"行業代號1":null,"名稱1":null,"行業代號2":null,"名稱2":null,"行業代號3":null,"名稱3":null,"category":["餐飲"],"id":20001511,"pay_list":"","pay_tool":""},{"index":4,"shop":"米吉屋速食專賣店","zone":"雲嘉南","city":"雲林縣","area":"北港鎮","market_address":"雲林縣北港鎮賜福里中正路４６號","user":"陳聰吉","行業代號":null,"market_name":["餐館、餐廳"],"行業代號1":null,"名稱1":null,"行業代號2":null,"名稱2":null,"行業代號3":null,"名稱3":null,"category":["餐飲"],"id":20001514,"pay_list":"","pay_tool":""},{"index":5,"shop":"小島屋餐飲","zone":"雲嘉南","city":"雲林縣","area":"北港鎮","market_address":"雲林縣北港鎮華勝里吉祥路１００號１樓","user":"蔡國守","行業代號":null,"market_name":["餐館、餐廳"],"行業代號1":null,"名稱1":null,"行業代號2":null,"名稱2":null,"行業代號3":null,"名稱3":null,"category":["餐飲"],"id":20002150,"pay_list":"","pay_tool":""},{"index":6,"shop":"黃至鴻","zone":"雲嘉南","city":"雲林縣","area":"北港鎮","market_address":"雲林縣北港鎮華勝里文明路１６４號","user":"黃至鴻","行業代號":null,"market_name":["麵店、小吃店"],"行業代號1":null,"名稱1":null,"行業代號2":null,"名稱2":null,"行業代號3":null,"名稱3":null,"category":["餐飲"],"id":20003263,"pay_list":"","pay_tool":""},{"index":7,"shop":"蔡素悅","zone":"雲嘉南","city":"雲林縣","area":"北港鎮","market_address":"雲林縣北港鎮南安里光明路５１號","user":"蔡素悅","行業代號":null,"market_name":["冰果店、冷（熱）飲店"],"行業代號1":null,"名稱1":null,"行業代號2":null,"名稱2":null,"行業代號3":null,"名稱3":null,"category":["餐飲"],"id":20003314,"pay_list":"","pay_tool":""},{"index":8,"shop":"張台北鵝肉","zone":"雲嘉南","city":"雲林縣","area":"北港鎮","market_address":"雲林縣北港鎮華勝里華勝路８９號","user":"張有義","行業代號":null,"market_name":["麵店、小吃店"],"行業代號1":null,"名稱1":null,"行業代號2":null,"名稱2":null,"行業代號3":null,"名稱3":null,"category":["餐飲"],"id":20003433,"pay_list":["街口支付","LINE PAY MONEY"],"pay_tool":["行動支付"]},{"index":9,"shop":"品味牛排火鍋簡餐","zone":"雲嘉南","city":"雲林縣","area":"北港鎮","market_address":"雲林縣北港鎮華勝里１１鄰公園路９７號","user":"許美玉","行業代號":null,"market_name":["麵店、小吃店"],"行業代號1":null,"名稱1":null,"行業代號2":null,"名稱2":null,"行業代號3":null,"名稱3":null,"category":["餐飲"],"id":20003474,"pay_list":"","pay_tool":""},{"index":10,"shop":"福安鴨肉飯","zone":"雲嘉南","city":"雲林縣","area":"北港鎮","market_address":"雲林縣北港鎮中和里中山路３７號騎樓","user":"楊明川","行業代號":null,"market_name":["麵店、小吃店"],"行業代號1":null,"名稱1":null,"行業代號2":null,"名稱2":null,"行業代號3":null,"名稱3":null,"category":["餐飲"],"id":20006530,"pay_list":"","pay_tool":""},{"index":11,"shop":"蔡速蘭","zone":"雲嘉南","city":"雲林縣","area":"北港鎮","market_address":"雲林縣北港鎮中和里光明路４２號","user":"蔡速蘭","行業代號":null,"market_name":["麵店、小吃店"],"行業代號1":null,"名稱1":null,"行業代號2":null,"名稱2":null,"行業代號3":null,"名稱3":null,"category":["餐飲"],"id":20006580,"pay_list":"","pay_tool":""},{"index":12,"shop":"天下圍鍋餐飲行","zone":"雲嘉南","city":"雲林縣","area":"北港鎮","market_address":"雲林縣北港鎮華勝里民有路３９號","user":"黃琴雅","行業代號":null,"market_name":["其他外燴及團膳承包"],"行業代號1":null,"名稱1":null,"行業代號2":null,"名稱2":null,"行業代號3":null,"名稱3":null,"category":["餐飲"],"id":20006609,"pay_list":["LINE PAY MONEY"],"pay_tool":["行動支付"]},{"index":13,"shop":"聖林餐飲店","zone":"雲嘉南","city":"雲林縣","area":"北港鎮","market_address":"雲林縣北港鎮仁和里仁和路２２號","user":"黎宜麗","行業代號":null,"market_name":["麵店、小吃店"],"行業代號1":null,"名稱1":null,"行業代號2":null,"名稱2":null,"行業代號3":null,"名稱3":null,"category":["餐飲"],"id":20007934,"pay_list":"","pay_tool":""},{"index":14,"shop":"便便屋手調茶飲專賣店","zone":"雲嘉南","city":"雲林縣","area":"北港鎮","market_address":"雲林縣北港鎮大同里文化路７２號","user":"張雅弼","行業代號":null,"market_name":["冰果店、冷（熱）飲店"],"行業代號1":null,"名稱1":null,"行業代號2":null,"名稱2":null,"行業代號3":null,"名稱3":null,"category":["餐飲"],"id":20007939,"pay_list":"","pay_tool":""},{"index":15,"shop":"港味燒腊快餐店","zone":"雲嘉南","city":"雲林縣","area":"北港鎮","market_address":"雲林縣北港鎮大同里５鄰文化路１２９―１號","user":"陳燦輝","行業代號":null,"market_name":["便當、自助餐店"],"行業代號1":null,"名稱1":null,"行業代號2":null,"名稱2":null,"行業代號3":null,"名稱3":null,"category":["餐飲"],"id":20009379,"pay_list":"","pay_tool":""},{"index":16,"shop":"海珍便當","zone":"雲嘉南","city":"雲林縣","area":"北港鎮","market_address":"雲林縣北港鎮華勝里公園路３４號","user":"蘇聖傑","行業代號":null,"market_name":["便當、自助餐店"],"行業代號1":null,"名稱1":null,"行業代號2":null,"名稱2":null,"行業代號3":null,"名稱3":null,"category":["餐飲"],"id":20011343,"pay_list":"","pay_tool":""},{"index":17,"shop":"建成小吃部","zone":"雲嘉南","city":"雲林縣","area":"北港鎮","market_address":"雲林縣北港鎮東華里中山路１２８號","user":"吳金龍","行業代號":null,"market_name":["冰果店、冷（熱）飲店","麵店、小吃店"],"行業代號1":null,"名稱1":null,"行業代號2":null,"名稱2":null,"行業代號3":null,"名稱3":null,"category":["餐飲"],"id":20011344,"pay_list":"","pay_tool":""},{"index":18,"shop":"紅蟳城小吃店","zone":"雲嘉南","city":"雲林縣","area":"北港鎮","market_address":"雲林縣北港鎮義民里１鄰民主路４３號","user":"洪亭玉","行業代號":null,"market_name":["麵店、小吃店"],"行業代號1":null,"名稱1":null,"行業代號2":null,"名稱2":null,"行業代號3":null,"名稱3":null,"category":["餐飲"],"id":20011345,"pay_list":"","pay_tool":""},{"index":19,"shop":"劉銘信（田中麵攤）","zone":"雲嘉南","city":"雲林縣","area":"北港鎮","market_address":"雲林縣北港鎮華勝里公園路５４號","user":"劉銘信","行業代號":null,"market_name":["麵店、小吃店"],"行業代號1":null,"名稱1":null,"行業代號2":null,"名稱2":null,"行業代號3":null,"名稱3":null,"category":["餐飲"],"id":20011583,"pay_list":"","pay_tool":""},{"index":20,"shop":"洪家莊麵館","zone":"雲嘉南","city":"雲林縣","area":"北港鎮","market_address":"雲林縣北港鎮賜福里大同路４９號","user":"洪欣漢","行業代號":null,"market_name":["麵店、小吃店"],"行業代號1":null,"名稱1":null,"行業代號2":null,"名稱2":null,"行業代號3":null,"名稱3":null,"category":["餐飲"],"id":20011587,"pay_list":"","pay_tool":""},{"index":21,"shop":"曹美玲","zone":"雲嘉南","city":"雲林縣","area":"北港鎮","market_address":"雲林縣北港鎮樹腳里大同路５１３號","user":"曹美玲","行業代號":null,"market_name":["冰果店、冷（熱）飲店"],"行業代號1":null,"名稱1":null,"行業代號2":null,"名稱2":null,"行業代號3":null,"名稱3":null,"category":["餐飲"],"id":20013811,"pay_list":"","pay_tool":""},{"index":22,"shop":"李桂櫻","zone":"雲嘉南","city":"雲林縣","area":"北港鎮","market_address":"雲林縣北港鎮華勝里華勝路５４號","user":"李桂櫻","行業代號":null,"market_name":["早餐店"],"行業代號1":null,"名稱1":null,"行業代號2":null,"名稱2":null,"行業代號3":null,"名稱3":null,"category":["餐飲"],"id":20014087,"pay_list":"","pay_tool":""},{"index":23,"shop":"逸壽司","zone":"雲嘉南","city":"雲林縣","area":"北港鎮","market_address":"雲林縣北港鎮華勝里公園路１８７號","user":"洪逸柏","行業代號":null,"market_name":["餐館、餐廳"],"行業代號1":null,"名稱1":null,"行業代號2":null,"名稱2":null,"行業代號3":null,"名稱3":null,"category":["餐飲"],"id":20014088,"pay_list":"","pay_tool":""},{"index":24,"shop":"莊柏林","zone":"雲嘉南","city":"雲林縣","area":"北港鎮","market_address":"雲林縣北港鎮華勝里民政路２６號","user":"莊伯林","行業代號":null,"market_name":["早餐店"],"行業代號1":null,"名稱1":null,"行業代號2":null,"名稱2":null,"行業代號3":null,"名稱3":null,"category":["餐飲"],"id":20014089,"pay_list":"","pay_tool":""},{"index":25,"shop":"陳麗嬌","zone":"雲嘉南","city":"雲林縣","area":"北港鎮","market_address":"雲林縣北港鎮華勝里民有路３３號","user":"陳麗嬌","行業代號":null,"market_name":["麵店、小吃店"],"行業代號1":null,"名稱1":null,"行業代號2":null,"名稱2":null,"行業代號3":null,"名稱3":null,"category":["餐飲"],"id":20014090,"pay_list":"","pay_tool":""},{"index":26,"shop":"林玉琴","zone":"雲嘉南","city":"雲林縣","area":"北港鎮","market_address":"雲林縣北港鎮華勝里民樂路４６號","user":"林玉琴","行業代號":null,"market_name":["麵店、小吃店"],"行業代號1":null,"名稱1":null,"行業代號2":null,"名稱2":null,"行業代號3":null,"名稱3":null,"category":["餐飲"],"id":20014091,"pay_list":"","pay_tool":""},{"index":27,"shop":"廟邊假魚肚","zone":"雲嘉南","city":"雲林縣","area":"北港鎮","market_address":"雲林縣北港鎮光民里中山路１８６號","user":"蔡煌明","行業代號":null,"market_name":["麵店、小吃店"],"行業代號1":null,"名稱1":null,"行業代號2":null,"名稱2":null,"行業代號3":null,"名稱3":null,"category":["餐飲"],"id":20014426,"pay_list":"","pay_tool":""},{"index":28,"shop":"阿杏素食","zone":"雲嘉南","city":"雲林縣","area":"北港鎮","market_address":"雲林縣北港鎮華勝里民治路３２號","user":"吳佩馨","行業代號":null,"market_name":["便當、自助餐店"],"行業代號1":null,"名稱1":null,"行業代號2":null,"名稱2":null,"行業代號3":null,"名稱3":null,"category":["餐飲"],"id":20014427,"pay_list":"","pay_tool":""},{"index":29,"shop":"園庭農庄土雞城","zone":"雲嘉南","city":"雲林縣","area":"北港鎮","market_address":"雲林縣北港鎮扶朝里１０鄰扶朝路８２號１樓","user":"蘇翰韋","行業代號":null,"market_name":["麵店、小吃店"],"行業代號1":null,"名稱1":null,"行業代號2":null,"名稱2":null,"行業代號3":null,"名稱3":null,"category":["餐飲"],"id":20014696,"pay_list":"","pay_tool":""},{"index":30,"shop":"鬥牛１００","zone":"雲嘉南","city":"雲林縣","area":"北港鎮","market_address":"雲林縣北港鎮華勝里華勝路１８６號","user":"丁世紀","行業代號":null,"market_name":["麵店、小吃店"],"行業代號1":null,"名稱1":null,"行業代號2":null,"名稱2":null,"行業代號3":null,"名稱3":null,"category":["餐飲"],"id":20014857,"pay_list":"","pay_tool":""},{"index":31,"shop":"郎港式鮮肉包北港店","zone":"雲嘉南","city":"雲林縣","area":"北港鎮","market_address":"雲林縣北港鎮華勝里４鄰公園路５９―１號","user":"廖安琪","行業代號":null,"market_name":["麵店、小吃店"],"行業代號1":null,"名稱1":null,"行業代號2":null,"名稱2":null,"行業代號3":null,"名稱3":null,"category":["餐飲"],"id":20015046,"pay_list":"","pay_tool":""},{"index":32,"shop":"快樂堡早餐店","zone":"雲嘉南","city":"雲林縣","area":"北港鎮","market_address":"雲林縣北港鎮華勝里民樂路３２號","user":"陳秀美","行業代號":null,"market_name":["早餐店"],"行業代號1":null,"名稱1":null,"行業代號2":null,"名稱2":null,"行業代號3":null,"名稱3":null,"category":["餐飲"],"id":20015056,"pay_list":"","pay_tool":""},{"index":33,"shop":"三角廚房","zone":"雲嘉南","city":"雲林縣","area":"北港鎮","market_address":"雲林縣北港鎮扶朝里未編門牌（扶朝段１０００地號）","user":"蘇定吾","行業代號":null,"market_name":["便當、自助餐店"],"行業代號1":null,"名稱1":null,"行業代號2":null,"名稱2":null,"行業代號3":null,"名稱3":null,"category":["餐飲"],"id":20015060,"pay_list":"","pay_tool":""},{"index":34,"shop":"蘇文正","zone":"雲嘉南","city":"雲林縣","area":"北港鎮","market_address":"雲林縣北港鎮華勝里２鄰文化路１５９號","user":"蘇文正","行業代號":null,"market_name":["麵店、小吃店"],"行業代號1":null,"名稱1":null,"行業代號2":null,"名稱2":null,"行業代號3":null,"名稱3":null,"category":["餐飲"],"id":20018523,"pay_list":"","pay_tool":""},{"index":35,"shop":"昇霖茶莊","zone":"雲嘉南","city":"雲林縣","area":"北港鎮","market_address":"雲林縣北港鎮華勝里民享路８號","user":"郭兆鈞","行業代號":null,"market_name":["冰果店、冷（熱）飲店"],"行業代號1":null,"名稱1":null,"行業代號2":null,"名稱2":null,"行業代號3":null,"名稱3":null,"category":["餐飲"],"id":20018688,"pay_list":["街口支付"],"pay_tool":["行動支付"]},{"index":36,"shop":"許勝任","zone":"雲嘉南","city":"雲林縣","area":"北港鎮","market_address":"雲林縣北港鎮華勝里華勝路５４號","user":"許勝任","行業代號":null,"market_name":["麵店、小吃店"],"行業代號1":null,"名稱1":null,"行業代號2":null,"名稱2":null,"行業代號3":null,"名稱3":null,"category":["餐飲"],"id":20018791,"pay_list":"","pay_tool":""},{"index":37,"shop":"許瓜鴨莊","zone":"雲嘉南","city":"雲林縣","area":"北港鎮","market_address":"雲林縣北港鎮華勝里５鄰大同路２２０號","user":"許宸維","行業代號":null,"market_name":["便當、自助餐店"],"行業代號1":null,"名稱1":null,"行業代號2":null,"名稱2":null,"行業代號3":null,"名稱3":null,"category":["餐飲"],"id":20018796,"pay_list":"","pay_tool":""},{"index":38,"shop":"蔡楚山","zone":"雲嘉南","city":"雲林縣","area":"北港鎮","market_address":"雲林縣北港鎮中和里光明路２５號","user":"蔡宗盛","行業代號":null,"market_name":["麵店、小吃店"],"行業代號1":null,"名稱1":null,"行業代號2":null,"名稱2":null,"行業代號3":null,"名稱3":null,"category":["餐飲"],"id":20018903,"pay_list":"","pay_tool":""},{"index":39,"shop":"明德古早味","zone":"雲嘉南","city":"雲林縣","area":"北港鎮","market_address":"雲林縣北港鎮東陽里中山路２２號","user":"呂韻麟","行業代號":null,"market_name":["麵店、小吃店"],"行業代號1":null,"名稱1":null,"行業代號2":null,"名稱2":null,"行業代號3":null,"名稱3":null,"category":["餐飲"],"id":20018916,"pay_list":"","pay_tool":""},{"index":40,"shop":"大象餐飲屋","zone":"雲嘉南","city":"雲林縣","area":"北港鎮","market_address":"雲林縣北港鎮東陽里３鄰中山路２０號","user":"許宗渝","行業代號":null,"market_name":["麵店、小吃店"],"行業代號1":null,"名稱1":null,"行業代號2":null,"名稱2":null,"行業代號3":null,"名稱3":null,"category":["餐飲"],"id":20019092,"pay_list":"","pay_tool":""},{"index":41,"shop":"??記烤鴨","zone":"雲嘉南","city":"雲林縣","area":"北港鎮","market_address":"雲林縣北港鎮光復里大同路與華南路口","user":"黃健朗","行業代號":null,"market_name":["麵店、小吃店"],"行業代號1":null,"名稱1":null,"行業代號2":null,"名稱2":null,"行業代號3":null,"名稱3":null,"category":["餐飲"],"id":20019135,"pay_list":"","pay_tool":""},{"index":42,"shop":"田中意麵啟","zone":"雲嘉南","city":"雲林縣","area":"北港鎮","market_address":"雲林縣北港鎮華勝里文明路１０４號","user":"劉璋霖","行業代號":null,"market_name":["麵店、小吃店"],"行業代號1":null,"名稱1":null,"行業代號2":null,"名稱2":null,"行業代號3":null,"名稱3":null,"category":["餐飲"],"id":20019140,"pay_list":"","pay_tool":""},{"index":43,"shop":"四川魷魚??","zone":"雲嘉南","city":"雲林縣","area":"北港鎮","market_address":"雲林縣北港鎮大同里大同路１０６號","user":"吳蔡銘琴","行業代號":null,"market_name":["麵店、小吃店"],"行業代號1":null,"名稱1":null,"行業代號2":null,"名稱2":null,"行業代號3":null,"名稱3":null,"category":["餐飲"],"id":20019157,"pay_list":"","pay_tool":""},{"index":44,"shop":"天天小館","zone":"雲嘉南","city":"雲林縣","area":"北港鎮","market_address":"雲林縣北港鎮華勝里公園路６１號","user":"蔡宗憲","行業代號":null,"market_name":["麵店、小吃店"],"行業代號1":null,"名稱1":null,"行業代號2":null,"名稱2":null,"行業代號3":null,"名稱3":null,"category":["餐飲"],"id":20026131,"pay_list":"","pay_tool":""},{"index":45,"shop":"橙堡早餐","zone":"雲嘉南","city":"雲林縣","area":"北港鎮","market_address":"雲林縣北港鎮華勝里公園路１１７號","user":"柯木泉","行業代號":null,"market_name":["早餐店"],"行業代號1":null,"名稱1":null,"行業代號2":null,"名稱2":null,"行業代號3":null,"名稱3":null,"category":["餐飲"],"id":20026139,"pay_list":"","pay_tool":""},{"index":46,"shop":"陳銘禧","zone":"雲嘉南","city":"雲林縣","area":"北港鎮","market_address":"雲林縣北港鎮光復里大同路３５３號１樓","user":"陳銘禧","行業代號":null,"market_name":["早餐店"],"行業代號1":null,"名稱1":null,"行業代號2":null,"名稱2":null,"行業代號3":null,"名稱3":null,"category":["餐飲"],"id":20026195,"pay_list":"","pay_tool":""},{"index":47,"shop":"吳明辨","zone":"雲嘉南","city":"雲林縣","area":"北港鎮","market_address":"雲林縣北港鎮光復里大同路２２５號","user":"吳明辨","行業代號":null,"market_name":["麵店、小吃店"],"行業代號1":null,"名稱1":null,"行業代號2":null,"名稱2":null,"行業代號3":null,"名稱3":null,"category":["餐飲"],"id":20026242,"pay_list":"","pay_tool":""},{"index":48,"shop":"吳龍輝","zone":"雲嘉南","city":"雲林縣","area":"北港鎮","market_address":"雲林縣北港鎮樹腳里文仁路４６７號","user":"吳龍輝","行業代號":null,"market_name":["麵店、小吃店"],"行業代號1":null,"名稱1":null,"行業代號2":null,"名稱2":null,"行業代號3":null,"名稱3":null,"category":["餐飲"],"id":20026243,"pay_list":"","pay_tool":""},{"index":49,"shop":"吳溪富","zone":"雲嘉南","city":"雲林縣","area":"北港鎮","market_address":"雲林縣北港鎮華勝里民樂路１５７號","user":"吳溪富","行業代號":null,"market_name":["麵店、小吃店"],"行業代號1":null,"名稱1":null,"行業代號2":null,"名稱2":null,"行業代號3":null,"名稱3":null,"category":["餐飲"],"id":20026255,"pay_list":"","pay_tool":""},{"index":50,"shop":"洧丞早餐店","zone":"雲嘉南","city":"雲林縣","area":"北港鎮","market_address":"雲林縣北港鎮華勝里０１１鄰公園路３０號","user":"李宇立","行業代號":null,"market_name":["早餐店"],"行業代號1":null,"名稱1":null,"行業代號2":null,"名稱2":null,"行業代號3":null,"名稱3":null,"category":["餐飲"],"id":20026269,"pay_list":"","pay_tool":""},{"index":51,"shop":"蔡蒼義","zone":"雲嘉南","city":"雲林縣","area":"北港鎮","market_address":"雲林縣北港鎮樹腳里０１３鄰文仁路４０９號","user":"蔡蒼義","行業代號":null,"market_name":["麵店、小吃店"],"行業代號1":null,"名稱1":null,"行業代號2":null,"名稱2":null,"行業代號3":null,"名稱3":null,"category":["餐飲"],"id":20026270,"pay_list":"","pay_tool":""},{"index":52,"shop":"王壬祥","zone":"雲嘉南","city":"雲林縣","area":"北港鎮","market_address":"雲林縣北港鎮光復里０１２鄰文仁路４６６－１號","user":"王壬祥","行業代號":null,"market_name":["麵店、小吃店"],"行業代號1":null,"名稱1":null,"行業代號2":null,"名稱2":null,"行業代號3":null,"名稱3":null,"category":["餐飲"],"id":20026301,"pay_list":"","pay_tool":""},{"index":53,"shop":"元木同商行","zone":"雲嘉南","city":"雲林縣","area":"北港鎮","market_address":"雲林縣北港鎮新街里新德路１３６號１樓","user":"丁子軒","行業代號":null,"market_name":["餐館、餐廳"],"行業代號1":null,"名稱1":null,"行業代號2":null,"名稱2":null,"行業代號3":null,"名稱3":null,"category":["餐飲"],"id":20026380,"pay_list":"","pay_tool":""},{"index":54,"shop":"阿成熱炒店","zone":"雲嘉南","city":"雲林縣","area":"北港鎮","market_address":"雲林縣北港鎮光民里中山路１８０號","user":"楊罔市","行業代號":null,"market_name":["麵店、小吃店"],"行業代號1":null,"名稱1":null,"行業代號2":null,"名稱2":null,"行業代號3":null,"名稱3":null,"category":["餐飲"],"id":20026481,"pay_list":"","pay_tool":""},{"index":55,"shop":"歐嗨喲！早餐屋","zone":"雲嘉南","city":"雲林縣","area":"北港鎮","market_address":"雲林縣北港鎮草湖里華勝路７３９號","user":"郭東鑫","行業代號":null,"market_name":["早餐店"],"行業代號1":null,"名稱1":null,"行業代號2":null,"名稱2":null,"行業代號3":null,"名稱3":null,"category":["餐飲"],"id":20026800,"pay_list":"","pay_tool":""},{"index":56,"shop":"蘇仁鴻","zone":"雲嘉南","city":"雲林縣","area":"北港鎮","market_address":"雲林縣北港鎮大同里文化路５８號","user":"蘇仁鴻","行業代號":null,"market_name":["早餐店"],"行業代號1":null,"名稱1":null,"行業代號2":null,"名稱2":null,"行業代號3":null,"名稱3":null,"category":["餐飲"],"id":20026861,"pay_list":"","pay_tool":""},{"index":57,"shop":"雲林縣笨港春文化教育協會","zone":"雲嘉南","city":"雲林縣","area":"北港鎮","market_address":"雲林縣北港鎮劉厝里７鄰５３―１號","user":"徐淑珠","行業代號":null,"market_name":["手工藝品零售","麵店、小吃店","其他藝術表演"],"行業代號1":null,"名稱1":null,"行業代號2":null,"名稱2":null,"行業代號3":null,"名稱3":null,"category":["餐飲"],"id":20027060,"pay_list":"","pay_tool":""},{"index":58,"shop":"許丙宗","zone":"雲嘉南","city":"雲林縣","area":"北港鎮","market_address":"雲林縣北港鎮華勝里北港段１２８６號","user":"許丙宗","行業代號":null,"market_name":["麵店、小吃店"],"行業代號1":null,"名稱1":null,"行業代號2":null,"名稱2":null,"行業代號3":null,"名稱3":null,"category":["餐飲"],"id":20027568,"pay_list":"","pay_tool":""},{"index":59,"shop":"黃如婕","zone":"雲嘉南","city":"雲林縣","area":"北港鎮","market_address":"雲林縣北港鎮華勝里北港段１２８６號","user":"黃如婕","行業代號":null,"market_name":["麵店、小吃店"],"行業代號1":null,"名稱1":null,"行業代號2":null,"名稱2":null,"行業代號3":null,"名稱3":null,"category":["餐飲"],"id":20027596,"pay_list":"","pay_tool":""},{"index":60,"shop":"大同冷飲站","zone":"雲嘉南","city":"雲林縣","area":"北港鎮","market_address":"雲林縣北港鎮光復里大同路２６１號","user":"康智緯","行業代號":null,"market_name":["茶葉零售","冰果店、冷（熱）飲店","未分類其他家用器具及用品零售","其他服裝及其配件零售"],"行業代號1":null,"名稱1":null,"行業代號2":null,"名稱2":null,"行業代號3":null,"名稱3":null,"category":["餐飲"],"id":20031657,"pay_list":"","pay_tool":""},{"index":61,"shop":"清心福全冷飲站北港二店","zone":"雲嘉南","city":"雲林縣","area":"北港鎮","market_address":"雲林縣北港鎮華勝里民享路２號","user":"邱俞溦","行業代號":null,"market_name":["冰果店、冷（熱）飲店"],"行業代號1":null,"名稱1":null,"行業代號2":null,"名稱2":null,"行業代號3":null,"名稱3":null,"category":["餐飲"],"id":20031663,"pay_list":"","pay_tool":""},{"index":62,"shop":"北港龍井","zone":"雲嘉南","city":"雲林縣","area":"北港鎮","market_address":"雲林縣北港鎮光民里中山路１８４號","user":"王清坡","行業代號":null,"market_name":["麵店、小吃店"],"行業代號1":null,"名稱1":null,"行業代號2":null,"名稱2":null,"行業代號3":null,"名稱3":null,"category":["餐飲"],"id":20031784,"pay_list":"","pay_tool":""},{"index":63,"shop":"初早餐泥好","zone":"雲嘉南","city":"雲林縣","area":"北港鎮","market_address":"雲林縣北港鎮華勝里北辰路２號隔壁","user":"葉怡君","行業代號":null,"market_name":["早餐店"],"行業代號1":null,"名稱1":null,"行業代號2":null,"名稱2":null,"行業代號3":null,"名稱3":null,"category":["餐飲"],"id":20032395,"pay_list":"","pay_tool":""},{"index":64,"shop":"丁裕城","zone":"雲嘉南","city":"雲林縣","area":"北港鎮","market_address":"雲林縣北港鎮華勝里１７鄰民享路４２號","user":"丁裕城","行業代號":null,"market_name":["麵店、小吃店"],"行業代號1":null,"名稱1":null,"行業代號2":null,"名稱2":null,"行業代號3":null,"名稱3":null,"category":["餐飲"],"id":20032529,"pay_list":"","pay_tool":""},{"index":65,"shop":"秀美餐飲","zone":"雲嘉南","city":"雲林縣","area":"北港鎮","market_address":"雲林縣北港鎮西勢里文化路４２―２號","user":"黃許秀美","行業代號":null,"market_name":["麵店、小吃店"],"行業代號1":null,"名稱1":null,"行業代號2":null,"名稱2":null,"行業代號3":null,"名稱3":null,"category":["餐飲"],"id":20032645,"pay_list":"","pay_tool":""},{"index":66,"shop":"陳明滄","zone":"雲嘉南","city":"雲林縣","area":"北港鎮","market_address":"雲林縣北港鎮東華里２鄰中山路１３０號","user":"陳明滄","行業代號":null,"market_name":["麵店、小吃店"],"行業代號1":null,"名稱1":null,"行業代號2":null,"名稱2":null,"行業代號3":null,"名稱3":null,"category":["餐飲"],"id":20032684,"pay_list":"","pay_tool":""},{"index":67,"shop":"上味美食快餐","zone":"雲嘉南","city":"雲林縣","area":"北港鎮","market_address":"雲林縣北港鎮仁安里大同路１８３號","user":"黃建雄","行業代號":null,"market_name":["便當、自助餐店"],"行業代號1":null,"名稱1":null,"行業代號2":null,"名稱2":null,"行業代號3":null,"名稱3":null,"category":["餐飲"],"id":20032758,"pay_list":"","pay_tool":""},{"index":68,"shop":"黃定國","zone":"雲嘉南","city":"雲林縣","area":"北港鎮","market_address":"雲林縣北港鎮大同里大同路１０５號","user":"黃定國","行業代號":null,"market_name":["麵店、小吃店"],"行業代號1":null,"名稱1":null,"行業代號2":null,"名稱2":null,"行業代號3":null,"名稱3":null,"category":["餐飲"],"id":20032947,"pay_list":"","pay_tool":""},{"index":69,"shop":"許名傑","zone":"雲嘉南","city":"雲林縣","area":"北港鎮","market_address":"雲林縣北港鎮華勝里２５鄰公園路１８―３號１樓","user":"許名傑","行業代號":null,"market_name":["麵店、小吃店"],"行業代號1":null,"名稱1":null,"行業代號2":null,"名稱2":null,"行業代號3":null,"名稱3":null,"category":["餐飲"],"id":20033243,"pay_list":"","pay_tool":""},{"index":70,"shop":"Ｔｅａ，ｓ原味北港店","zone":"雲嘉南","city":"雲林縣","area":"北港鎮","market_address":"雲林縣北港鎮華勝里公園路２８號","user":"邱詩淵","行業代號":null,"market_name":["冰果店、冷（熱）飲店"],"行業代號1":null,"名稱1":null,"行業代號2":null,"名稱2":null,"行業代號3":null,"名稱3":null,"category":["餐飲"],"id":20033285,"pay_list":"","pay_tool":""},{"index":71,"shop":"祥江??魠","zone":"雲嘉南","city":"雲林縣","area":"北港鎮","market_address":"雲林縣北港鎮華勝里民政路９８號","user":"許松江","行業代號":null,"market_name":["麵店、小吃店"],"行業代號1":null,"名稱1":null,"行業代號2":null,"名稱2":null,"行業代號3":null,"名稱3":null,"category":["餐飲"],"id":20033591,"pay_list":"","pay_tool":""},{"index":72,"shop":"ＴＥＡ＇Ｓ原味北港文化店","zone":"雲嘉南","city":"雲林縣","area":"北港鎮","market_address":"雲林縣北港鎮西勢里文化路４２―３號","user":"邱詩淵","行業代號":null,"market_name":["冰果店、冷（熱）飲店"],"行業代號1":null,"名稱1":null,"行業代號2":null,"名稱2":null,"行業代號3":null,"名稱3":null,"category":["餐飲"],"id":20033674,"pay_list":"","pay_tool":""},{"index":73,"shop":"蕭金理","zone":"雲嘉南","city":"雲林縣","area":"北港鎮","market_address":"雲林縣北港鎮仁安里中正路１１５號","user":"蕭金理","行業代號":null,"market_name":["麵店、小吃店"],"行業代號1":null,"名稱1":null,"行業代號2":null,"名稱2":null,"行業代號3":null,"名稱3":null,"category":["餐飲"],"id":20033681,"pay_list":"","pay_tool":""},{"index":74,"shop":"阿豐油飯麵線糊","zone":"雲嘉南","city":"雲林縣","area":"北港鎮","market_address":"雲林縣北港鎮賜福里中正路２４號","user":"葉成豐","行業代號":null,"market_name":["麵店、小吃店"],"行業代號1":null,"名稱1":null,"行業代號2":null,"名稱2":null,"行業代號3":null,"名稱3":null,"category":["餐飲"],"id":20034303,"pay_list":"","pay_tool":""},{"index":75,"shop":"惠枝便當店","zone":"雲嘉南","city":"雲林縣","area":"北港鎮","market_address":"雲林縣北港鎮華勝里文仁路３５３―５號","user":"蘇惠枝","行業代號":null,"market_name":["便當、自助餐店"],"行業代號1":null,"名稱1":null,"行業代號2":null,"名稱2":null,"行業代號3":null,"名稱3":null,"category":["餐飲"],"id":20034362,"pay_list":"","pay_tool":""},{"index":76,"shop":"何記燒肉飯","zone":"雲嘉南","city":"雲林縣","area":"北港鎮","market_address":"雲林縣北港鎮華勝里文星路１５０巷２１號１樓","user":"何宜旋","行業代號":null,"market_name":["便當、自助餐店"],"行業代號1":null,"名稱1":null,"行業代號2":null,"名稱2":null,"行業代號3":null,"名稱3":null,"category":["餐飲"],"id":20034371,"pay_list":"","pay_tool":""},{"index":77,"shop":"阿等土豆油飯","zone":"雲嘉南","city":"雲林縣","area":"北港鎮","market_address":"雲林縣北港鎮賜福里大同路７９號","user":"陳文志","行業代號":null,"market_name":["麵店、小吃店"],"行業代號1":null,"名稱1":null,"行業代號2":null,"名稱2":null,"行業代號3":null,"名稱3":null,"category":["餐飲"],"id":20034376,"pay_list":"","pay_tool":""},{"index":78,"shop":"呷尚宝北港店","zone":"雲嘉南","city":"雲林縣","area":"北港鎮","market_address":"雲林縣北港鎮華勝里文昌路３１號","user":"陳美紅","行業代號":null,"market_name":["早餐店"],"行業代號1":null,"名稱1":null,"行業代號2":null,"名稱2":null,"行業代號3":null,"名稱3":null,"category":["餐飲"],"id":20034559,"pay_list":"","pay_tool":""},{"index":79,"shop":"品軒美食館","zone":"雲嘉南","city":"雲林縣","area":"北港鎮","market_address":"雲林縣北港鎮華勝里民樂路６８號","user":"吳家豐","行業代號":null,"market_name":["麵店、小吃店"],"行業代號1":null,"名稱1":null,"行業代號2":null,"名稱2":null,"行業代號3":null,"名稱3":null,"category":["餐飲"],"id":20034858,"pay_list":"","pay_tool":""},{"index":80,"shop":"林上發綠豆沙楊桃汁","zone":"雲嘉南","city":"雲林縣","area":"北港鎮","market_address":"雲林縣北港鎮賜福里中正路５４號〈騎樓〉","user":"蔡佩珊","行業代號":null,"market_name":["冰果店、冷（熱）飲店"],"行業代號1":null,"名稱1":null,"行業代號2":null,"名稱2":null,"行業代號3":null,"名稱3":null,"category":["餐飲"],"id":20034872,"pay_list":"","pay_tool":""},{"index":81,"shop":"一郎小吃店","zone":"雲嘉南","city":"雲林縣","area":"北港鎮","market_address":"雲林縣北港鎮仁和里仁和路３號１樓","user":"許一郎","行業代號":null,"market_name":["麵店、小吃店"],"行業代號1":null,"名稱1":null,"行業代號2":null,"名稱2":null,"行業代號3":null,"名稱3":null,"category":["餐飲"],"id":20034905,"pay_list":"","pay_tool":""},{"index":82,"shop":"伍二捌商行","zone":"雲嘉南","city":"雲林縣","area":"北港鎮","market_address":"雲林縣北港鎮大同里文化路７０號","user":"王倩怡","行業代號":null,"market_name":["冰果店、冷（熱）飲店"],"行業代號1":null,"名稱1":null,"行業代號2":null,"名稱2":null,"行業代號3":null,"名稱3":null,"category":["餐飲"],"id":20034958,"pay_list":"","pay_tool":""},{"index":83,"shop":"大喜冰品屋","zone":"雲嘉南","city":"雲林縣","area":"北港鎮","market_address":"雲林縣北港鎮華勝里民享路３１－１號","user":"陳映如","行業代號":null,"market_name":["冰果店、冷（熱）飲店"],"行業代號1":null,"名稱1":null,"行業代號2":null,"名稱2":null,"行業代號3":null,"名稱3":null,"category":["餐飲"],"id":20035001,"pay_list":"","pay_tool":""},{"index":84,"shop":"暗光百年老店","zone":"雲嘉南","city":"雲林縣","area":"北港鎮","market_address":"雲林縣北港鎮華勝里３鄰民有路２２―１號","user":"陳威豪","行業代號":null,"market_name":["麵店、小吃店"],"行業代號1":null,"名稱1":null,"行業代號2":null,"名稱2":null,"行業代號3":null,"名稱3":null,"category":["餐飲"],"id":20039505,"pay_list":"","pay_tool":""},{"index":85,"shop":"攤販","zone":"雲嘉南","city":"雲林縣","area":"北港鎮","market_address":"雲林縣北港鎮仁安里公民路嘉義客運北港站邊第１號","user":"陳世方","行業代號":null,"market_name":["麵店、小吃店"],"行業代號1":null,"名稱1":null,"行業代號2":null,"名稱2":null,"行業代號3":null,"名稱3":null,"category":["餐飲"],"id":20039507,"pay_list":"","pay_tool":""},{"index":86,"shop":"攤販","zone":"雲嘉南","city":"雲林縣","area":"北港鎮","market_address":"雲林縣北港鎮仁安里公民路嘉義客運邊第６號","user":"蔡東陽","行業代號":null,"market_name":["麵店、小吃店"],"行業代號1":null,"名稱1":null,"行業代號2":null,"名稱2":null,"行業代號3":null,"名稱3":null,"category":["餐飲"],"id":20039508,"pay_list":"","pay_tool":""},{"index":87,"shop":"三雅紅茶大王","zone":"雲嘉南","city":"雲林縣","area":"北港鎮","market_address":"雲林縣北港鎮華勝里公園路６３號","user":"陳雅賢","行業代號":null,"market_name":["冰果店、冷（熱）飲店"],"行業代號1":null,"名稱1":null,"行業代號2":null,"名稱2":null,"行業代號3":null,"名稱3":null,"category":["餐飲"],"id":20039511,"pay_list":"","pay_tool":""},{"index":88,"shop":"鄉村超低溫生魚片專賣店","zone":"雲嘉南","city":"雲林縣","area":"北港鎮","market_address":"雲林縣北港鎮大同里文化路１５０號","user":"劉淑玲","行業代號":null,"market_name":["餐館、餐廳"],"行業代號1":null,"名稱1":null,"行業代號2":null,"名稱2":null,"行業代號3":null,"名稱3":null,"category":["餐飲"],"id":20039760,"pay_list":"","pay_tool":""},{"index":89,"shop":"吳芳彥","zone":"雲嘉南","city":"雲林縣","area":"北港鎮","market_address":"雲林縣北港鎮華勝里民政路１０６號","user":"吳芳彥","行業代號":null,"market_name":["早餐店"],"行業代號1":null,"名稱1":null,"行業代號2":null,"名稱2":null,"行業代號3":null,"名稱3":null,"category":["餐飲"],"id":20039765,"pay_list":"","pay_tool":""},{"index":90,"shop":"嘉義火雞肉飯","zone":"雲嘉南","city":"雲林縣","area":"北港鎮","market_address":"雲林縣北港鎮華勝里公園路５１號","user":"湯慶生","行業代號":null,"market_name":["麵店、小吃店"],"行業代號1":null,"名稱1":null,"行業代號2":null,"名稱2":null,"行業代號3":null,"名稱3":null,"category":["餐飲"],"id":20039766,"pay_list":"","pay_tool":""},{"index":91,"shop":"廣味軒熱炒","zone":"雲嘉南","city":"雲林縣","area":"北港鎮","market_address":"雲林縣北港鎮華勝里大同路３５６號","user":"黃崇益","行業代號":null,"market_name":["麵店、小吃店"],"行業代號1":null,"名稱1":null,"行業代號2":null,"名稱2":null,"行業代號3":null,"名稱3":null,"category":["餐飲"],"id":20040953,"pay_list":"","pay_tool":""},{"index":92,"shop":"李佳明","zone":"雲嘉南","city":"雲林縣","area":"北港鎮","market_address":"雲林縣北港鎮仁和里公民路４２號","user":"李佳明","行業代號":null,"market_name":["麵店、小吃店","經營網路購物"],"行業代號1":null,"名稱1":null,"行業代號2":null,"名稱2":null,"行業代號3":null,"名稱3":null,"category":["餐飲"],"id":20041207,"pay_list":"","pay_tool":""},{"index":93,"shop":"漢鼎快餐店","zone":"雲嘉南","city":"雲林縣","area":"北港鎮","market_address":"雲林縣北港鎮華勝里華勝路６６號","user":"姚敦瀚","行業代號":null,"market_name":["便當、自助餐店"],"行業代號1":null,"名稱1":null,"行業代號2":null,"名稱2":null,"行業代號3":null,"名稱3":null,"category":["餐飲"],"id":20041269,"pay_list":"","pay_tool":""},{"index":94,"shop":"路上有花","zone":"雲嘉南","city":"雲林縣","area":"北港鎮","market_address":"雲林縣北港鎮華勝里文昌路１５８號１樓","user":"林靜如","行業代號":null,"market_name":["餐館、餐廳"],"行業代號1":null,"名稱1":null,"行業代號2":null,"名稱2":null,"行業代號3":null,"名稱3":null,"category":["餐飲"],"id":20041344,"pay_list":"","pay_tool":""},{"index":95,"shop":"手厚","zone":"雲嘉南","city":"雲林縣","area":"北港鎮","market_address":"雲林縣北港鎮華勝里華興街４１號","user":"蘇峯毅","行業代號":null,"market_name":["餐館、餐廳"],"行業代號1":null,"名稱1":null,"行業代號2":null,"名稱2":null,"行業代號3":null,"名稱3":null,"category":["餐飲"],"id":20041594,"pay_list":"","pay_tool":""},{"index":96,"shop":"一等涼","zone":"雲嘉南","city":"雲林縣","area":"北港鎮","market_address":"雲林縣北港鎮大同里中正路６２―２號","user":"蔡明峰","行業代號":null,"market_name":["冰果店、冷（熱）飲店"],"行業代號1":null,"名稱1":null,"行業代號2":null,"名稱2":null,"行業代號3":null,"名稱3":null,"category":["餐飲"],"id":20041740,"pay_list":"","pay_tool":""},{"index":97,"shop":"陳雅琴","zone":"雲嘉南","city":"雲林縣","area":"北港鎮","market_address":"雲林縣北港鎮華勝里民享路２２號旁","user":"陳雅琴","行業代號":null,"market_name":["麵店、小吃店"],"行業代號1":null,"名稱1":null,"行業代號2":null,"名稱2":null,"行業代號3":null,"名稱3":null,"category":["餐飲"],"id":20041844,"pay_list":"","pay_tool":""},{"index":98,"shop":"芬媽咪魔法廚房","zone":"雲嘉南","city":"雲林縣","area":"北港鎮","market_address":"雲林縣北港鎮華勝里文仁路２８５號","user":"黃麗芬","行業代號":null,"market_name":["餐館、餐廳"],"行業代號1":null,"名稱1":null,"行業代號2":null,"名稱2":null,"行業代號3":null,"名稱3":null,"category":["餐飲"],"id":20041998,"pay_list":"","pay_tool":""},{"index":99,"shop":"俊傑商行","zone":"雲嘉南","city":"雲林縣","area":"北港鎮","market_address":"雲林縣北港鎮共榮里義民路９６―３號","user":"黃永松","行業代號":null,"market_name":["早餐店"],"行業代號1":null,"名稱1":null,"行業代號2":null,"名稱2":null,"行業代號3":null,"名稱3":null,"category":["餐飲"],"id":20042137,"pay_list":"","pay_tool":""},{"index":100,"shop":"鍋棧","zone":"雲嘉南","city":"雲林縣","area":"北港鎮","market_address":"雲林縣北港鎮義民里民主路５９號","user":"蔡詔宇","行業代號":null,"market_name":["麵店、小吃店"],"行業代號1":null,"名稱1":null,"行業代號2":null,"名稱2":null,"行業代號3":null,"名稱3":null,"category":["餐飲"],"id":20042155,"pay_list":"","pay_tool":""},{"index":101,"shop":"谷二町日本料理","zone":"雲嘉南","city":"雲林縣","area":"北港鎮","market_address":"雲林縣北港鎮華勝里華勝路１７５號","user":"李承煜","行業代號":null,"market_name":["餐館、餐廳"],"行業代號1":null,"名稱1":null,"行業代號2":null,"名稱2":null,"行業代號3":null,"名稱3":null,"category":["餐飲"],"id":20042293,"pay_list":"","pay_tool":""},{"index":102,"shop":"美而美漢堡店","zone":"雲嘉南","city":"雲林縣","area":"北港鎮","market_address":"雲林縣北港鎮華勝里文昌路９０號","user":"黃詠琦","行業代號":null,"market_name":["早餐店"],"行業代號1":null,"名稱1":null,"行業代號2":null,"名稱2":null,"行業代號3":null,"名稱3":null,"category":["餐飲"],"id":20045499,"pay_list":"","pay_tool":""},{"index":103,"shop":"紅茶王北港店","zone":"雲嘉南","city":"雲林縣","area":"北港鎮","market_address":"雲林縣北港鎮新街里０１８鄰太平路３３號","user":"蔡彥琦","行業代號":null,"market_name":["冰果店、冷（熱）飲店"],"行業代號1":null,"名稱1":null,"行業代號2":null,"名稱2":null,"行業代號3":null,"名稱3":null,"category":["餐飲"],"id":20048670,"pay_list":"","pay_tool":""},{"index":104,"shop":"峰碩商行","zone":"雲嘉南","city":"雲林縣","area":"北港鎮","market_address":"雲林縣北港鎮大同里文化路１２９號","user":"許峰碩","行業代號":null,"market_name":["冰果店、冷（熱）飲店"],"行業代號1":null,"名稱1":null,"行業代號2":null,"名稱2":null,"行業代號3":null,"名稱3":null,"category":["餐飲"],"id":20048810,"pay_list":"","pay_tool":""},{"index":105,"shop":"沅樟鵝肉專賣店","zone":"雲嘉南","city":"雲林縣","area":"北港鎮","market_address":"雲林縣北港鎮賜福里中正路５２號","user":"吳建旻","行業代號":null,"market_name":["麵店、小吃店"],"行業代號1":null,"名稱1":null,"行業代號2":null,"名稱2":null,"行業代號3":null,"名稱3":null,"category":["餐飲"],"id":20048871,"pay_list":"","pay_tool":""},{"index":106,"shop":"輝哥豆花","zone":"雲嘉南","city":"雲林縣","area":"北港鎮","market_address":"雲林縣北港鎮華勝里民樂路１２３號","user":"李建輝","行業代號":null,"market_name":["冰果店、冷（熱）飲店"],"行業代號1":null,"名稱1":null,"行業代號2":null,"名稱2":null,"行業代號3":null,"名稱3":null,"category":["餐飲"],"id":20048886,"pay_list":"","pay_tool":""},{"index":107,"shop":"黃重銘","zone":"雲嘉南","city":"雲林縣","area":"北港鎮","market_address":"雲林縣北港鎮華勝里公園路５３號","user":"黃重銘","行業代號":null,"market_name":["麵店、小吃店"],"行業代號1":null,"名稱1":null,"行業代號2":null,"名稱2":null,"行業代號3":null,"名稱3":null,"category":["餐飲"],"id":20049005,"pay_list":"","pay_tool":""},{"index":108,"shop":"楊玉華","zone":"雲嘉南","city":"雲林縣","area":"北港鎮","market_address":"雲林縣北港鎮華勝里民享路１０號","user":"楊玉華","行業代號":null,"market_name":["麵店、小吃店"],"行業代號1":null,"名稱1":null,"行業代號2":null,"名稱2":null,"行業代號3":null,"名稱3":null,"category":["餐飲"],"id":20049384,"pay_list":"","pay_tool":""},{"index":109,"shop":"顏鴻麟","zone":"雲嘉南","city":"雲林縣","area":"北港鎮","market_address":"雲林縣北港鎮華勝里民享路６號","user":"顏鴻麟","行業代號":null,"market_name":["麵店、小吃店"],"行業代號1":null,"名稱1":null,"行業代號2":null,"名稱2":null,"行業代號3":null,"名稱3":null,"category":["餐飲"],"id":20049412,"pay_list":"","pay_tool":""},{"index":110,"shop":"新味珍原汁牛肉麵","zone":"雲嘉南","city":"雲林縣","area":"北港鎮","market_address":"雲林縣北港鎮西勢里文化路４０―６號","user":"李清和","行業代號":null,"market_name":["麵店、小吃店"],"行業代號1":null,"名稱1":null,"行業代號2":null,"名稱2":null,"行業代號3":null,"名稱3":null,"category":["餐飲"],"id":20049573,"pay_list":"","pay_tool":""},{"index":111,"shop":"吳秋美","zone":"雲嘉南","city":"雲林縣","area":"北港鎮","market_address":"雲林縣北港鎮仁和里大同路３７號１樓","user":"吳秋美","行業代號":null,"market_name":["麵店、小吃店"],"行業代號1":null,"名稱1":null,"行業代號2":null,"名稱2":null,"行業代號3":null,"名稱3":null,"category":["餐飲"],"id":20049684,"pay_list":"","pay_tool":""},{"index":112,"shop":"木木早午餐店","zone":"雲嘉南","city":"雲林縣","area":"北港鎮","market_address":"雲林縣北港鎮華勝里民治路１９－１０號","user":"林筠涵","行業代號":null,"market_name":["早餐店"],"行業代號1":null,"名稱1":null,"行業代號2":null,"名稱2":null,"行業代號3":null,"名稱3":null,"category":["餐飲"],"id":20049687,"pay_list":"","pay_tool":""},{"index":113,"shop":"吳輝煌","zone":"雲嘉南","city":"雲林縣","area":"北港鎮","market_address":"雲林縣北港鎮仁和里博愛路１３６―４號","user":"吳輝煌","行業代號":null,"market_name":["麵店、小吃店"],"行業代號1":null,"名稱1":null,"行業代號2":null,"名稱2":null,"行業代號3":null,"名稱3":null,"category":["餐飲"],"id":20049711,"pay_list":"","pay_tool":""},{"index":114,"shop":"文仁牛排館","zone":"雲嘉南","city":"雲林縣","area":"北港鎮","market_address":"雲林縣北港鎮樹腳里０１３鄰文仁路３９８號","user":"吳東祐","行業代號":null,"market_name":["餐館、餐廳"],"行業代號1":null,"名稱1":null,"行業代號2":null,"名稱2":null,"行業代號3":null,"名稱3":null,"category":["餐飲"],"id":20049719,"pay_list":"","pay_tool":""},{"index":115,"shop":"黃連春","zone":"雲嘉南","city":"雲林縣","area":"北港鎮","market_address":"雲林縣北港鎮賜福里義民路１１０號","user":"黃連春","行業代號":null,"market_name":["麵店、小吃店"],"行業代號1":null,"名稱1":null,"行業代號2":null,"名稱2":null,"行業代號3":null,"名稱3":null,"category":["餐飲"],"id":20049744,"pay_list":"","pay_tool":""},{"index":116,"shop":"陳瑞卿","zone":"雲嘉南","city":"雲林縣","area":"北港鎮","market_address":"雲林縣北港鎮中和里光明路９號","user":"陳瑞卿","行業代號":null,"market_name":["麵店、小吃店"],"行業代號1":null,"名稱1":null,"行業代號2":null,"名稱2":null,"行業代號3":null,"名稱3":null,"category":["餐飲"],"id":20049772,"pay_list":["LINE PAY MONEY"],"pay_tool":["行動支付"]},{"index":117,"shop":"冰緣企業社","zone":"雲嘉南","city":"雲林縣","area":"北港鎮","market_address":"雲林縣北港鎮新街里新德路１２３號Ｂ１樓","user":"吳秀卿","行業代號":null,"market_name":["冰果店、冷（熱）飲店"],"行業代號1":null,"名稱1":null,"行業代號2":null,"名稱2":null,"行業代號3":null,"名稱3":null,"category":["餐飲"],"id":20049857,"pay_list":"","pay_tool":""},{"index":118,"shop":"蘇家飲料店","zone":"雲嘉南","city":"雲林縣","area":"北港鎮","market_address":"雲林縣北港鎮共榮里民主路２５號","user":"蘇若禎","行業代號":null,"market_name":["冰果店、冷（熱）飲店"],"行業代號1":null,"名稱1":null,"行業代號2":null,"名稱2":null,"行業代號3":null,"名稱3":null,"category":["餐飲"],"id":20049939,"pay_list":"","pay_tool":""},{"index":119,"shop":"８鍋臭臭鍋","zone":"雲嘉南","city":"雲林縣","area":"北港鎮","market_address":"雲林縣北港鎮樹腳里大同路５１１號","user":"陳嘉偉","行業代號":null,"market_name":["餐館、餐廳"],"行業代號1":null,"名稱1":null,"行業代號2":null,"名稱2":null,"行業代號3":null,"名稱3":null,"category":["餐飲"],"id":20050038,"pay_list":"","pay_tool":""},{"index":120,"shop":"那一家","zone":"雲嘉南","city":"雲林縣","area":"北港鎮","market_address":"雲林縣北港鎮大同里文化路７６號","user":"籃心怡","行業代號":null,"market_name":["早餐店"],"行業代號1":null,"名稱1":null,"行業代號2":null,"名稱2":null,"行業代號3":null,"名稱3":null,"category":["餐飲"],"id":20053745,"pay_list":"","pay_tool":""},{"index":121,"shop":"漁吧燒烤熱炒","zone":"雲嘉南","city":"雲林縣","area":"北港鎮","market_address":"雲林縣北港鎮華勝里民樂路８號","user":"吳明洲","行業代號":null,"market_name":["餐館、餐廳"],"行業代號1":null,"名稱1":null,"行業代號2":null,"名稱2":null,"行業代號3":null,"名稱3":null,"category":["餐飲"],"id":20053901,"pay_list":"","pay_tool":""},{"index":122,"shop":"民樂早餐店","zone":"雲嘉南","city":"雲林縣","area":"北港鎮","market_address":"雲林縣北港鎮新街里民樂路１６３號","user":"李永進","行業代號":null,"market_name":["早餐店"],"行業代號1":null,"名稱1":null,"行業代號2":null,"名稱2":null,"行業代號3":null,"名稱3":null,"category":["餐飲"],"id":20053980,"pay_list":"","pay_tool":""},{"index":123,"shop":"陳瑞湄","zone":"雲嘉南","city":"雲林縣","area":"北港鎮","market_address":"雲林縣北港鎮文仁路與北辰路口附近（文仁路上）","user":"陳瑞湄","行業代號":null,"market_name":["早餐店"],"行業代號1":null,"名稱1":null,"行業代號2":null,"名稱2":null,"行業代號3":null,"名稱3":null,"category":["餐飲"],"id":20053990,"pay_list":"","pay_tool":""},{"index":124,"shop":"小辣椒自助餐","zone":"雲嘉南","city":"雲林縣","area":"北港鎮","market_address":"雲林縣北港鎮華勝里民有路２１號","user":"黃同佑","行業代號":null,"market_name":["便當、自助餐店"],"行業代號1":null,"名稱1":null,"行業代號2":null,"名稱2":null,"行業代號3":null,"名稱3":null,"category":["餐飲"],"id":20054037,"pay_list":"","pay_tool":""},{"index":125,"shop":"蕭啓志","zone":"雲嘉南","city":"雲林縣","area":"北港鎮","market_address":"雲林縣北港鎮新街里北辰路９、１０、１１攤位","user":"蕭??志","行業代號":null,"market_name":["麵店、小吃店"],"行業代號1":null,"名稱1":null,"行業代號2":null,"名稱2":null,"行業代號3":null,"名稱3":null,"category":["餐飲"],"id":20054159,"pay_list":"","pay_tool":""},{"index":126,"shop":"民主素食鹽酥Ｇ","zone":"雲嘉南","city":"雲林縣","area":"北港鎮","market_address":"雲林縣北港鎮共榮里民主路５６－１號","user":"蔡勇立","行業代號":null,"market_name":["麵店、小吃店"],"行業代號1":null,"名稱1":null,"行業代號2":null,"名稱2":null,"行業代號3":null,"名稱3":null,"category":["餐飲"],"id":20054640,"pay_list":"","pay_tool":""},{"index":127,"shop":"張富翔","zone":"雲嘉南","city":"雲林縣","area":"北港鎮","market_address":"雲林縣北港鎮光復里大同路２０５號","user":"張富翔","行業代號":null,"market_name":["麵店、小吃店"],"行業代號1":null,"名稱1":null,"行業代號2":null,"名稱2":null,"行業代號3":null,"名稱3":null,"category":["餐飲"],"id":20054697,"pay_list":"","pay_tool":""},{"index":128,"shop":"鍋霸火烤兩吃","zone":"雲嘉南","city":"雲林縣","area":"北港鎮","market_address":"雲林縣北港鎮華勝里０２０鄰大同路３８８號","user":"吳佳林","行業代號":null,"market_name":["吃到飽餐廳"],"行業代號1":null,"名稱1":null,"行業代號2":null,"名稱2":null,"行業代號3":null,"名稱3":null,"category":["餐飲"],"id":20057637,"pay_list":"","pay_tool":""},{"index":129,"shop":"聖母便當","zone":"雲嘉南","city":"雲林縣","area":"北港鎮","market_address":"雲林縣北港鎮新街里聖母路６０號（新東段店鋪第１０－１號店鋪）","user":"吳日新","行業代號":null,"market_name":["便當、自助餐店"],"行業代號1":null,"名稱1":null,"行業代號2":null,"名稱2":null,"行業代號3":null,"名稱3":null,"category":["餐飲"],"id":20057924,"pay_list":"","pay_tool":""},{"index":130,"shop":"泡泡龍茶飲","zone":"雲嘉南","city":"雲林縣","area":"北港鎮","market_address":"雲林縣北港鎮華勝里公園路３４號","user":"張遠銘","行業代號":null,"market_name":["冰果店、冷（熱）飲店"],"行業代號1":null,"名稱1":null,"行業代號2":null,"名稱2":null,"行業代號3":null,"名稱3":null,"category":["餐飲"],"id":20061088,"pay_list":"","pay_tool":""},{"index":131,"shop":"蘇政陽阿美水餃","zone":"雲嘉南","city":"雲林縣","area":"北港鎮","market_address":"雲林縣北港鎮華勝里公園路１１５號前","user":"蘇政陽","行業代號":null,"market_name":["麵店、小吃店"],"行業代號1":null,"名稱1":null,"行業代號2":null,"名稱2":null,"行業代號3":null,"名稱3":null,"category":["餐飲"],"id":20061089,"pay_list":"","pay_tool":""},{"index":132,"shop":"大眾牛肉麵店","zone":"雲嘉南","city":"雲林縣","area":"北港鎮","market_address":"雲林縣北港鎮華勝里民樂路１５５號","user":"黃建成","行業代號":null,"market_name":["麵店、小吃店"],"行業代號1":null,"名稱1":null,"行業代號2":null,"名稱2":null,"行業代號3":null,"名稱3":null,"category":["餐飲"],"id":20061090,"pay_list":"","pay_tool":""},{"index":133,"shop":"利昌牛排館","zone":"雲嘉南","city":"雲林縣","area":"北港鎮","market_address":"雲林縣北港鎮華勝里２２鄰華勝路１５６－６號","user":"楊孟修","行業代號":null,"market_name":["餐館、餐廳"],"行業代號1":null,"名稱1":null,"行業代號2":null,"名稱2":null,"行業代號3":null,"名稱3":null,"category":["餐飲"],"id":20061095,"pay_list":"","pay_tool":""},{"index":134,"shop":"木瓜田冷飲店","zone":"雲嘉南","city":"雲林縣","area":"北港鎮","market_address":"雲林縣北港鎮仁安里文化路７９號","user":"王清波","行業代號":null,"market_name":["冰果店、冷（熱）飲店"],"行業代號1":null,"名稱1":null,"行業代號2":null,"名稱2":null,"行業代號3":null,"名稱3":null,"category":["餐飲"],"id":20061125,"pay_list":"","pay_tool":""},{"index":135,"shop":"陳記小吃部","zone":"雲嘉南","city":"雲林縣","area":"北港鎮","market_address":"雲林縣北港鎮華勝里公園路２號","user":"陳清安","行業代號":null,"market_name":["餐館、餐廳"],"行業代號1":null,"名稱1":null,"行業代號2":null,"名稱2":null,"行業代號3":null,"名稱3":null,"category":["餐飲"],"id":20063040,"pay_list":"","pay_tool":""},{"index":136,"shop":"和德昌股份有限公司北港華勝分公司","zone":"雲嘉南","city":"雲林縣","area":"北港鎮","market_address":"雲林縣北港鎮光復里華南路６０號","user":"李昌霖","行業代號":"561114","market_name":["連鎖速食店"],"行業代號1":"","名稱1":"","行業代號2":"","名稱2":"","行業代號3":"","名稱3":"","category":["餐飲"],"id":60002493,"pay_list":null,"pay_tool":null},{"index":137,"shop":"悠旅生活事業股份有限公司北港門市部","zone":"雲嘉南","city":"雲林縣","area":"北港鎮","market_address":"雲林縣北港鎮仁安里華南路３８號","user":"陳瑞堂","行業代號":"563112","market_name":["咖啡館"],"行業代號1":"","名稱1":"","行業代號2":"","名稱2":"","行業代號3":"","名稱3":"","category":["餐飲"],"id":60003417,"pay_list":null,"pay_tool":null},{"index":138,"shop":"風雅商行","zone":"雲嘉南","city":"雲林縣","area":"北港鎮","market_address":"雲林縣北港鎮大同里大同路１２９號","user":"廖瓊珠","行業代號":"563111","market_name":["西點麵包零售","冰果店、冷（熱）飲店","醫療耗材零售"],"行業代號1":"472922","名稱1":"西點麵包零售","行業代號2":"475113","名稱2":"醫療耗材零售","行業代號3":"","名稱3":"","category":["餐飲","糕餅"],"id":60006153,"pay_list":null,"pay_tool":null},{"index":139,"shop":"青松餐廳","zone":"雲嘉南","city":"雲林縣","area":"北港鎮","market_address":"雲林縣北港鎮新街里０３８鄰太平路３６９號","user":"陳清松","行業代號":"561115","market_name":["餐館、餐廳"],"行業代號1":"","名稱1":"","行業代號2":"","名稱2":"","行業代號3":"","名稱3":"","category":["餐飲"],"id":60006807,"pay_list":null,"pay_tool":null},{"index":140,"shop":"鳳緹商行","zone":"雲嘉南","city":"雲林縣","area":"北港鎮","market_address":"雲林縣北港鎮仁安里大同路１８９號","user":"張鳳儀","行業代號":"563111","market_name":["冰果店、冷（熱）飲店"],"行業代號1":"","名稱1":"","行業代號2":"","名稱2":"","行業代號3":"","名稱3":"","category":["餐飲"],"id":60008277,"pay_list":null,"pay_tool":null},{"index":141,"shop":"北港鍋物店","zone":"雲嘉南","city":"雲林縣","area":"北港鎮","market_address":"雲林縣北港鎮新街里華勝路２６０號","user":"李鴻志","行業代號":"561115","market_name":["餐館、餐廳"],"行業代號1":"","名稱1":"","行業代號2":"","名稱2":"","行業代號3":"","名稱3":"","category":["餐飲"],"id":60008279,"pay_list":null,"pay_tool":null},{"index":142,"shop":"益臻國際有限公司","zone":"雲嘉南","city":"雲林縣","area":"北港鎮","market_address":"雲林縣北港鎮南安里民生路１９９號１樓","user":"吳勃毅","行業代號":"561115","market_name":["未分類其他食品、飲料及菸草製品零售","餐館、餐廳"],"行業代號1":"472999","名稱1":"未分類其他食品、飲料及菸草製品零售","行業代號2":"","名稱2":"","行業代號3":"","名稱3":"","category":["餐飲"],"id":60012559,"pay_list":null,"pay_tool":null},{"index":143,"shop":"北港保生堂有限公司","zone":"雲嘉南","city":"雲林縣","area":"北港鎮","market_address":"雲林縣北港鎮中和里中山路６１號１樓","user":"林安樂","行業代號":"563112","market_name":["咖啡館"],"行業代號1":"","名稱1":"","行業代號2":"","名稱2":"","行業代號3":"","名稱3":"","category":["餐飲"],"id":60013789,"pay_list":null,"pay_tool":null},{"index":144,"shop":"青松食品有限公司","zone":"雲嘉南","city":"雲林縣","area":"北港鎮","market_address":"雲林縣北港鎮新街里０３８鄰太平路３６９號","user":"陳清松","行業代號":"561115","market_name":["其他外燴及團膳承包","餐館、餐廳","菸酒零售"],"行業代號1":"562099","名稱1":"其他外燴及團膳承包","行業代號2":"472913","名稱2":"菸酒零售","行業代號3":"","名稱3":"","category":["餐飲"],"id":60016288,"pay_list":null,"pay_tool":null},{"index":145,"shop":"金德美有限公司","zone":"雲嘉南","city":"雲林縣","area":"北港鎮","market_address":"雲林縣北港鎮新街里新西街１６號","user":"林士元","行業代號":"561115","market_name":["旅館","不動產轉租賃","消防設備批發","餐館、餐廳"],"行業代號1":"464913","名稱1":"消防設備批發","行業代號2":"681113","名稱2":"不動產轉租賃","行業代號3":"551012","名稱3":"旅館","category":["餐飲"],"id":60016855,"pay_list":null,"pay_tool":null},{"index":146,"shop":"朝聖餐飲有限公司","zone":"雲嘉南","city":"雲林縣","area":"北港鎮","market_address":"雲林縣北港鎮東華里中山路１６８號２樓之２","user":"王元亨","行業代號":"561115","market_name":["餐館、餐廳"],"行業代號1":"","名稱1":"","行業代號2":"","名稱2":"","行業代號3":"","名稱3":"","category":["餐飲"],"id":60017516,"pay_list":null,"pay_tool":null},{"index":147,"shop":"尊任有限公司","zone":"雲嘉南","city":"雲林縣","area":"北港鎮","market_address":"雲林縣北港鎮華勝里吉祥路１４８號１樓","user":"蔡依凝","行業代號":"563112","market_name":["藝術表演活動籌辦、監製與經紀","工商展覽籌辦","經營網路購物","咖啡館"],"行業代號1":"820212","名稱1":"工商展覽籌辦","行業代號2":"903015","名稱2":"藝術表演活動籌辦、監製與經紀","行業代號3":"487113","名稱3":"經營網路購物","category":["餐飲"],"id":60020914,"pay_list":null,"pay_tool":null},{"index":148,"shop":"澐璽餐飲事業有限公司","zone":"雲嘉南","city":"雲林縣","area":"北港鎮","market_address":"雲林縣北港鎮新街里公園路２７９巷７１號１樓","user":"陳耀文","行業代號":"561115","market_name":["餐館、餐廳"],"行業代號1":"","名稱1":"","行業代號2":"","名稱2":"","行業代號3":"","名稱3":"","category":["餐飲"],"id":60022935,"pay_list":null,"pay_tool":null},{"index":149,"shop":"爭鮮股份有限公司北港門市部","zone":"雲嘉南","city":"雲林縣","area":"北港鎮","market_address":"雲林縣北港鎮光復里華南路１０１號","user":"陳津秋","行業代號":"561114","market_name":["連鎖速食店"],"行業代號1":"","名稱1":"","行業代號2":"","名稱2":"","行業代號3":"","名稱3":"","category":["餐飲"],"id":60025457,"pay_list":null,"pay_tool":null},{"index":150,"shop":"花媽麵食店北港分店","zone":"雲嘉南","city":"雲林縣","area":"北港鎮","market_address":"雲林縣北港鎮光復里華南路１０１號","user":"江蕭壽緞","行業代號":"561113","market_name":["麵店、小吃店"],"行業代號1":"","名稱1":"","行業代號2":"","名稱2":"","行業代號3":"","名稱3":"","category":["餐飲"],"id":60025566,"pay_list":null,"pay_tool":null},{"index":151,"shop":"三商餐飲股份有限公司北港一門市部","zone":"雲嘉南","city":"雲林縣","area":"北港鎮","market_address":"雲林縣北港鎮光復里華南路１０１號","user":"陳翔玢","行業代號":"561115","market_name":["餐館、餐廳"],"行業代號1":"","名稱1":"","行業代號2":"","名稱2":"","行業代號3":"","名稱3":"","category":["餐飲"],"id":60025970,"pay_list":null,"pay_tool":null},{"index":152,"shop":"三商餐飲股份有限公司北港門市部","zone":"雲嘉南","city":"雲林縣","area":"北港鎮","market_address":"雲林縣北港鎮光復里華南路１０１號","user":"陳翔玢","行業代號":"561115","market_name":["餐館、餐廳"],"行業代號1":"","名稱1":"","行業代號2":"","名稱2":"","行業代號3":"","名稱3":"","category":["餐飲"],"id":60025971,"pay_list":null,"pay_tool":null},{"index":153,"shop":"一二三鴨莊","zone":"雲嘉南","city":"雲林縣","area":"北港鎮","market_address":"雲林縣北港鎮大同里大同路１８６號","user":"李龍彬","行業代號":"561112","market_name":["便當、自助餐店"],"行業代號1":"","名稱1":"","行業代號2":"","名稱2":"","行業代號3":"","名稱3":"","category":["餐飲"],"id":60037078,"pay_list":null,"pay_tool":null},{"index":154,"shop":"櫻之演歌場","zone":"雲嘉南","city":"雲林縣","area":"北港鎮","market_address":"雲林縣北港鎮華勝里民治路４６號１樓","user":"吳敏卿","行業代號":"561113","market_name":["冰果店、冷（熱）飲店","麵店、小吃店","視唱中心（ＫＴＶ）"],"行業代號1":"563111","名稱1":"冰果店、冷（熱）飲店","行業代號2":"932211","名稱2":"視唱中心（ＫＴＶ）","行業代號3":"","名稱3":"","category":["餐飲"],"id":60038509,"pay_list":null,"pay_tool":null},{"index":155,"shop":"老受鴨肉飯","zone":"雲嘉南","city":"雲林縣","area":"北港鎮","market_address":"雲林縣北港鎮東華里３鄰中山路１０４號１樓","user":"蔡柏壬","行業代號":"561113","market_name":["麵店、小吃店"],"行業代號1":"","名稱1":"","行業代號2":"","名稱2":"","行業代號3":"","名稱3":"","category":["餐飲"],"id":60039728,"pay_list":null,"pay_tool":null},{"index":156,"shop":"福泉餐飲店","zone":"雲嘉南","city":"雲林縣","area":"北港鎮","market_address":"雲林縣北港鎮華勝里１１鄰公園路９５號１樓","user":"徐梅雅","行業代號":"563111","market_name":["冰果店、冷（熱）飲店","麵店、小吃店"],"行業代號1":"561113","名稱1":"麵店、小吃店","行業代號2":"","名稱2":"","行業代號3":"","名稱3":"","category":["餐飲"],"id":60041430,"pay_list":null,"pay_tool":null},{"index":157,"shop":"趙街尾鴨肉??店","zone":"雲嘉南","city":"雲林縣","area":"北港鎮","market_address":"雲林縣北港鎮東陽里中山路３８號１樓","user":"趙正忠","行業代號":"561113","market_name":["麵店、小吃店"],"行業代號1":"","名稱1":"","行業代號2":"","名稱2":"","行業代號3":"","名稱3":"","category":["餐飲"],"id":60043030,"pay_list":null,"pay_tool":null},{"index":158,"shop":"佳萱冷熱飲店","zone":"雲嘉南","city":"雲林縣","area":"北港鎮","market_address":"雲林縣北港鎮華勝里文化路１６７號","user":"黃珮婷","行業代號":"563111","market_name":["冰果店、冷（熱）飲店"],"行業代號1":"","名稱1":"","行業代號2":"","名稱2":"","行業代號3":"","名稱3":"","category":["餐飲"],"id":60043465,"pay_list":null,"pay_tool":null},{"index":159,"shop":"飲和食德食品行","zone":"雲嘉南","city":"雲林縣","area":"北港鎮","market_address":"雲林縣北港鎮大同里１６鄰太平路１８巷１９號１樓","user":"陳煥綸","行業代號":"562099","market_name":["其他外燴及團膳承包"],"行業代號1":"","名稱1":"","行業代號2":"","名稱2":"","行業代號3":"","名稱3":"","category":["餐飲"],"id":60043867,"pay_list":null,"pay_tool":null},{"index":160,"shop":"米亞糖茶行","zone":"雲嘉南","city":"雲林縣","area":"北港鎮","market_address":"雲林縣北港鎮東陽里中山路８６號１樓","user":"王禹霏","行業代號":"563111","market_name":["冰果店、冷（熱）飲店"],"行業代號1":"","名稱1":"","行業代號2":"","名稱2":"","行業代號3":"","名稱3":"","category":["餐飲"],"id":60048908,"pay_list":null,"pay_tool":null},{"index":161,"shop":"阿寶晨食館","zone":"雲嘉南","city":"雲林縣","area":"北港鎮","market_address":"雲林縣北港鎮華勝里１７鄰民享路３８號","user":"吳純婷","行業代號":"561111","market_name":["早餐店"],"行業代號1":"","名稱1":"","行業代號2":"","名稱2":"","行業代號3":"","名稱3":"","category":["餐飲"],"id":60048919,"pay_list":null,"pay_tool":null},{"index":162,"shop":"穎定咖啡店","zone":"雲嘉南","city":"雲林縣","area":"北港鎮","market_address":"雲林縣北港鎮華勝里公園路１８―６號１樓","user":"蔡文定","行業代號":"563112","market_name":["咖啡館"],"行業代號1":"","名稱1":"","行業代號2":"","名稱2":"","行業代號3":"","名稱3":"","category":["餐飲"],"id":60058659,"pay_list":null,"pay_tool":null},{"index":163,"shop":"好收冷飲店","zone":"雲嘉南","city":"雲林縣","area":"北港鎮","market_address":"雲林縣北港鎮好收里好收路１１１號一樓","user":"王智堯","行業代號":"563111","market_name":["冰果店、冷（熱）飲店"],"行業代號1":"","名稱1":"","行業代號2":"","名稱2":"","行業代號3":"","名稱3":"","category":["餐飲"],"id":60058676,"pay_list":null,"pay_tool":null},{"index":164,"shop":"豐味便當工廠","zone":"雲嘉南","city":"雲林縣","area":"北港鎮","market_address":"雲林縣北港鎮劉厝里劉厝路１３７―３號１樓","user":"吳蔡花","行業代號":"561112","market_name":["便當、自助餐店"],"行業代號1":"","名稱1":"","行業代號2":"","名稱2":"","行業代號3":"","名稱3":"","category":["餐飲"],"id":60058690,"pay_list":null,"pay_tool":null},{"index":165,"shop":"店小二小吃店","zone":"雲嘉南","city":"雲林縣","area":"北港鎮","market_address":"雲林縣北港鎮新街里文仁路３４６號１樓","user":"楊宜樺","行業代號":"561115","market_name":["餐館、餐廳"],"行業代號1":"","名稱1":"","行業代號2":"","名稱2":"","行業代號3":"","名稱3":"","category":["餐飲"],"id":60058720,"pay_list":null,"pay_tool":null},{"index":166,"shop":"青森實業社","zone":"雲嘉南","city":"雲林縣","area":"北港鎮","market_address":"雲林縣北港鎮樹腳里文仁路３８４號１樓","user":"許彤瑤","行業代號":"563111","market_name":["冰果店、冷（熱）飲店"],"行業代號1":"","名稱1":"","行業代號2":"","名稱2":"","行業代號3":"","名稱3":"","category":["餐飲"],"id":60058741,"pay_list":null,"pay_tool":null},{"index":167,"shop":"帛瓚企業社","zone":"雲嘉南","city":"雲林縣","area":"北港鎮","market_address":"雲林縣北港鎮西勢里文化路３７―６號","user":"陳政哲","行業代號":"563112","market_name":["咖啡館"],"行業代號1":"","名稱1":"","行業代號2":"","名稱2":"","行業代號3":"","名稱3":"","category":["餐飲"],"id":60058755,"pay_list":null,"pay_tool":null},{"index":168,"shop":"忠呈溫州大餛飩","zone":"雲嘉南","city":"雲林縣","area":"北港鎮","market_address":"雲林縣北港鎮大同里復興路３９號１樓","user":"蘇維呈","行業代號":"561113","market_name":["麵店、小吃店"],"行業代號1":"","名稱1":"","行業代號2":"","名稱2":"","行業代號3":"","名稱3":"","category":["餐飲"],"id":60058774,"pay_list":null,"pay_tool":null},{"index":169,"shop":"鱻田便當","zone":"雲嘉南","city":"雲林縣","area":"北港鎮","market_address":"雲林縣北港鎮華勝里華興街１６號１樓","user":"張森田","行業代號":"561112","market_name":["便當、自助餐店"],"行業代號1":"","名稱1":"","行業代號2":"","名稱2":"","行業代號3":"","名稱3":"","category":["餐飲"],"id":60059341,"pay_list":null,"pay_tool":null},{"index":170,"shop":"天后食品行","zone":"雲嘉南","city":"雲林縣","area":"北港鎮","market_address":"雲林縣北港鎮中和里中山路９３號１樓","user":"林翠玲","行業代號":"563111","market_name":["冰果店、冷（熱）飲店"],"行業代號1":"","名稱1":"","行業代號2":"","名稱2":"","行業代號3":"","名稱3":"","category":["餐飲"],"id":60059806,"pay_list":null,"pay_tool":null},{"index":171,"shop":"蘭叨小吃店","zone":"雲嘉南","city":"雲林縣","area":"北港鎮","market_address":"雲林縣北港鎮華勝里華勝路２０２號","user":"李文財","行業代號":"561115","market_name":["餐館、餐廳"],"行業代號1":"","名稱1":"","行業代號2":"","名稱2":"","行業代號3":"","名稱3":"","category":["餐飲"],"id":60059810,"pay_list":null,"pay_tool":null},{"index":172,"shop":"九久醇義麵坊","zone":"雲嘉南","city":"雲林縣","area":"北港鎮","market_address":"雲林縣北港鎮仁和里公民路３７號１樓","user":"曾馨儀","行業代號":"561115","market_name":["餐館、餐廳"],"行業代號1":"","名稱1":"","行業代號2":"","名稱2":"","行業代號3":"","名稱3":"","category":["餐飲"],"id":60059821,"pay_list":null,"pay_tool":null},{"index":173,"shop":"食邑簡餐店","zone":"雲嘉南","city":"雲林縣","area":"北港鎮","market_address":"雲林縣北港鎮華勝里民治路１９－８號","user":"吳美蒨","行業代號":"561115","market_name":["餐館、餐廳"],"行業代號1":"","名稱1":"","行業代號2":"","名稱2":"","行業代號3":"","名稱3":"","category":["餐飲"],"id":60059839,"pay_list":null,"pay_tool":null},{"index":174,"shop":"泔田企業社","zone":"雲嘉南","city":"雲林縣","area":"北港鎮","market_address":"雲林縣北港鎮共榮里１０鄰中山路１５３號","user":"鄧湘羚","行業代號":"563111","market_name":["冰果店、冷（熱）飲店"],"行業代號1":"","名稱1":"","行業代號2":"","名稱2":"","行業代號3":"","名稱3":"","category":["餐飲"],"id":60059850,"pay_list":null,"pay_tool":null},{"index":175,"shop":"永袁小吃部","zone":"雲嘉南","city":"雲林縣","area":"北港鎮","market_address":"雲林縣北港鎮華勝里華勝路１３４－１號","user":"孫榮華","行業代號":"561115","market_name":["餐館、餐廳"],"行業代號1":"","名稱1":"","行業代號2":"","名稱2":"","行業代號3":"","名稱3":"","category":["餐飲"],"id":60060313,"pay_list":null,"pay_tool":null},{"index":176,"shop":"幸福燈塔複合式餐飲","zone":"雲嘉南","city":"雲林縣","area":"北港鎮","market_address":"雲林縣北港鎮大同里復興街１９號","user":"郭建志","行業代號":"561114","market_name":["連鎖速食店"],"行業代號1":"","名稱1":"","行業代號2":"","名稱2":"","行業代號3":"","名稱3":"","category":["餐飲"],"id":60060341,"pay_list":null,"pay_tool":null},{"index":177,"shop":"釬利冷飲店","zone":"雲嘉南","city":"雲林縣","area":"北港鎮","market_address":"雲林縣北港鎮華勝里華勝路５５號１樓","user":"李莉虹","行業代號":"563111","market_name":["冰果店、冷（熱）飲店"],"行業代號1":"","名稱1":"","行業代號2":"","名稱2":"","行業代號3":"","名稱3":"","category":["餐飲"],"id":60060444,"pay_list":null,"pay_tool":null},{"index":178,"shop":"八方通路館","zone":"雲嘉南","city":"雲林縣","area":"北港鎮","market_address":"雲林縣北港鎮華勝里民政路１４－１號","user":"黃鈺雅","行業代號":"561113","market_name":["麵店、小吃店"],"行業代號1":"","名稱1":"","行業代號2":"","名稱2":"","行業代號3":"","名稱3":"","category":["餐飲"],"id":60069533,"pay_list":null,"pay_tool":null},{"index":179,"shop":"義民扁食店","zone":"雲嘉南","city":"雲林縣","area":"北港鎮","market_address":"雲林縣北港鎮西勢里義民路１９號","user":"高燦雄","行業代號":"561113","market_name":["麵店、小吃店"],"行業代號1":"","名稱1":"","行業代號2":"","名稱2":"","行業代號3":"","名稱3":"","category":["餐飲"],"id":60069563,"pay_list":null,"pay_tool":null},{"index":180,"shop":"紅妙香素食店","zone":"雲嘉南","city":"雲林縣","area":"北港鎮","market_address":"雲林縣北港鎮華勝里大同路２０２號１樓","user":"蔡易霖","行業代號":"561113","market_name":["麵店、小吃店"],"行業代號1":"","名稱1":"","行業代號2":"","名稱2":"","行業代號3":"","名稱3":"","category":["餐飲"],"id":60069619,"pay_list":null,"pay_tool":null},{"index":181,"shop":"哈寶堡早餐元氣店","zone":"雲嘉南","city":"雲林縣","area":"北港鎮","market_address":"雲林縣北港鎮大同里文化路１３２號１樓","user":"陳俊卿","行業代號":"561115","market_name":["餐館、餐廳"],"行業代號1":"","名稱1":"","行業代號2":"","名稱2":"","行業代號3":"","名稱3":"","category":["餐飲"],"id":60069972,"pay_list":null,"pay_tool":null},{"index":182,"shop":"我家飲食店","zone":"雲嘉南","city":"雲林縣","area":"北港鎮","market_address":"雲林縣北港鎮華勝里１７鄰民政路５９號","user":"黃昭惠","行業代號":"561113","market_name":["麵店、小吃店"],"行業代號1":"","名稱1":"","行業代號2":"","名稱2":"","行業代號3":"","名稱3":"","category":["餐飲"],"id":60069999,"pay_list":null,"pay_tool":null},{"index":183,"shop":"永富商行","zone":"雲嘉南","city":"雲林縣","area":"北港鎮","market_address":"雲林縣北港鎮大同里文化路１４９號１樓","user":"黃嘉翎","行業代號":"561113","market_name":["麵店、小吃店"],"行業代號1":"","名稱1":"","行業代號2":"","名稱2":"","行業代號3":"","名稱3":"","category":["餐飲"],"id":60070365,"pay_list":null,"pay_tool":null},{"index":184,"shop":"民樂早餐店","zone":"雲嘉南","city":"雲林縣","area":"北港鎮","market_address":"雲林縣北港鎮華勝里民樂路１２７號１樓","user":"林芳蘭","行業代號":"561111","market_name":["早餐店"],"行業代號1":"","名稱1":"","行業代號2":"","名稱2":"","行業代號3":"","名稱3":"","category":["餐飲"],"id":60070405,"pay_list":null,"pay_tool":null},{"index":185,"shop":"東記豆漿店","zone":"雲嘉南","city":"雲林縣","area":"北港鎮","market_address":"雲林縣北港鎮仁安里文化路９１號１樓","user":"廖秀靜","行業代號":"561111","market_name":["早餐店"],"行業代號1":"","名稱1":"","行業代號2":"","名稱2":"","行業代號3":"","名稱3":"","category":["餐飲"],"id":60070483,"pay_list":null,"pay_tool":null},{"index":186,"shop":"柏瑋商號","zone":"雲嘉南","city":"雲林縣","area":"北港鎮","market_address":"雲林縣北港鎮仁安里中正路９８號１樓","user":"莊柏瑋","行業代號":"561115","market_name":["餐館、餐廳"],"行業代號1":"","名稱1":"","行業代號2":"","名稱2":"","行業代號3":"","名稱3":"","category":["餐飲"],"id":60071174,"pay_list":null,"pay_tool":null},{"index":187,"shop":"北港橋頭肉羹麵店","zone":"雲嘉南","city":"雲林縣","area":"北港鎮","market_address":"雲林縣北港鎮南安里０１３鄰光明路５５－１號１樓","user":"趙永義","行業代號":"561113","market_name":["麵店、小吃店"],"行業代號1":"","名稱1":"","行業代號2":"","名稱2":"","行業代號3":"","名稱3":"","category":["餐飲"],"id":60071199,"pay_list":null,"pay_tool":null},{"index":188,"shop":"禾興商行","zone":"雲嘉南","city":"雲林縣","area":"北港鎮","market_address":"雲林縣北港鎮東陽里東興街５０號","user":"黃淑真","行業代號":"563112","market_name":["民宿","咖啡館"],"行業代號1":"551013","名稱1":"民宿","行業代號2":"","名稱2":"","行業代號3":"","名稱3":"","category":["餐飲"],"id":60071230,"pay_list":null,"pay_tool":null},{"index":189,"shop":"心素齋商行","zone":"雲嘉南","city":"雲林縣","area":"北港鎮","market_address":"雲林縣北港鎮華勝里文仁路２３１號１樓","user":"許琁茵","行業代號":"561115","market_name":["未分類其他食品、飲料及菸草製品零售","麵店、小吃店","餐館、餐廳"],"行業代號1":"561113","名稱1":"麵店、小吃店","行業代號2":"472999","名稱2":"未分類其他食品、飲料及菸草製品零售","行業代號3":"","名稱3":"","category":["餐飲"],"id":60071241,"pay_list":null,"pay_tool":null},{"index":190,"shop":"六九生猛海鮮","zone":"雲嘉南","city":"雲林縣","area":"北港鎮","market_address":"雲林縣北港鎮新街里華勝路２９４號","user":"吳榮興","行業代號":"561115","market_name":["餐館、餐廳"],"行業代號1":"","名稱1":"","行業代號2":"","名稱2":"","行業代號3":"","名稱3":"","category":["餐飲"],"id":60071265,"pay_list":null,"pay_tool":null},{"index":191,"shop":"尚禾冷飲","zone":"雲嘉南","city":"雲林縣","area":"北港鎮","market_address":"雲林縣北港鎮華勝里公園路５０號","user":"黃博聲","行業代號":"563111","market_name":["冰果店、冷（熱）飲店"],"行業代號1":"","名稱1":"","行業代號2":"","名稱2":"","行業代號3":"","名稱3":"","category":["餐飲"],"id":60072058,"pay_list":null,"pay_tool":null},{"index":192,"shop":"星龍冰菓廠","zone":"雲嘉南","city":"雲林縣","area":"北港鎮","market_address":"雲林縣北港鎮新街里華勝路２５５號１樓","user":"許鈜智","行業代號":"563111","market_name":["冰果店、冷（熱）飲店"],"行業代號1":"","名稱1":"","行業代號2":"","名稱2":"","行業代號3":"","名稱3":"","category":["餐飲"],"id":60079944,"pay_list":null,"pay_tool":null},{"index":193,"shop":"莊記飲食店","zone":"雲嘉南","city":"雲林縣","area":"北港鎮","market_address":"雲林縣北港鎮華勝里民治路１巷１３號１樓","user":"莊翹蓉","行業代號":"561112","market_name":["便當、自助餐店"],"行業代號1":"","名稱1":"","行業代號2":"","名稱2":"","行業代號3":"","名稱3":"","category":["餐飲"],"id":60079949,"pay_list":null,"pay_tool":null},{"index":194,"shop":"魚家鄉自助餐","zone":"雲嘉南","city":"雲林縣","area":"北港鎮","market_address":"雲林縣北港鎮大同里義民路６９號","user":"李中良","行業代號":"561112","market_name":["便當、自助餐店"],"行業代號1":"","名稱1":"","行業代號2":"","名稱2":"","行業代號3":"","名稱3":"","category":["餐飲"],"id":60080336,"pay_list":null,"pay_tool":null},{"index":195,"shop":"金川坊","zone":"雲嘉南","city":"雲林縣","area":"北港鎮","market_address":"雲林縣北港鎮華勝里民享路２３號１樓","user":"許又文","行業代號":"561115","market_name":["餐館、餐廳"],"行業代號1":"","名稱1":"","行業代號2":"","名稱2":"","行業代號3":"","名稱3":"","category":["餐飲"],"id":60082347,"pay_list":null,"pay_tool":null},{"index":196,"shop":"禾家味自助餐餐飲館","zone":"雲嘉南","city":"雲林縣","area":"北港鎮","market_address":"雲林縣北港鎮華勝里民治路１９－６號","user":"吳宜蓁","行業代號":"561112","market_name":["便當、自助餐店"],"行業代號1":"","名稱1":"","行業代號2":"","名稱2":"","行業代號3":"","名稱3":"","category":["餐飲"],"id":60082360,"pay_list":null,"pay_tool":null},{"index":197,"shop":"上田拉麵","zone":"雲嘉南","city":"雲林縣","area":"北港鎮","market_address":"雲林縣北港鎮華勝里民樂路１２５號","user":"陳董壽","行業代號":"561115","market_name":["餐館、餐廳"],"行業代號1":"","名稱1":"","行業代號2":"","名稱2":"","行業代號3":"","名稱3":"","category":["餐飲"],"id":60082460,"pay_list":null,"pay_tool":null},{"index":198,"shop":"草湖商行","zone":"雲嘉南","city":"雲林縣","area":"北港鎮","market_address":"雲林縣北港鎮仁和里博愛路１１０號","user":"吳芊沛","行業代號":"561115","market_name":["餐館、餐廳"],"行業代號1":"","名稱1":"","行業代號2":"","名稱2":"","行業代號3":"","名稱3":"","category":["餐飲"],"id":60082475,"pay_list":null,"pay_tool":null},{"index":199,"shop":"山口商行","zone":"雲嘉南","city":"雲林縣","area":"北港鎮","market_address":"雲林縣北港鎮大同里大同路１１１號１樓","user":"黃莉婷","行業代號":"561115","market_name":["餐館、餐廳"],"行業代號1":"","名稱1":"","行業代號2":"","名稱2":"","行業代號3":"","名稱3":"","category":["餐飲"],"id":60082499,"pay_list":null,"pay_tool":null},{"index":200,"shop":"八九便當","zone":"雲嘉南","city":"雲林縣","area":"北港鎮","market_address":"雲林縣北港鎮新街里華勝路３７２號","user":"魏朝因","行業代號":"561112","market_name":["便當、自助餐店"],"行業代號1":"","名稱1":"","行業代號2":"","名稱2":"","行業代號3":"","名稱3":"","category":["餐飲"],"id":60082517,"pay_list":null,"pay_tool":null}]